Workbook

Sheet orders_raw
A1: order_id | B1: order_date | C1: customer_id | D1: customer_name | E1: email | F1: phone | G1: region | H1: sales_channel | I1: status | J1: sku | K1: product_name | L1: category | M1: unit_price_gbp | N1: quantity | O1: total_price | P1: currency | Q1: shipping_method | R1: payment_type | S1: notes
A2: ORD-100718 | B2: 29-Mar-2024 | C2: CUST-5524 | D2: Tara Walker | E2: tara.walker@example.com | F2: 07992 178 353 | G2: Poland | H2: In-Store | I2: aCncelled | J2: SKU-1125 | K2: Docking Station Pro | L2: ACCESSORIES | M2: 587.78 | N2: 2 | O2: €1,224.22 | P2: EUR | Q2: Next Day | R2: Card
A3: ORD-100720 | B3: 06.02.2023 | C3: CUST-5367 | D3: NINA SMITH | E3: Nina.Smith@Gmail.Com | F3: +44 718 938 4674 | G3: Spain | H3: Marketplace | I3: Shipped | J3: SKU-1050 | K3: Ultrabook 14 | L3: tSorage | N3: 2 | O3: $828,41 | P3: USD | Q3: Standard | R3: PayPal | S3: gift
A4: ORD-100128 | B4: 22/05/2023 20:20 | C4: CUST-5554 | D4: Igor Brown | E4: Igor.Brown@Shop.Io | F4: +44 623 652 7366 | G4: France | H4: Mobile App | I4: Paid | J4: SKU-1148 | K4: Portable HDD 2TB | L4: Computers | M4: 179.29 | N4: 2 | O4: GBP 373.42 | P4: GBP | Q4: Express | R4: PayPal | S4: urgent
A5: ORD-100513 | B5: 31-Aug-2024 | C5: CUST-5111 | D5: Marek Khan | E5: Marek.Khan@Company.Co.Uk | G5: UK | H5: Marketplace | I5: Refunded | J5: SKU-1139 | K5: Nvme Ssd 2Tb | L5: Smart Hoem | M5: 1704.12 | N5: 2 | O5: GBP 3,494.77 | P5: GBP | Q5: Next Day | R5: Cash | S5: delayed
A6: ORD-100653 | B6: 2025/04/03 | C6: CUST-5082 | D6: Qi Smith | E6: qi.smith@gmail.com | F6: +44 711 862 5723 | G6: Ireland | H6: In-Stroe | I6: Refunded | J6: SKU-1119 | K6: LED Light Strip | L6: Audio | M6: 417.04 | N6: 1 | O6: zł418.27 | P6: PLN | Q6: PICKUP | R6: Crad
A7: ORD-100336 | B7: 2025/09/25 | C7: CUST-5621 | D7: Sam Lopez | E7: sam.lopez@gmail.com | G7: Ireland | H7: Marketplace | I7: Refunded | J7: SKU-1000 | K7: Router XA5400 | L7: Audoi | M7: 1448.91 | N7: 1 | O7: EUR 1,436.62 | P7: EUR | Q7: Express | R7: Cash
A8: ORD-100898 | B8: Mar 01, 2023 08:59 | C8: CUST-5377 | D8: Gabe Garcia | E8: gabe.garcia@example.com | F8: +1-660-253-6456 | G8: UK | H8: Web | I8: Cancelled | J8: SKU-1019 | K8: LED Light Strip | L8: Computers | N8: 5 | O8: $2,894.38 | P8: USD | Q8: Standard | R8: GIFT CARD | S8: urgent
A9: ORD-100355 | B9: 2025/06/11 | C9: CUST-5077 | D9: Tara Khan | E9: tara.khan@company.co.uk | F9: +1-257-200-4796 | G9: Ireland | H9: Mobile App | I9: Refunded | J9: SKU-1048 | K9: External SSD 1BT | L9: NETWORKING | N9: 2 | O9: USD 1,966.67 | P9: USD | Q9: NEXT DAY | R9: Bank Transfer | S9: VIP
A10: ORD-100168 | B10: 45783 | C10: CUST-5101 | D10: Omar Khan | E10: Omar.Khan@Shop.Io | G10: Spain | H10: In-Store | I10: Shipped | J10: SKU-1022 | K10: Smart Plug 2-Pack | L10: Computers | N10: 2 | O10: zł1,057.28 | P10: PLN | Q10: Pickup | R10: Gift Card | S10: gift
A11: ORD-100597 | B11: 2025-09-27 | C11: CUST-5010 | D11: Hanna Kowalski | E11: hanna.kowalski@company.co.uk | F11: 4+4 993 638 5784 | G11: USA | H11: Web | I11: eRfunded | J11: SKU-1069 | K11: Portable HDD 2TB | L11: A udio | M11: 750.84 | N11: 1 | O11: GBP 784.00 | P11: GBP | Q11: Pcikup | R11: Gift Card | S11: VIP
A12: ORD-100101 | B12: 2025/02/25 | C12: CUST-5288 | D12: Lia Taylor | E12: Lia.Taylor@Example.Com | F12: +1-353-409-3163 | G12: Usa | H12: Web | I12: Refunded | J12: SKU-1039 | K12: LED Light Strip | L12: Monitors | M12: 1401.64 | N12: 2 | O12: $2,775.90 | P12: USD | Q12: Standard | R12: PayPal
A13: ORD-100977 | B13: 2025-02-28 | C13: CUST-5072 | D13: Wiktor Young | E13: witkor.young@yahoo.com | F13: +44 442 197 9030 | G13: France | H13: Marketplace | I13: Paid | J13: SKU-1024 | K13: 4 K Monitor 32 | L13: Accessories | M13: 1503.67 | N13: 3 | O13: EUR 4,648.50 | P13: EUR | Q13: Next Day | R13: Card | S13: VIP
A14: ORD-100457 | B14: 09-Jun-2024 | C14: CUST-5670 | D14: Ken Novak | E14: ken.novak@company.co.uk | F14: +44 434 357 1644 | G14: Spain | H14: Web | I14: Refunded | J14: SKU-1080 | K14: Bluetooth Speaker | L14: Monitors | M14: 856.9 | N14: 3 | O14: £2692,3 | P14: GBP | Q14: Pickup | R14: Bank Transfer | S14: VIP
A15: ORD-100414 | B15: 04/04/2024 18:09 | C15: CUST-5056 | D15: Zack Muller | E15: Zack.Muller@Shop.Io | F15: +1-882-256-7084 | G15: USA | H15: In-Store | I15: Refunded | J15: SKU-1130 | K15: Bluetooth Speaker | L15: COMPUETRS | N15: 1 | O15: GBP 1,674.83 | P15: GBP | Q15: Pickup | R15: PayPal | S15: delayed
A16: ORD-100264 | B16: 26-Feb-2024 | C16: CUST-5652 | D16: Omar Brown | E16: omar.brown@company.co.uk | G16: Spain | H16: Mobile App | I16: CANCELLED | J16: SKU-1076 | K16: Gaming Laptop 15 | L16: Audio | M16: 46.08 | N16: 1 | O16: $45,54 | P16: USD | Q16: Pickup | R16: Gfit Card | S16: urgent
A17: ORD-100848 | B17: 07/13/2025 | C17: CUST-5507 | D17: Vlad Williams | E17: vlad.williams@gmail.com | F17: +1-667-478-2689 | G17: UK | H17: Web | I17: Paid | J17: SKU-1108 | K17: SMART PLUG 2-PACK | L17: Audio | M17: 906.04 | N17: 2 | O17: USD 1,888.10 | P17: USD | Q17: Pickup | R17: aCrd
A18: ORD-100901 | B18: 25.12.2024 22:49 | C18: CUST-5289 | D18: PAULA MARTINEZ | E18: PAULA.MARTINEZ@EXAMPLE.COM | F18: +44 395 454 0136 | G18: Ireland | H18: In-Store | I18: Refunded | J18: SKU-1034 | K18: Wireless Mouse | L18: ACCESSORIES | M18: 768.63 | N18: 1 | O18: PLN 763.17 | P18: PLN | Q18: EXPRESS | R18: Bank Tarnsfer
A19: ORD-100046 | B19: 08.10.2023 | C19: CUST-5412 | D19: Ken Kowalczyk | E19: ken.kowlaczyk@shop.io | F19: +44 769 186 7502 | G19: France | H19: Marketplace | I19: Paid | J19: SKU-1093 | K19: Gaming Chair | L19: Storage | M19: 1497.04 | N19: 3 | O19: $4,347.91 | P19: USD | Q19: Picku p | R19: Bank Transfer
A20: ORD-100902 | B20: 11-Jul-2024 | C20: CUST-5118 | D20: Daria King | E20: daria.king@yahoo.com | F20: +1-440-780-7545 | G20: Ireland | H20: Web | I20: Paid | J20: SKU-1047 | K20: LED Light Strip | L20: Audio | N20: 1 | O20: $403,47 | P20: USD | Q20: Pickup | R20: Paypal | S20: VIP
A21: ORD-100881 | B21: 07/17/2023 20:01 | C21: CUST-5037 | D21: Omar Young | E21: omar.young@company.co.uk | F21: +1-468-684-6697 | G21: UK | H21: Marketplace | I21: Padi | J21: SKU-1060 | K21: Noise Cancelling Headphones | L21: AUDIO | N21: 1 | O21: USD 468.40 | P21: USD | Q21: Pickup | R21: PayPal | S21: urgent
A22: ORD-101119 | B22: 29-May-2023 | C22: CUST-5565 | D22: Yara Rossi | E22: yara.rossi@company.co.uk | F22: +1-605-656-6749 | G22: Poland | H22: Marketplace | I22: Refunded | J22: SKU-1103 | K22: External SSD 1TB | L22: Storaeg | N22: 1 | O22: USD 25.92 | P22: Usd | Q22: Next Day | R22: PayPal | S22: urgent
A23: ORD-100432 | B23: 45704 | C23: CUST-5334 | D23: Hanna Dubois | F23: +1-505-572-3052 | G23: UK | H23: Web | I23: Shipped | J23: SKU-1005 | K23: NVMe SSD 2TB | L23: COMPUTERS | M23: 614.07 | N23: 3 | O23: EUR 1,773.39 | P23: EUR | Q23: Standard | R23: Card
A24: ORD-100454 | B24: 28-Dec-2024 | C24: CUST-5345 | D24: Bella Davis | E24: Bella.Davis@Yahoo.Com | F24: +1-404-983-6248 | G24: Spain | H24: IN-STORE | I24: Refunded | J24: SKU-1035 | K24: DOCKING STATION PRO | L24: Storage | M24: 1559.25 | N24: 1 | O24: £1,547.35 | P24: GBP | Q24: Standard | R24: Bank Transfer | S24: urgent
A25: ORD-101063 | B25: 28-Aug-2025 | C25: CUST-5678 | D25: Yara Walker | F25: +44 583 359 1842 | G25: Usa | H25: Marketplace | I25: Shipped | J25: SKU-1012 | K25: Wireless Mouse | L25: Accessories | M25: 1094.59 | N25: 5 | O25: USD 5,283.39 | P25: USD | Q25: Pickup | R25: PayPal | S25: VIP
A26: ORD-100466 | B26: 03/04/2024 17:51 | C26: CUST-5407 | D26: Omar Taylor | E26: omar.taylor@company.co.uk | F26: +44 914 229 6422 | G26: France | H26: Mobile App | I26: Pendnig | J26: SKU-1077 | K26: External SSD 1TB | L26: Accessories | N26: 1 | O26: zł9.56 | P26: PLN | Q26: Standard | R26: Bank Transfer
A27: ORD-100009 | B27: 30-Aug-2023 | C27: CUST-5599 | D27: Marek Smith | E27: Marek.Smith@Outloo.kCom | G27: Spain | H27: Mobile App | I27: Pending | J27: SKU-1104 | K27: Docking Station Pro | L27: Storage | M27: 709.89 | O27: £718.45 | P27: GBP | Q27: NextD ay | R27: PayPal | S27: delayed
A28: ORD-100571 | B28: Sep 27, 2025 | C28: CUST-5287 | D28: PAULA NOVAK | E28: paula.novak@gmail.com | F28: 07535 426 253 | G28: Poland | H28: Marketplace | I28: Paid | J28: SKU-1060 | K28: Noise Cancelling Headphones | L28: AUDIO | M28: 680.14 | N28: 1 | O28: USD 691.78 | P28: USD | Q28: Pickup | R28: PayPal | S28: VIP
A29: ORD-100534 | B29: 01/24/2025 | C29: CUST-5569 | D29: ETHAN KOWALSKI | E29: ethan.kowalski@example.com | F29: +1-736-338-1390 | G29: Poland | H29: Marketplace | I29: Cancelled | J29: SKU-1089 | K29: Portable HDD 2TB | L29: Smart Home | N29: 2 | O29: $673,86 | P29: USD | Q29: Epxress | R29: PayPal | S29: urgent
A30: ORD-100113 | B30: Jan 12, 2023 06:29 | C30: CUST-5136 | D30: Adam Kowalczyk | E30: Adam.Kowalczyk@Outlook.Com | F30: +1-368-779-5228 | G30: Italy | H30: Marketplace | I30: PENDING | J30: SKU-1070 | K30: Ultraobok 14 | L30: Audio | N30: 2 | O30: GBP 1,006.25 | P30: GBP | Q30: Pickup | R30: Card | S30: gift
A31: ORD-100685 | B31: 07/04/2025 | C31: CUST-5187 | D31: Ethan Kowalski | E31: Ethan.Kowalski@Example.Com | F31: +44 167 297 1510 | G31: Franc e | H31: Mobile App | I31: Paid | J31: SKU-1024 | K31: 4 K Monitor 32 | L31: Accessories | M31: 1309.01 | N31: 1 | O31: EUR 1,372.09 | P31: EUR | Q31: iPckup | R31: Cash | S31: gift
A32: ORD-100526 | B32: May 08, 2025 | C32: CUST-5313 | D32: ACRLOS DUBOIS | E32: carlos.dubois@gmail.com | F32: +44 129 997 2553 | G32: ITALY | H32: Mobiel App | I32: Cancellde | J32: SKU-1115 | K32: 27in Monitor | L32: Storage | N32: 2 | O32: GBP 1,887.10 | P32: GBP | Q32: Pickup | R32: CARD | S32: VIP
A33: ORD-101011 | B33: 07/19/2024 | C33: CUST-5119 | D33: Ehtan Taylor | E33: ethan.taylor@outlook.com | G33: UK | H33: Mobile App | I33: Pending | J33: SKU-1031 | K33: USB-C Hub 7in1 | L33: Sotrage | M33: 1660.79 | N33: 1 | O33: USD 1,663.84 | P33: USD | Q33: Next Day | R33: Cash
A34: ORD-101147 | B34: 01/01/2025 | C34: CUST-5515 | D34: Sam Young | E34: sam.young@yahoo.com | G34: France | H34: Web | I34: Shipped | J34: SKU-1061 | K34: 27INM ONITOR | L34: Monitors | N34: 3 | O34: zł4,133.34 | P34: PLN | Q34: STANDARD | R34: GIFT CARD
A35: ORD-100587 | B35: 45753 11:38 | C35: CUST-5125 | D35: Lia Davis | E35: LIA.DAVIS@YAHOO.COM | F35: +44 272 275 2968 | G35: France | H35: Mobile App | I35: Refunded | J35: SKU-1129 | K35: Microphone USB | L35: COMPUTERS | M35: 1383.78 | N35: 5 | O35: zł7,064.26 | P35: PLN | Q35: PICKUP | R35: PayPal | S35: VIP
A36: ORD-100141 | B36: 2025/03/26 | C36: CUST-5204 | D36: Zack Brown | E36: ZACK.BROWN@YAHOO.COM | F36: +44 582 74 15155 | G36: USA | H36: In-Store | I36: Shipped | J36: SKU-1080 | K36: Bluetooth Speaker | L36: Monitors | O36: GBP 1,492.86 | P36: GBP | Q36: Pickup | R36: Card
A37: ORD-100835 | B37: 45092 | C37: CUST-5504 | D37: Qi Nowak | E37: qi.nowak@yahoo.com | F37: +44 483 783 2104 | G37: Spain | H37: In-Store | I37: Pending | J37: SKU-1105 | K37: Webcam 1080p | L37: Computers | N37: 5 | O37: EUR 8,282.75 | P37: EUR | Q37: Express | R37: Cash | S37: delayed
A38: ORD-100350 | B38: 25-Nov-2023 | C38: CUST-5385 | D38: Sam Rodriguez | E38: SAM.RODRIGUEZ@SHOP.IO | G38: USA | H38: Mobile App | I38: Refunded | J38: SKU-1004 | K38: Gaming Laptop 15 | L38: Accessories | M38: 571.4 | N38: 5 | O38: USD 2,716.52 | P38: USD | Q38: Pickup | R38: PAYPAL | S38: VIP
A39: ORD-100758 | B39: 45116 | C39: CUST-5085 | D39: Xenia Lopze | E39: xenia.lopez@yahoo.com | F39: +44 330 641 1288 | G39: Germany | H39: MOBILE APP | I39: Paid | J39: SKU-1097 | K39: Smartphone Case | L39: Netwroking | M39: 759.26 | N39: 2 | O39: PLN 1,535.25 | P39: PLN | Q39: Pickup | R39: GIFT CARD
A40: ORD-100894 | B40: 19.11.2023 | C40: CUST-5326 | D40: ADAM IWLLIAMS | E40: adam.wililams@shop.io | F40: +44 354 661 1215 | G40: USA | H40: Marketplace | I40: Shipped | J40: SKU-1064 | K40: Docking Station Pro | L40: Accessories | M40: 1456.79 | N40: 1 | O40: zł1,508.64 | P40: PLN | Q40: Pickup | R40: CARD
A41: ORD-100800 | B41: 2024-06-25 | C41: CUST-5595 | D41: Wiktor Taylo r | E41: wiktor.tyalor@yahoo.com | G41: Poland | H41: Markteplace | I41: Cancelled | J41: SKU-1123 | K41: NVMe SSD 2TB | L41: Computesr | N41: 2 | O41: GBP 3,652.46 | P41: GBP | Q41: Next Day | R41: Bank Transfer | S41: delayed
A42: ORD-100929 | B42: 45154 | C42: CUST-5459 | D42: Daria Dubois | G42: USA | H42: In-Store | I42: Pending | J42: SKU-1067 | K42: Docking Station Pro | L42: Netowrking | M42: 963.4 | N42: 2 | O42: EUR 2,013.13 | P42: EUR | Q42: Express | R42: Bank Transfer | S42: gift
A43: ORD-100374 | B43: 28.03.2024 03:00 | C43: CUST-5337 | D43: Ethan Walker | E43: Ethan.Walker@Company.Co.Uk | F43: 08034 271 186 | G43: Spain | H43: In-Store | I43: PAID | J43: SKU-1074 | K43: Ultrabook 14 | L43: Monitors | M43: 312.58 | N43: 1 | O43: zł326,28 | P43: PLN | Q43: Next Day | R43: Card | S43: gift
A44: ORD-100252 | B44: 31/03/2023 12:34 | C44: CUST-5588 | D44: Omar Nowak | E44: Omar.Nowak@Yahoo.Com | F44: +44 569 628 2971 | G44: UK | H44: Marketplace | I44: SHIPPED | J44: SKU-1051 | K44: 27in Monitor | L44: Networking | M44: 1443.74 | N44: 2 | O44: zł2,891.80 | P44: PLN | Q44: Pickup | R44: Card
A45: ORD-101088 | B45: Jan 18, 2023 | C45: CUST-5102 | D45: VLAD WALKER | E45: VLAD.WALKER@YAHOO.COM | F45: +1-269-860-3858 | G45: Ireland | H45: In-Store | I45: Pending | J45: SKU-1053 | K45: Noise Cancelling Headphones | L45: Audio | M45: 1594.99 | N45: 2 | O45: USD 3,219.89 | P45: USD | Q45: Standard | R45: BANK TRANSFER | S45: delayed
A46: ORD-100172 | B46: 20.03.2024 | C46: CUST-5039 | D46: Igor Dubois | E46: igor.dubois@company.co.uk | F46: +1-560-444-7313 | G46: USA | H46: Web | I46: Pending | J46: SKU-1101 | K46: EXTERNAL SSD 1TB | L46: ACCESSORIES | M46: 876.76 | N46: 3 | O46: €2,700.67 | P46: EUR | Q46: Pickup | R46: Card
A47: ORD-100572 | B47: 07-Jan-2025 20:53 | C47: CUST-5506 | D47: Rita Kowalczyk | E47: Rita.Kowalczyk@Example.Com | G47: Spain | H47: In-Store | I47: Paid | J47: SKU-1000 | K47: Router XA5400 | L47: Audoi | N47: 3 | O47: EUR 785.89 | P47: EUR | Q47: iPckup | R47: PAYPAL | S47: gift
A48: ORD-100980 | B48: 2024-03-14 | C48: CUST-5629 | D48: IQ JOHNSON | E48: qi.johnson@company.co.uk | G48: FRANCE | H48: Web | I48: Shipped | J48: SKU-1012 | K48: Wireless Mouse | L48: Accessories | N48: 1 | O48: £1281,77 | P48: GBP | Q48: Pickup | R48: Cash | S48: delayed
A49: ORD-101127 | B49: 05/15/2024 | C49: CUST-5228 | D49: Tara Muller | E49: Tara.Muller@Example.Com | F49: +44 646 773 2015 | G49: Italy | H49: Marketplace | I49: Shipped | J49: SKU-1030 | K49: Ultrabook 14 | L49: Smart Home | N49: 2 | O49: EUR 1,044.61 | P49: EUR | Q49: Express | R49: Bank Transfer | S49: VIP
A50: ORD-100488 | B50: 09/08/2025 | C50: CUST-5632 | D50: Omar Rodriguez | E50: omar.ordriguez@gmail.com | F50: 06488 432 200 | G50: Poland | H50: In-Store | I50: Refunded | J50: SKU-1028 | K50: Microphoen USB | L50: Monitors | M50: 1625.99 | O50: $3171,81 | P50: USD | Q50: Standar d | R50: Bank Transfer | S50: delayed
A51: ORD-100691 | B51: 2023-06-01 | C51: CUST-5077 | D51: Tara Khan | E51: tara.khan@company.co.uk | F51: +1-257-200-4796 | G51: Ireland | H51: Mobile App | I51: Piad | J51: SKU-1019 | K51: LED Light Strip | L51: Computers | O51: €383.45 | P51: EUR | Q51: Express | R51: PayaPl | S51: gift
A52: ORD-100578 | B52: 2024/01/05 | C52: CUST-5692 | D52: Bella Johnson | E52: bella.johnson@company.co.uk | F52: +44 975 742 8815 | G52: UK | H52: Marketplace | I52: Cancelled | J52: SKU-1032 | K52: External SSD 1TB | L52: Computers | M52: 825.82 | N52: 2 | P52: GBP | Q52: NextD ay | R52: Card | S52: VIP
A53: ORD-100716 | B53: 25-Sep-2025 | C53: CUST-5303 | D53: Yara Kowalski | E53: yara.kowalski@company.co.uk | F53: 03094 490 988 | G53: USA | H53: In-Store | I53: Shpiped | J53: SKU-1031 | K53: USB-C Hub 7in1 | L53: Sotrage | M53: 561.88 | N53: 2 | O53: €1154,69 | P53: EUR | Q53: NEXT DAY | R53: Cash | S53: gift
A54: ORD-100926 | B54: 10/04/2023 02:44 | C54: CUST-5213 | D54: Daria Nowak | E54: daria.nowak@gmail.com | F54: +1-636-524-8798 | G54: Spain | H54: Marketpalce | I54: Paid | J54: SKU-1055 | K54: Noise Cancelling Headphones | L54: Monitors | M54: 1281.06 | N54: 1 | O54: EUR 1,309.80 | P54: EUR | Q54: Express | R54: Bank Transfer | S54: urgent
A55: ORD-100216 | B55: 44938 22:40 | C55: CUST-5316 | D55: Qi Taylor | E55: QI.TAYLOR@EXAMPLE.COM | F55: +1-899-555-3305 | G55: Germany | H55: In-Store | I55: Refunded | J55: SKU-1131 | K55: LED Light Strip | L55: cAcessories | N55: 1 | O55: USD 880.77 | P55: USD | Q55: Express | R55: Gift Card | S55: gift
A56: ORD-100420 | B56: Jun 17, 2024 | C56: CUST-5108 | D56: Gabe Johnson | E56: gabe.johnson@yahoo.com | F56: 07698 742 663 | G56: UK | H56: In-Store | I56: Shipped | J56: SKU-1040 | K56: SMARTPHONE CAES | L56: COMPUTERS | N56: 1 | O56: USD 1,669.75 | P56: USD | Q56: Next Day | R56: Card | S56: urgent
A57: ORD-100467 | B57: 11/09/2024 08:19 | C57: CUST-5150 | D57: Gabe Davis | E57: gabe.davis@yahoo.com | F57: +1-410-237-3050 | G57: France | H57: Marketplace | I57: Refunded | J57: SKU-1067 | K57: Docking Station Pro | L57: Netowrking | N57: 5 | O57: GBP 3,438.17 | P57: GBP | Q57: Next Day | R57: CARD | S57: urgent
A58: ORD-100769 | B58: 15.05.2024 | C58: CUST-5468 | D58: Sam Tyalor | E58: sam.taylor@example.com | F58: +1-554-671-3714 | G58: Germany | H58: Mobile App | I58: PAID | J58: SKU-1007 | K58: Led Light Strip | L58: Networking | N58: 1 | O58: USD 514.92 | P58: USD | Q58: Next Day | R58: PayPal | S58: VIP
A59: ORD-100054 | B59: 2023/05/31 | C59: CUST-5554 | D59: Igor Brown | E59: Igor.Brown@Shop.Io | F59: +44 623 652 7366 | G59: France | H59: In-tSore | I59: Cancleled | J59: SKU-1137 | K59: Mechanical Keyboard | L59: Audio | M59: 1514.36 | N59: 1 | O59: GBP 1,472.35 | P59: GBP | Q59: Standard | R59: Bank Transfer | S59: gift
A60: ORD-101046 | B60: 2024/02/07 00:26 | C60: CUST-5481 | D60: Gabe Kowalski | E60: gabe.kowalski@shop.io | F60: +44 315 732 9340 | G60: USA | H60: Mobile App | I60: Refunded | J60: SKU-1037 | K60: 27in Monitor | L60: Accessories | M60: 1188.08 | N60: 3 | O60: €3,419.90 | P60: EUR | Q60: Express | R60: Cash | S60: gift
A61: ORD-100793 | B61: 2025-06-27 22:54 | C61: CUST-5234 | D61: IGOR YOUNG | E61: igor.young@shop.io | F61: +44 544 415 2143 | G61: Ireland | H61: Marketplace | I61: Refunded | J61: SKU-1134 | K61: Microphone USB | L61: Audio | N61: 2 | O61: £1,603.18 | P61: GBP | Q61: Express | R61: Cash
A62: ORD-100305 | B62: 45334 17:06 | C62: CUST-5432 | D62: Jade Garcia | E62: jade.garcia@shop.io | F62: +44 400 265 9097 | G62: Italy | H62: eWb | I62: CANCELLED | J62: SKU-1095 | K62: LED Light Strip | L62: Networking | M62: 1301.51 | O62: EUR 1,283.11 | P62: EUR | Q62: NEXT DAY | R62: Csah | S62: delayed
A63: ORD-100968 | B63: 2024/04/29 | C63: CUST-5012 | D63: MAREK DAVIS | E63: marek.davis@outlook.com | F63: +1-778-7095-912 | G63: USA | H63: Marketplace | I63: Pending | J63: SKU-1004 | K63: Gaming Laptop 15 | L63: Accessories | M63: 470.36 | N63: 1 | O63: PLN 453.59 | P63: PLN | Q63: P ickup | R63: Csah
A64: ORD-101114 | B64: 25.05.2025 07:15 | C64: CUST-5463 | D64: Daria Young | E64: daria.youn@gyahoo.com | F64: +1-216-978-3643 | G64: France | H64: In-tSore | I64: Pending | J64: SKU-1026 | K64: Portable DHD 2TB | L64: Audio | N64: 1 | O64: €313.45 | P64: EUR | Q64: Pickup | R64: Cash
A65: ORD-100845 | B65: 45650 | C65: CUST-5334 | D65: Hanna Dubois | F65: +1-505-572-3052 | G65: UK | H65: IN-STORE | I65: Shipped | J65: SKU-1034 | K65: Wireless Mouse | L65: ACCESSORIES | M65: 969.05 | N65: 2 | O65: USD 1,989.76 | P65: USD | Q65: NextD ay | R65: Cash
A66: ORD-100422 | B66: 29.06.2023 | C66: CUST-5555 | D66: Zakc Kowalczyk | G66: USA | H66: Marketplace | I66: PENDING | J66: SKU-1117 | K66: Noise Cancelling Headphones | L66: STORAGE | M66: 498.24 | N66: 2 | O66: €951,33 | P66: EUR | Q66: Next Day | R66: Cash
A67: ORD-100585 | B67: 2024/09/27 10:48 | C67: CUST-5443 | D67: Paula Khan | E67: paula.khan@yahoo.com | F67: +1-940-852-5350 | G67: Germany | H67: Marketplace | I67: Shipped | J67: SKU-1081 | K67: USB-C Hub 7in1 | L67: Networking | M67: 803.41 | N67: 1 | O67: EUR 783.99 | P67: EUR | Q67: Standard | R67: BANK TRANSFER | S67: VIP
A68: ORD-100562 | B68: 24-Jan-2025 | C68: CUST-5539 | D68: Carlos Davis | E68: carlos.davis@outlook.com | F68: +44 562 718 2508 | G68: IRELAND | H68: Marketplace | I68: Cancelled | J68: SKU-1054 | K68: LED Light Strip | L68: Accessories | M68: 97.3 | N68: 1 | O68: zł100.41 | P68: PLN | Q68: Pickup | R68: Card | S68: urgent
A69: ORD-100447 | B69: 23.01.2023 | C69: CUST-5139 | D69: Sam Novak | E69: sam.novak@outlook.com | F69: 05024 155 527 | G69: Poland | H69: Marketplace | I69: Refunded | J69: SKU-1044 | K69: Portable HDD 2TB | L69: COPMUTERS | M69: 1210.57 | O69: USD 3,571.82 | P69: USD | Q69: Express | R69: Cash
A70: ORD-100109 | B70: 2025-06-08 | C70: CUST-5353 | D70: Gabe Nowak | E70: gabe.nowak@company.co.uk | F70: 01162 776 241 | G70: POLAND | H70: In-Store | I70: Pedning | J70: SKU-1018 | K70: Smart Plug 2-Pack | L70: Smart Home | M70: 1200.31 | N70: 2 | O70: zł2,316.50 | P70: PLN | Q70: STANDARD | R70: Bank Transfer
A71: ORD-100040 | B71: 2023-07-24 | C71: CUST-5621 | D71: Sam Lopez | E71: sam.lopez@gmail.com | G71: Ireland | H71: Mobile App | I71: Refunded | J71: SKU-1096 | K71: 27In Monitor | L71: mSart Home | M71: 208.44 | N71: 1 | O71: EUR 217.72 | P71: EUR | Q71: Next Day | R71: Cash | S71: delayed
A72: ORD-101098 | B72: 2024-05-08 | C72: CUST-5406 | D72: MAREK KOWALCZYK | E72: Marek.Koawlczyk@Outlook.Com | F72: +446 77 131 6962 | G72: France | H72: Web | I72: Paid | J72: SKU-1107 | K72: xEternal SSD 1TB | L72: ACCESSORIES | M72: 1480.78 | N72: 3 | O72: EUR 4,581.21 | P72: EUR | Q72: STANDARD | R72: Bank Transfer | S72: VIP
A73: ORD-100489 | B73: 14-Jul-2024 | C73: CUST-5472 | D73: ETHAN KING | E73: ethan.king@company.co.uk | F73: 06471 730 487 | G73: Itlay | H73: Mobile App | I73: CANCELELD | J73: SKU-1112 | K73: Wireless Mouse | L73: Monitors | N73: 1 | O73: GBP 1,214.87 | P73: GBP | Q73: Express | R73: Paypal | S73: gift
A74: ORD-100997 | B74: 08-May-2024 | C74: CUST-5106 | D74: JADE KOWALCZYK | E74: jade.kowalczyk@example.com | F74: +1-394-365-8783 | G74: Poland | H74: WEB | I74: Refunded | J74: SKU-1137 | K74: Mechanical Keyboard | L74: Audio | M74: 1424.97 | N74: 2 | P74: GBP | Q74: EXPRESS | R74: Cash | S74: urgent
A75: ORD-100407 | B75: 45125 | C75: CUST-5319 | D75: Vlad Dubois | E75: vlad.dubois@yahoo.com | F75: 05630 844 984 | G75: Italy | H75: Marketplace | I75: Paid | J75: SKU-1112 | K75: Wireless Mouse | L75: Monitors | M75: 1281.05 | P75: EUR | Q75: Next Day | R75: Card
A76: ORD-101133 | B76: 2025/09/26 10:21 | C76: CUST-5027 | D76: Daria Kowalski | E76: daria.kowalski@outlook.com | F76: 00052 787 001 | G76: USA | H76: Marketplace | I76: Paid | J76: SKU-1106 | K76: Wireless Mouse | L76: Smart Home | O76: zł1,715.53 | P76: PLN | Q76: NEXT DAY | R76: Bank Trasnfer | S76: VIP
A77: ORD-100472 | B77: Aug 03, 2024 | C77: CUST-5283 | D77: Zack Johnson | E77: zack.johnson@example.com | F77: +44 472 91 68833 | G77: Ireland | H77: In-Store | I77: Refunded | J77: SKU-1133 | K77: Smartphone Case | L77: Smart Home | M77: 1601.92 | N77: 5 | O77: PLN 7,952.88 | P77: PLN | Q77: Express | R77: Cash
A78: ORD-101065 | B78: Dec 15, 2023 | C78: CUST-5412 | D78: Ken Kowalczyk | E78: ken.kowlaczyk@shop.io | F78: +44 769 186 7502 | G78: France | H78: Mobile App | I78: Cancelled | J78: SKU-1093 | K78: Gaming Chair | L78: Storage | M78: 586.49 | N78: 1 | O78: EUR 607.12 | P78: EUR | Q78: Pickup | R78: Cash | S78: gift
A79: ORD-100810 | B79: 03/10/2024 | C79: CUST-5483 | D79: Gabe King | F79: +1-470-785-6667 | G79: UK | H79: Marketplace | I79: Pending | J79: SKU-1014 | K79: 4K MONITOR 32 | L79: Accessories | M79: 459.16 | N79: 5 | O79: £2,272.24 | P79: GBP | Q79: Express | R79: Gift Card
A80: ORD-100594 | B80: 2025-03-13 22:52 | C80: CUST-5317 | D80: Marek Garcia | E80: marek.garcia@shop.io | G80: USA | H80: Web | I80: Shipped | J80: SKU-1120 | K80: WIRELESS MOUSE | L80: Computers | M80: 1227.98 | N80: 1 | O80: zł1,258.22 | P80: PLN | Q80: Express | R80: PAYPAL
A81: ORD-100851 | B81: 2023/05/21 | C81: CUST-5679 | D81: Lia Taylor | E81: lia.taylor@shop.io | F81: 05486 657 615 | G81: Frnace | H81: Web | I81: PIAD | J81: SKU-1018 | K81: Smart Plug 2-Pack | L81: Smart Home | N81: 1 | O81: EUR 241.20 | P81: EUR | Q81: Standard | R81: Bank Tranfser
A82: ORD-100712 | B82: 2023/06/17 | C82: CUST-5190 | D82: Daria Johnson | E82: daria.johnson@shop.io | F82: 08698 629 534 | G82: Poland | H82: Mobile App | I82: Cancelled | J82: SKU-1047 | K82: LED Light Strip | L82: Audio | M82: 173.67 | N82: 2 | O82: £352.66 | P82: GBP | Q82: Next Day | R82: Card
A83: ORD-100179 | B83: 05-Aug-2025 | C83: CUST-5458 | D83: Rita Davis | E83: rita.davis@yahoo.com | F83: 09977 414 309 | G83: Germany | H83: In-tSore | I83: Refunded | J83: SKU-1086 | K83: Gaming Laptop 15 | L83: Monitors | N83: 2 | O83: USD 1,786.09 | P83: USD | Q83: Standard | R83: Bank Transfer | S83: VIP
A84: ORD-100478 | B84: 15-Aug-2023 | C84: CUST-5155 | D84: Uma Walker | E84: UMA.WALKER@YAHOO.COM | F84: +44 425 556 7902 | G84: Poland | H84: Mobile App | I84: Pending | J84: SKU-1117 | K84: Noise Cancelling Headphones | L84: STORAGE | N84: 1 | O84: GBP 365.68 | P84: GBP | Q84: Standard | R84: Paypal | S84: delayed
A85: ORD-100204 | B85: 2023/01/29 | C85: CUST-5102 | D85: VLAD WALKER | E85: VLAD.WALKER@YAHOO.COM | F85: +1-269-860-3858 | G85: Ireland | H85: In-Store | I85: Paid | J85: SKU-1037 | K85: 27in Monitor | L85: Accessories | M85: 680.35 | N85: 3 | O85: PLN 1,995.97 | P85: PLN | Q85: Standard | R85: Cash | S85: gift
A86: ORD-100705 | B86: 45527 | C86: CUST-5476 | D86: Wiktor Lee | E86: wiktor.lee@outlook.com | F86: +1-334-533-7659 | G86: POLAND | H86: Mobile App | I86: Paid | J86: SKU-1016 | K86: Docking Station Pro | L86: COMPUTERS | N86: 5 | O86: zł720,2 | P86: PLN | Q86: Next Day | R86: Bank Transfer | S86: VIP
A87: ORD-100306 | B87: Jun 05, 2025 01:58 | C87: CUST-5663 | D87: Wiktor Young | F87: +1-357-826-5200 | G87: UK | H87: Mobile App | I87: Shipped | J87: SKU-1069 | K87: Portable HDD 2TB | L87: A udio | N87: 5 | O87: USD 5,305.94 | P87: USD | Q87: Next Day | R87: PayPal | S87: gift
A88: ORD-100101 | B88: 2025/02/25 | C88: CUST-5288 | D88: Lia Taylor | E88: Lia.Taylor@Example.Com | F88: +1-353-409-3163 | G88: Usa | H88: Web | I88: Refunded | J88: SKU-1039 | K88: LED Light Strip | L88: Monitors | M88: 1401.64 | N88: 2 | O88: $2,775.90 | P88: USD | Q88: Standard | R88: PayPal
A89: ORD-100408 | B89: 45363 | C89: CUST-5303 | D89: Yara Kowalski | E89: yara.kowalski@company.co.uk | F89: 03094 490 988 | G89: USA | H89: In-Store | I89: Shipped | J89: SKU-1064 | K89: Docking Station Pro | L89: Accessories | N89: 3 | O89: GBP 1,603.31 | P89: GBP | Q89: Next Day | R89: Crad
A90: ORD-100609 | B90: 09/28/2023 | C90: CUST-5294 | D90: Ken Young | E90: ken.young@yahoo.com | G90: Spain | H90: In-Store | I90: Refunded | J90: SKU-1132 | K90: Smartphone Case | L90: Accessories | N90: 5 | O90: PLN 2,977.05 | P90: PLN | Q90: Next Day | R90: Bank Transfer
A91: ORD-100870 | B91: 14.04.2025 21:16 | C91: CUST-5619 | D91: Carlos Kowalski | E91: carlos.kowalski@company.co.uk | F91: +1-532-833-9358 | G91: UK | H91: WEB | I91: Refunded | J91: SKU-1112 | K91: Wireless Mouse | L91: Monitors | N91: 2 | O91: EUR 125.24 | P91: EUR | Q91: Pickup | R91: Card
A92: ORD-100828 | B92: 10/09/2025 | C92: CUST-5238 | D92: Qi Kowalski | F92: +44 577 934 5738 | G92: Irealnd | H92: WEB | I92: Pending | J92: SKU-1059 | K92: NOISE CANCELLING HEADPHONES | L92: Monitors | M92: 442.34 | N92: 2 | P92: PLN | Q92: Standard | R92: Cash | S92: VIP
A93: ORD-100097 | B93: 21/09/2023 14:19 | C93: CUST-5356 | D93: Vlad Taylor | E93: Vlad.Taylor@Example.Com | F93: 07398 177 564 | G93: IRELAND | H93: Web | I93: Paid | J93: SKU-1051 | K93: 27in Monitor | L93: Networking | M93: 1745.48 | N93: 3 | O93: PLN 5,249.89 | P93: PLN | Q93: Express | R93: PayPal | S93: gift
A94: ORD-100171 | B94: 01/08/2023 | C94: CUST-5360 | D94: Hanna Martinez | E94: hanna.martinez@example.com | F94: 09286 713 486 | G94: Italy | H94: Mobile App | I94: Cancelled | J94: SKU-1066 | K94: Microphone USB | L94: Accessories | M94: 1489.5 | N94: 5 | O94: PLN 7,259.76 | P94: PLN | Q94: Express | R94: Bank Transfer
A95: ORD-100140 | B95: 45519 | C95: CUST-5407 | D95: Omar Taylor | E95: omar.taylor@company.co.uk | F95: +44 914 229 6422 | G95: France | H95: In-tSore | I95: Shipped | J95: SKU-1076 | K95: Gaming Laptop 15 | L95: Audio | M95: 875.66 | N95: 1 | O95: USD 837.49 | P95: USD | Q95: xEpress | R95: Gift Card | S95: delayed
A96: ORD-100186 | B96: 45205 08:16 | C96: CUST-5272 | D96: Vlad Garcia | E96: vlad.garcia@outlook.com | F96: +44 131 853 4404 | G96: USA | H96: eWb | I96: Cancelled | J96: SKU-1132 | K96: Smartphone Case | L96: Accessories | M96: 1189.45 | N96: 1 | O96: £1,167.94 | P96: GBP | Q96: Express | R96: Cash | S96: VIP
A97: ORD-100017 | B97: 12/25/2023 04:38 | C97: CUST-5584 | D97: Gaeb Williams | E97: gabe.williams@outlook.com | F97: +1-426-744-1173 | G97: USA | H97: Web | I97: Shipped | J97: SKU-1045 | K97: 27i nMonitor | L97: MONITORS | M97: 921.88 | N97: 1 | O97: GBP 954.75 | P97: GBP | Q97: Pickup | R97: GIFT CARD
A98: ORD-100053 | B98: 14-Sep-2025 22:27 | C98: CUST-5690 | D98: Adam Dbuois | E98: adam.duboi@sshop.io | G98: Germany | H98: In-Store | I98: PAID | J98: SKU-1063 | K98: Gaming Laptop 15 | L98: NETWORKING | N98: 1 | O98: £48,96 | P98: GBP | Q98: Express | R98: Card
A99: ORD-100224 | B99: 2024-05-31 | C99: CUST-5396 | D99: Bella Dubois | E99: BELLA.DUBOIS@EXAMPLE.COM | F99: 03517 732 814 | G99: UK | H99: Mobile App | I99: CANCELLED | J99: SKU-1003 | K99: USB-C Hub 7in1 | L99: Monitors | N99: 1 | O99: GBP 1,260.13 | P99: GBP | Q99: STANDARD | R99: Paypal | S99: gift
A100: ORD-101060 | B100: 01-Jun-2025 20:26 | C100: CUST-5151 | D100: Paula Khan | E100: Paula.Khan@Example.Com | F100: +44 082 113 2027 | G100: Spain | H100: Mobile App | I100: Pending | J100: SKU-1038 | K100: Webcam 1080P | L100: Stroage | M100: 723.64 | N100: 2 | O100: $1,432.34 | P100: USD | Q100: Stadnard | R100: Card | S100: urgent
...

Sheet customers_raw
A1: customer_id | B1: full_name | C1: email | D1: phone | E1: region | F1: created_at | G1: marketing_opt_in
A2: CUST-5191 | B2: Gabe Smith | C2: gabe.smith@example.com | D2: +1-762-417-3146 | E2: Italy | F2: 12/15/2023 05:03 | G2: No
A3: CUST-5682 | B3: Gabe King | C3: gabe.king@shop.io | D3: 04047 092 759 | E3: France | F3: 2024-10-23 | G3: Yes
A4: CUST-5318 | B4: Wiktor Williams | C4: wiktor.williams@example.com | D4: +44 150 027 7689 | E4: Poland | F4: 2025-09-25 | G4: no
A5: CUST-5562 | B5: Bella Dubois | C5: bella.dubois@shop.io | D5: +44 730 574 7856 | E5: USA | F5: Dec 22, 2022 20:11 | G5: No
A6: CUST-5623 | B6: JADE DAVIS | C6: jade.davis@yahoo.com | D6: +1-673-239-2500 | E6: Poland | F6: 45108 | G6: yes
A7: CUST-5399 | B7: Igor Kowalczyk | C7: igor.kowalczyk@example.com | D7: 01487 030 535 | E7: Poland | F7: 12/21/2023 | G7: No
A8: CUST-5657 | B8: Igor Young | C8: IGOR.YOUNG@YAHOO.COM | D8: +44 063 475 2008 | E8: Uk | F8: 05/16/2025
A9: CUST-5677 | B9: Jade Garcia | C9: jade.garcia@company.co.uk | D9: +1-795-856-9827 | E9: UK | F9: 45606 | G9: no
A10: CUST-5232 | B10: Ethan Taylor | C10: ethan.taylor@companyc.o.uk | D10: 05856 965 499 | E10: RFANCE | F10: 02/01/2023 | G10: No
A11: CUST-5544 | B11: Marek Novak | C11: marek.novak@yahoo.com | D11: +1-394-664-9948 | E11: Ireland | F11: 17.01.2022 | G11: Yes
A12: CUST-5435 | B12: Fiona Davis | C12: fiona.davis@company.co.uk | D12: +1-731-971-2240 | E12: Ireland | F12: 13-Mar-2025 17:45
A13: CUST-5057 | B13: Carlos Lee | C13: carlos.lee@company.co.uk | D13: 05360 848 529 | E13: UK | F13: 13-Jun-2022 12:23 | G13: Y
A14: CUST-5612 | B14: Gabe Martinez | C14: GABE.MARTINEZ@SHOP.IO | D14: +1-983-639-7989 | E14: GERMANY | F14: 2025-02-21 | G14: TRUE
A15: CUST-5670 | B15: Ken Novak | C15: ken.novak@company.co.uk | D15: +44 434 357 1644 | E15: Spain | F15: Dec 15, 2024 | G15: yes
A16: CUST-5229 | B16: NINA DAVIS | C16: nina.davis@outlook.com | D16: +44 925 750 9054 | E16: UK | F16: 2022-02-18
A17: CUST-5188 | B17: Xenia Kowalczyk | C17: xenia.kowalczyk@gmail.com | E17: Poland | F17: 2025/06/10 07:46
A18: CUST-5168 | B18: Yara Davis | C18: Yara.Davis@Example.Com | D18: +44 656 840 8328 | E18: ITALY | F18: 44998 09:58
A19: CUST-5223 | B19: IGOR BROWN | C19: igor.brown@outlook.com | D19: +1-778-262-8429 | E19: Ireland | F19: 21-Mar-2025
A20: CUST-5278 | B20: Vla dRodriguez | C20: Vlad.Rodriguez@Example.Com | D20: +1-832-202-5314 | E20: GERMANY | F20: 27/08/2022 | G20: N
A21: CUST-5351 | B21: UMA LOPEZ | C21: Uma.Lopez@Company.Co.Uk | D21: 04945 481 349 | E21: Ireland | F21: 25/04/2024 02:59 | G21: TRUE
A22: CUST-5236 | B22: Uma Lee | C22: uma.lee@gmail.ocm | E22: Spain | F22: 19.04.2025 | G22: yes
A23: CUST-5249 | B23: Yara Brown | C23: yara.brown@company.co.uk | D23: +44 865 848 6086 | E23: POLADN | F23: 02.01.2023
A24: CUST-5358 | B24: Hanna Kowalczyk | C24: hanna.kowalczyk@example.com | D24: 06746 868 344 | E24: Spain | F24: 2025-01-27 | G24: No
A25: CUST-5148 | B25: Yara Nowak | C25: yara.nowak@yahoo.com | D25: 06750 972 902 | E25: Fracne | F25: 45449 | G25: No
A26: CUST-5543 | B26: Wiktor Young | C26: wiktor.young@cmopany.co.uk | D26: +1-433-470-2895 | E26: Germany | F26: Jul 23, 2023 | G26: yes
A27: CUST-5272 | B27: Vlad Garcia | C27: vlad.garcia@outlook.com | D27: +44 131 853 4404 | E27: USA | F27: Aug 27, 2025 16:18 | G27: yes
A28: CUST-5698 | B28: Ethan Novak | C28: ethan.novak@gmail.com | D28: +1-546-331-6613 | E28: Itlay | F28: 07.10.2022 | G28: yes
A29: CUST-5417 | B29: Igor Muller | C29: igor.muller@yahoo.com | D29: 04470 275 125 | E29: France | F29: 04/04/2025 | G29: TRUE
A30: CUST-5650 | B30: Sam Novak | C30: sam.novak@gmail.com | D30: +1-890-678-7089 | E30: USA | F30: 06/03/2025 | G30: Yes
A31: CUST-5514 | B31: Jade Davis | C31: JADE.DAVIS@COMPANY.CO.UK | D31: +44 784 108 3844 | E31: Germany | F31: 2025/07/09 19:03 | G31: no
A32: CUST-5098 | B32: Zack Dubois | C32: zack.dubois@yahoo.com | D32: 02567 462 522 | E32: Spain | F32: 44656 | G32: no
A33: CUST-5061 | B33: Adam Garcia | C33: adam.garcia@outlook.com | D33: +44 136 191 8851 | E33: Ireland | F33: 2022/01/11 | G33: Yes
A34: CUST-5513 | B34: Ken Williams | C34: ken.williams@company.co.uk | D34: +44 346 831 3679 | E34: Spain | F34: 19.11.2024 | G34: yes
A35: CUST-5470 | B35: Ethan Muller | C35: ETHAN.MULLER@OUTLOOK.COM | D35: 01186 574 539 | E35: Ireland | F35: 23-Oct-2023 04:30
A36: CUST-5099 | B36: Marek King | C36: marek.king@gmail.com | D36: +44 662 605 1552 | E36: USA | F36: 03-Jan-2024 02:57 | G36: TRUE
A37: CUST-5009 | B37: Marek Davis | C37: marek.davis@gmail.com | D37: +44 094 948 0914 | E37: Uk | F37: 07/12/2024 | G37: FALSE
A38: CUST-5283 | B38: Zack Johnson | C38: zack.johnson@example.com | D38: +44 472 91 68833 | E38: Ireland | F38: 2022-07-19 | G38: yes
A39: CUST-5221 | B39: Jade Nowak | C39: JADE.NOWAK@EXAPMLE.COM | D39: 04361 416 433 | E39: Poland | F39: 03-Mar-2025 | G39: No
A40: CUST-5547 | B40: Carlos Taylor | C40: carlos.taylor@example.com | D40: +44 751 427 4575 | E40: Poland | F40: 2023-09-05 | G40: no
A41: CUST-5482 | B41: Lia Taylor | C41: lia.taylor@yahoo.com | E41: Italy | F41: 45041 | G41: Yes
A42: CUST-5300 | B42: XENIA DUBOIS | C42: xenia.dubois@shop.io | D42: +44 160 196 9783 | E42: Germany | F42: 05-Nov-2022 | G42: N
A43: CUST-5110 | B43: Omar Williams | D43: +1-482-570-3500 | E43: Poland | F43: 17-Mar-2024 15:01 | G43: No
A44: CUST-5411 | B44: Ken Khan | C44: ken.khan@shop.io | D44: 03118 254 128 | E44: UK | F44: 24-May-2024 | G44: FALSE
A45: CUST-5256 | B45: Omar Smith | C45: OMAR.SMITH@SHOP.IO | D45: 09237 347 689 | E45: France | F45: 10/18/2024 | G45: Yes
A46: CUST-5640 | B46: Nina Rodriguez | C46: nina.rodriguez@shop.io | D46: +1-589-270-2543 | E46: Poland | F46: 26/07/2025 | G46: FALSE
A47: CUST-5364 | B47: Lia Nvoak | C47: lia.novak@shop.io | D47: 05794 434 277 | E47: Germany | F47: 2025/03/07 | G47: Y
A48: CUST-5611 | B48: VLAD JOHNSON | C48: vlad.johnson@shop.io | D48: 08143 522 575 | E48: USA | F48: 45517 | G48: Yes
A49: CUST-5548 | B49: Ken Gracia | C49: ken.garcia@gmail.com | D49: 06203 344 528 | E49: Poland | F49: 05/05/2023 | G49: TRUE
A50: CUST-5545 | B50: LIA TAYLOR | C50: Lia.Taylor@Company.Co.Uk | D50: 08601 051 272 | E50: USA | F50: 08.06.2022 | G50: TRUE
A51: CUST-5013 | B51: Lia Lee | C51: lia.lee@example.com | D51: +1-379-313-5831 | E51: Italy | F51: 45095 | G51: No
A52: CUST-5327 | B52: Ken Dubois | C52: ken.dubois@shop.io | D52: +1-566-455-1513 | E52: Italy | F52: Jul 22, 2024 | G52: TRUE
A53: CUST-5467 | B53: DARIA YOUNG | C53: daria.young@yahoo.com | D53: +1-325-930-3380 | E53: Poland | F53: 23/09/2024 | G53: Yes
A54: CUST-5632 | B54: Omar Rodriguez | C54: omar.ordriguez@gmail.com | D54: 06488 432 200 | E54: Poland | F54: 2024/08/15
A55: CUST-5321 | B55: Paul aMartinez | C55: paula.martinez@yahoo.com | E55: USA | F55: 45157 | G55: N
A56: CUST-5592 | B56: Hanna Kowalski | C56: hanna.kowalski@yahoo.com | D56: +1-800-868-8593 | E56: Spain | F56: 24/08/2025 | G56: yes
A57: CUST-5639 | B57: Omar Kowalski | C57: omar.kowalski@company.co.ku | D57: +44 227 077 6598 | E57: UK | F57: 2022/08/04 | G57: Yes
A58: CUST-5281 | B58: Omar Lee | C58: omar.lee@gmail.com | D58: +44 167 561 9925 | E58: USA | F58: 45097 | G58: TRUE
A59: CUST-5484 | B59: Zack Rodriguez | D59: 08844 823 181 | E59: Usa | F59: 45703 19:20 | G59: Y
A60: CUST-5242 | B60: IGOR YOUNG | C60: igor.young@shop.io | D60: 05303 791 915 | E60: Germany | F60: Feb 28, 2023 | G60: FALSE
A61: CUST-5553 | B61: W iktor Novak | C61: Wiktor.Novak@Company.Co.Uk | D61: +1-206-888-5222 | E61: USA | F61: Apr 19, 2024
A62: CUST-5420 | B62: Bella Williams | C62: bella.williams@example.com | D62: 05197 562 364 | E62: Uk | F62: 05/28/2023 | G62: yes
A63: CUST-5681 | B63: Bella Johnson | C63: bella.johnson@yahoo.com | D63: +44 449 583 1936 | E63: USA | F63: 45040 | G63: FALSE
A64: CUST-5423 | B64: Rita Rossi | C64: rita.rossi@example.com | D64: 00149 114 624 | E64: Ireland | F64: 03.03.2022 | G64: No
A65: CUST-5251 | B65: Adam Lopez | C65: adam.lopez@yahoo.com | E65: GERMANY | F65: 10/02/2025
A66: CUST-5600 | B66: Nina Lee | C66: nina.lee@example.co m | D66: 08397 657 596 | E66: Spain | F66: 06-Mar-2025 | G66: TRUE
A67: CUST-5350 | B67: MarekK owalczyk | C67: marek.kowalczyk@yahoo.com | D67: 03635 092 182 | E67: Uk | F67: 2022-12-03 01:23 | G67: Yes
A68: CUST-5401 | B68: Vlad Rodriguez | C68: vla.drodriguez@company.co.uk | D68: 08752 123 882 | E68: Ireland | F68: 04.02.2024 | G68: yes
A69: CUST-5614 | B69: Tara Young | C69: TARA.YOUNG@SHOP.IO | D69: 01277 495 895 | E69: FRANCE | F69: Dec 01, 2024 | G69: no
A70: CUST-5489 | B70: Bella Lee | C70: bella.lee@company.co.uk | D70: +1-773-226-5983 | E70: Poland | F70: Jan 07, 2022 | G70: No
A71: CUST-5060 | B71: Hanna Dubois | C71: Hanna.Dubois@Shop.Io | D71: 1+-202-273-1486 | E71: UK | F71: 04-Oct-2024 00:42 | G71: TRUE
A72: CUST-5564 | B72: Zack Novak | C72: zack.novak@company.co.uk | D72: 06771 575 950 | E72: Germany | F72: 45174 | G72: Y
A73: CUST-5452 | B73: Jade Kowalczyk | C73: JADE.KOWALCZYK@YAHOO.COM | D73: +1-733-987-9704 | E73: POLAND | F73: 02/16/2023 | G73: FALSE
A74: CUST-5193 | B74: Adam Dubois | C74: adam.dubois@yahoo.com | D74: +44 513 930 7632 | E74: Poland | F74: 08/25/2022 | G74: Yes
A75: CUST-5328 | B75: Daria Garcia | C75: Daria.Garcia@Company.Co.Uk | D75: +1-716-956-7526 | E75: Spain | F75: 11-May-2023 | G75: no
A76: CUST-5538 | B76: Adam Walker | C76: adam.wlaker@shop.io | D76: +44 379 892 8470 | E76: GERMANY | F76: 01-Sep-2024
A77: CUST-5057 | B77: Carlos Lee | C77: carlos.lee@company.co.uk | D77: 05360 848 529 | E77: UK | F77: 13-Jun-2022 12:23 | G77: Y
A78: CUST-5668 | B78: Bella Kowalczyk | C78: bella.kowalczyk@outlook.com | D78: 00700 568 132 | E78: Itayl | F78: 13-Sep-2025 | G78: N
A79: CUST-5625 | B79: Uma Kowalski | C79: uma.kowalski@gmail.com | D79: 06657 194 796 | E79: Italy | F79: 45867 | G79: Y
A80: CUST-5392 | B80: Bella Dubois | C80: bella.dubois@yahoo.com | D80: +1-452-661-6471 | E80: USA | F80: Aug 25, 2023 | G80: FALSE
A81: CUST-5142 | B81: Nina Kowalski | C81: NINA.KOWALSKI@GMAIL.COM | D81: +1-889-774-7383 | E81: Italy | F81: Feb 04, 2025 | G81: yes
A82: CUST-5248 | B82: Ethan Khan | C82: Ethan.Khan@Company.Co.Uk | D82: +1-782-792-5448 | E82: Usa | F82: 28/03/2023 07:46 | G82: TRUE
A83: CUST-5128 | B83: Rita Garcia | D83: 03832 875 750 | E83: Ireland | F83: 2024/03/15
A84: CUST-5589 | B84: Rita Walker | C84: rita.walekr@example.com | D84: +1-820-817-1618 | E84: Italy | F84: 16-Sep-2024 20:54 | G84: TRUE
A85: CUST-5109 | B85: Paula Lopez | C85: paula.lopez@company.co.uk | D85: +44 326 040 6758 | E85: USA | F85: 44704 | G85: yes
A86: CUST-5610 | B86: Vlad Rodriguez | C86: vlad.rodriguez@shop.io | D86: +44 262 888 8419 | E86: USA | F86: 44814 | G86: Yes
A87: CUST-5571 | B87: Wiktor Young | C87: wiktor.young@yahoo.cmo | D87: +1-394-440-5402 | E87: Italy | F87: Jan 23, 2023 | G87: no
A88: CUST-5370 | B88: GABE KING | C88: gabe.king@shop.io | D88: +1-518-547-1853 | E88: Germany | F88: 2023/07/24 | G88: N
A89: CUST-5074 | B89: Daria Rossi | C89: DARIA.ROSSI@OUTLOOK.COM | D89: +44 486 885 0030 | E89: Ireland | F89: 2022-04-07 | G89: TRUE
A90: CUST-5186 | B90: Igor Muller | C90: igor.muller@outlook.com | E90: Poland | F90: 09/04/2025 | G90: no
A91: CUST-5209 | B91: Carlos Kowalczyk | C91: carlos.kowalcyzk@shop.io | D91: 08170 623 161 | E91: Germany | F91: 08/10/2025
A92: CUST-5344 | B92: Qi Lee | D92: 00870 927 037 | E92: France | F92: 2024/06/27 15:06
A93: CUST-5127 | B93: Daria Khan | C93: daria.khan@shop.io | D93: +44 647 485 4035 | E93: USA | F93: 45129 | G93: FALSE
A94: CUST-5217 | B94: Marek Davis | C94: MAREK.DAVIS@SHOP.IO | D94: 05714 726 486 | E94: Spain | F94: 2024/11/23 | G94: no
A95: CUST-5294 | B95: Ken Young | C95: ken.young@yahoo.com | E95: Spain | F95: 2023/08/04 | G95: FALSE
A96: CUST-5320 | B96: Bella King | C96: bella.king@yahoo.com | D96: +44 616 503 8709 | E96: France | F96: 02/29/2024 | G96: yes
A97: CUST-5064 | B97: Carlos Johnson | C97: calros.johnson@outlook.com | D97: +44 817 847 2144 | E97: Poland | F97: 2025-06-01 05:13 | G97: FALSE
A98: CUST-5664 | B98: Adam Rodriguze | C98: adam.rodriguez@example.com | D98: +1-225-906-4722 | E98: Ireland | F98: 2022/08/18 | G98: No
A99: CUST-5063 | B99: LiaK owalski | C99: LIA.KOWALSKI@COMPANY.CO.UK | D99: 03404 612 979 | E99: Poland | F99: 44948 00:22 | G99: Yes
A100: CUST-5473 | B100: Jade Khan | C100: Jade.Khan@Yahoo.Com | E100: rIeland | F100: 2024-11-17 | G100: N
...

Sheet products_raw
A1: sku | B1: product_name | C1: category | D1: list_price | E1: active
A2: SKU-1000 | B2: Router XA5400 | C2: Audoi | D2: £716.33 | E2: Yes
A3: SKU-1001 | B3: 4K Monito r32 | C3: Computers | D3: 115.74 GBP | E3: NO
A4: SKU-1002 | B4: NOISE CANCELLING HEADPHONES | C4: Storage | D4: 759.83 GBP | E4: yes
A5: SKU-1003 | B5: USB-C Hub 7in1 | C5: Monitors | D5: €116.62 | E5: No
A6: SKU-1004 | B6: Gaming Laptop 15 | C6: Accessories | D6: 1,037.64 PLN | E6: No
A7: SKU-1005 | B7: NVMe SSD 2TB | C7: COMPUTERS | D7: 80.13 GBP | E7: FALSE
A8: SKU-1006 | B8: USB-C Hub 7in1 | C8: SMART HOME | D8: $177.43 | E8: TRUE
A9: SKU-1007 | B9: Led Light Strip | C9: Networking | D9: zł630.79 | E9: NO
A10: SKU-1008 | B10: NVMe SSD 2TB | C10: Accessories | D10: 307.62 PLN | E10: FALSE
A11: SKU-1009 | B11: Gaming Laptop 15 | C11: Audoi | D11: €158.45
A12: SKU-1010 | B12: Gaming Chair | C12: Storage | D12: £1,715.09 | E12: FALSE
A13: SKU-1011 | B13: LED LIGHT STRIP | C13: Accessories | D13: €350,99
A14: SKU-1012 | B14: Wireless Mouse | C14: Accessories | D14: zł1,574.18 | E14: FALSE
A15: SKU-1013 | B15: NVMe SSD 2TB | C15: Computesr | D15: €567.90 | E15: yes
A16: SKU-1014 | B16: 4K MONITOR 32 | C16: Accessories | D16: 1,366.32 USD
A17: SKU-1015 | B17: 4K Monitor 32 | C17: Smart Home | D17: 909.32 EUR | E17: No
A18: SKU-1016 | B18: Docking Station Pro | C18: COMPUTERS | D18: 646.09 GBP | E18: yes
A19: SKU-1017 | B19: Smart Plug 2-Pack | C19: Storage | D19: £154,07 | E19: yes
A20: SKU-1018 | B20: Smart Plug 2-Pack | C20: Smart Home | D20: 1,160.56 GBP | E20: NO
A21: SKU-1019 | B21: LED Light Strip | C21: Computers | D21: 728,08 GBP | E21: NO
A22: SKU-1020 | B22: Smartphone Case | C22: Computers | D22: $1,185.85 | E22: No
A23: SKU-1021 | B23: Microphone Usb | C23: Smart Home | D23: €358.50 | E23: Yes
A24: SKU-1022 | B24: Smart Plug 2-Pack | C24: Computers | D24: 1,195.16 PLN
A25: SKU-1023 | B25: Wireless oMuse | C25: Smart Home | D25: €1,439.71 | E25: Yes
A26: SKU-1024 | B26: 4 K Monitor 32 | C26: Accessories | D26: $454,55
A27: SKU-1025 | B27: Webcam 1080P | C27: Networking | D27: 505.88 PLN | E27: No
A28: SKU-1026 | B28: Portable DHD 2TB | C28: Audio | D28: zł755,36 | E28: yes
A29: SKU-1027 | B29: Smart Plug 2-Pack | C29: Audio | D29: 462.80 EUR | E29: No
A30: SKU-1028 | B30: Microphoen USB | C30: Monitors | D30: zł732.41
A31: SKU-1029 | B31: Smartphone Case | C31: Storage | D31: £926.43 | E31: No
A32: SKU-1030 | B32: Ultrabook 14 | C32: Smart Home | D32: 241.77 PLN | E32: TRUE
A33: SKU-1031 | B33: USB-C Hub 7in1 | C33: Sotrage | D33: €112,91 | E33: NO
A34: SKU-1032 | B34: External SSD 1TB | C34: Computers | D34: 30.65 PLN | E34: Yes
A35: SKU-1033 | B35: Bluetooth Speaker | C35: Audio | D35: 1,677.79 USD | E35: Yes
A36: SKU-1034 | B36: Wireless Mouse | C36: ACCESSORIES | D36: 1,321.48 EUR | E36: FALSE
A37: SKU-1035 | B37: DOCKING STATION PRO | C37: Storage | D37: €1,240.37 | E37: No
A38: SKU-1036 | B38: WIRELESS MOUSE | C38: Accessories | D38: $1,128,92 | E38: yes
A39: SKU-1037 | B39: 27in Monitor | C39: Accessories | D39: €831,96 | E39: TRUE
A40: SKU-1038 | B40: Webcam 1080P | C40: Stroage | D40: $337.30 | E40: No
A41: SKU-1039 | B41: LED Light Strip | C41: Monitors | D41: £84.53 | E41: NO
A42: SKU-1040 | B42: SMARTPHONE CAES | C42: COMPUTERS | D42: zł1,377.35 | E42: yes
A43: SKU-1041 | B43: Docking Station Pro | C43: AUDIO | D43: 1,637.79 GBP | E43: No
A44: SKU-1042 | B44: SMART PLUG 2-PACK | C44: Accessories | D44: 683.76 PLN
A45: SKU-1043 | B45: 4K Monitor 32 | C45: Accessories | D45: 1,189.48 GBP | E45: yes
A46: SKU-1044 | B46: Portable HDD 2TB | C46: COPMUTERS | D46: £1,522.65 | E46: yes
A47: SKU-1045 | B47: 27i nMonitor | C47: MONITORS | D47: £1,025.72 | E47: FALSE
A48: SKU-1046 | B48: Portable HDD 2TB | C48: Computers | D48: €1,382,46 | E48: TRUE
A49: SKU-1047 | B49: LED Light Strip | C49: Audio | D49: €1,649,72 | E49: TRUE
A50: SKU-1048 | B50: External SSD 1BT | C50: NETWORKING | D50: 663.32 PLN | E50: FALSE
A51: SKU-1049 | B51: Smart Plug 2-Pack | C51: Computers | D51: $575.46 | E51: TRUE
A52: SKU-1050 | B52: Ultrabook 14 | C52: tSorage | D52: 126.24 PLN | E52: yes
A53: SKU-1051 | B53: 27in Monitor | C53: Networking | E53: NO
A54: SKU-1052 | B54: LED Light Strip | C54: MONITORS | D54: £992.56
A55: SKU-1053 | B55: Noise Cancelling Headphones | C55: Audio | D55: $854.73 | E55: yes
A56: SKU-1054 | B56: LED Light Strip | C56: Accessories | D56: €309.35 | E56: FALSE
A57: SKU-1055 | B57: Noise Cancelling Headphones | C57: Monitors | E57: NO
A58: SKU-1056 | B58: Microphone USB | C58: Computers | D58: €750.43 | E58: yes
A59: SKU-1057 | B59: Webcam 1080p | C59: Accessories | D59: €494.85 | E59: FALSE
A60: SKU-1058 | B60: NVMe SSD 2TB | C60: Monitors | D60: £886.29 | E60: No
A61: SKU-1059 | B61: NOISE CANCELLING HEADPHONES | C61: Monitors | D61: 1,748.71 GBP | E61: NO
A62: SKU-1060 | B62: Noise Cancelling Headphones | C62: AUDIO | D62: 1,028.62 GBP | E62: Yes
A63: SKU-1061 | B63: 27INM ONITOR | C63: Monitors | D63: €1,697.99 | E63: NO
A64: SKU-1062 | B64: GAMNIG LAPTOP 15 | C64: Computers | D64: €951.51 | E64: TRUE
A65: SKU-1063 | B65: Gaming Laptop 15 | C65: NETWORKING | D65: $769,11 | E65: yes
A66: SKU-1064 | B66: Docking Station Pro | C66: Accessories | D66: €377.13 | E66: FALSE
A67: SKU-1065 | B67: Smartphone Case | C67: Audio | D67: zł1,613.79 | E67: No
A68: SKU-1066 | B68: Microphone USB | C68: Accessories | D68: €1,279.93 | E68: No
A69: SKU-1067 | B69: Docking Station Pro | C69: Netowrking | D69: 846.56 USD | E69: FALSE
A70: SKU-1068 | B70: External SSD 1TB | C70: Monitors | D70: €1,735.08
A71: SKU-1069 | B71: Portable HDD 2TB | C71: A udio | D71: zł588.39 | E71: Yes
A72: SKU-1070 | B72: Ultraobok 14 | C72: Audio | D72: $1,346.89
A73: SKU-1071 | B73: USB-C Hub 7in1 | C73: Accessories | D73: £1,487.75 | E73: FALSE
A74: SKU-1072 | B74: BLUETOOTH SPEAKER | C74: Accessories | D74: 1,445.79 USD | E74: Yes
A75: SKU-1073 | B75: Docking Station Pro | C75: Audio | D75: €710,72 | E75: Yes
A76: SKU-1074 | B76: Ultrabook 14 | C76: Monitors | D76: £160.41 | E76: No
A77: SKU-1075 | B77: 4K Monitor 32 | C77: Smart Home | D77: 1,394.46 GBP | E77: No
A78: SKU-1076 | B78: Gaming Laptop 15 | C78: Audio | D78: €284.28 | E78: Yes
A79: SKU-1077 | B79: External SSD 1TB | C79: Accessories | D79: 859.35 EUR
A80: SKU-1078 | B80: Webcam 1080p | C80: Accessories | D80: €675.93 | E80: No
A81: SKU-1079 | B81: Mechanical Keyboard | C81: Stroage | D81: £618.28 | E81: TRUE
A82: SKU-1080 | B82: Bluetooth Speaker | C82: Monitors | D82: €568.51
A83: SKU-1081 | B83: USB-C Hub 7in1 | C83: Networking | D83: $302.83 | E83: FALSE
A84: SKU-1082 | B84: Wireless Mouse | C84: Smart Home | D84: 1,381.56 USD | E84: Yes
A85: SKU-1083 | B85: LED Light Strip | C85: Monitors | D85: 1,589,40 PLN | E85: TRUE
A86: SKU-1084 | B86: Docking Station Pro | C86: Audio | D86: $270,98 | E86: TRUE
A87: SKU-1085 | B87: NOISE CANCELLING HEADPOHNES | C87: SMART HOME | D87: zł1,697.16 | E87: NO
A88: SKU-1086 | B88: Gaming Laptop 15 | C88: Monitors | D88: 733,62 EUR | E88: No
A89: SKU-1087 | B89: Webcam 1080p | C89: Accessories | D89: 1,591.23 GBP | E89: TRUE
A90: SKU-1088 | B90: Gaming Chair | C90: Audio | D90: $771.64 | E90: NO
A91: SKU-1089 | B91: Portable HDD 2TB | C91: Smart Home | D91: zł331,24 | E91: Yes
A92: SKU-1090 | B92: Noise Cancelling Headphones | C92: Accessories | D92: 1,659.68 USD | E92: NO
A93: SKU-1091 | B93: Usb-C Hub 7In1 | C93: Monitors | D93: £1,319.70 | E93: No
A94: SKU-1092 | B94: USB-C Hub 7in1 | C94: Smart Home | D94: $637.75 | E94: No
A95: SKU-1093 | B95: Gaming Chair | C95: Storage | D95: €1,111,78 | E95: No
A96: SKU-1094 | B96: Ultrabook 14 | C96: Accessories | D96: 1,384.43 GBP
A97: SKU-1095 | B97: LED Light Strip | C97: Networking | D97: $1,437.03 | E97: Yes
A98: SKU-1096 | B98: 27In Monitor | C98: mSart Home | D98: 933.31 USD | E98: TRUE
A99: SKU-1097 | B99: Smartphone Case | C99: Netwroking | D99: 783,26 USD
A100: SKU-1098 | B100: SMART PLUG 2-PACK | C100: Monitors | D100: 411.19 USD | E100: No
...

Sheet customers_clean
A1: customer_id | B1: customer_id_flag | C1: full_name | D1: full_name_F | E1: name_token_count | F1: name_flag | G1: full_name_email | H1: email_F | I1: email | J1: email_flag | K1: phone | Q1: phone_flag | R1: region | S1: created_at | T1: Step_1 | U1: Step_2 | V1: Step_3 | W1: Step_4 | X1: Step_5 | Y1: creat_at_F
A2: CUST-5000 | B2: {=IF(COUNTIF(A:A,A2:A701)=1, "✅ Unique", "❌ Duplicate")} -> ✅ Unique | C2: Ethan King | D2: =IFERROR(__xludf.DUMMYFUNCTION("PROPER(REGEXREPLACE(TRIM(C2),""\s+"","" ""))"),"Ethan King") -> Ethan King | E2: =IFERROR(__xludf.DUMMYFUNCTION("IF(LEN(D2:D701), COUNTA(SPLIT(D2:D701,"" "")), """")"),2.0) -> 2 | F2: =IF(D2=G2,"✅","❌") -> ✅ | G2: =IFERROR(__xludf.DUMMYFUNCTION("REGEXEXTRACT(PROPER(SUBSTITUTE(TRIM(I2),""."","" "")),""^[^@]+"")"),"Ethan King") -> Ethan King | H2: =LOWER(TRIM(I2)) -> ethan.king@shop.i o | I2: ethan.king@shop.i o | J2: =IFERROR(__xludf.DUMMYFUNCTION("IF(REGEXMATCH(TRIM(I2),""^[A-Za-z0-9._%+-]+@[A-Za-z0-9.-]+\.[A-Za-z]{2,}$""),""✅ Valid"",""❌ Invalid"")"),"❌ Invalid") -> ❌ Invalid | K2: 18912177948 | L2: =IFERROR(__xludf.DUMMYFUNCTION("IF(OR(K2=""N/A"", K2=""missing"", K2=""none""), """", REGEXREPLACE( SUBSTITUTE(SUBSTITUTE(SUBSTITUTE(TO_TEXT(K2), CHAR(160),""""), UNICHAR(8239),""""), UNICHAR(8201),""""),""[+\-/(): )]"", """"))"),"18912177948") -> 18912177948 | M2: =IFERROR(__xludf.DUMMYFUNCTION("IF(L2="""","""", REGEXEXTRACT(REGEXREPLACE(L2,""x"", """"), ""[0-9]+""))"),"18912177948") -> 18912177948 | N2: =IF(LEFT(M2,1)="1", RIGHT(M2,LEN(M2)-1),M2) -> 8912177948 | O2: =IFERROR(__xludf.DUMMYFUNCTION("REGEXMATCH(TO_TEXT(N2), ""^[2-9][0-9]{9}$"")"),TRUE) -> TRUE | P2: =LEN(N2) -> 10 | Q2: =IF(AND(O2=TRUE, P2=10), "✅ VALID", "❌ INVALID") -> ✅ VALID | R2: USA | S2: 04/22/2025 | T2: =IFERROR(__xludf.DUMMYFUNCTION("IF(ISNUMBER(S2),TEXT(S2,""yyyy-MM-dd""),REGEXREPLACE(REGEXREPLACE(TO_TEXT(S2),""[^0-9a-zA-Z]+"",""-""),""[^0-9]*$"",""""))"),"04-22-2025") -> 04-22-2025 | U2: =TEXT(T2,"yyyy-MM-dd") -> 04-22-2025 | V2: 2025-04-22 | Y2: 2025-04-22
A3: CUST-5001 | B3: ✅ Unique | C3: Wiktor Muller | D3: =IFERROR(__xludf.DUMMYFUNCTION("PROPER(REGEXREPLACE(TRIM(C3),""\s+"","" ""))"),"Wiktor Muller") -> Wiktor Muller | E3: =IFERROR(__xludf.DUMMYFUNCTION("IF(LEN(D3:D701), COUNTA(SPLIT(D3:D701,"" "")), """")"),2.0) -> 2 | F3: =IF(D3=G3,"✅","❌") -> ✅ | G3: =IFERROR(__xludf.DUMMYFUNCTION("REGEXEXTRACT(PROPER(SUBSTITUTE(TRIM(I3),""."","" "")),""^[^@]+"")"),"Wiktor Muller") -> Wiktor Muller | H3: =LOWER(TRIM(I3)) -> wiktor.muller@shop.io | I3: wiktor.muller@shop.io | J3: =IFERROR(__xludf.DUMMYFUNCTION("IF(REGEXMATCH(TRIM(I3),""^[A-Za-z0-9._%+-]+@[A-Za-z0-9.-]+\.[A-Za-z]{2,}$""),""✅ Valid"",""❌ Invalid"")"),"✅ Valid") -> ✅ Valid | L3: =IFERROR(__xludf.DUMMYFUNCTION("IF(OR(K3=""N/A"", K3=""missing"", K3=""none""), """", REGEXREPLACE( SUBSTITUTE(SUBSTITUTE(SUBSTITUTE(TO_TEXT(K3), CHAR(160),""""), UNICHAR(8239),""""), UNICHAR(8201),""""),""[+\-/(): )]"", """"))"),"") | M3: =IFERROR(__xludf.DUMMYFUNCTION("IF(L3="""","""", REGEXEXTRACT(REGEXREPLACE(L3,""x"", """"), ""[0-9]+""))"),"") | N3: =IF(LEFT(M3,1)="1", RIGHT(M3,LEN(M3)-1),M3) | O3: =IFERROR(__xludf.DUMMYFUNCTION("REGEXMATCH(TO_TEXT(N3), ""^[2-9][0-9]{9}$"")"),FALSE) -> FALSE | P3: =LEN(N3) -> 0 | Q3: =IF(AND(O3=TRUE, P3=10), "✅ VALID", "❌ INVALID") -> ❌ INVALID | R3: USA | S3: 45813 | T3: =IFERROR(__xludf.DUMMYFUNCTION("IF(ISNUMBER(S3),TEXT(S3,""yyyy-MM-dd""),REGEXREPLACE(REGEXREPLACE(TO_TEXT(S3),""[^0-9a-zA-Z]+"",""-""),""[^0-9]*$"",""""))"),"2025-06-05") -> 2025-06-05 | U3: 2025-06-05 | Y3: 2025-06-05
A4: CUST-5002 | B4: ✅ Unique | C4: Lia Novak | D4: =IFERROR(__xludf.DUMMYFUNCTION("PROPER(REGEXREPLACE(TRIM(C4),""\s+"","" ""))"),"Lia Novak") -> Lia Novak | E4: =IFERROR(__xludf.DUMMYFUNCTION("IF(LEN(D4:D701), COUNTA(SPLIT(D4:D701,"" "")), """")"),2.0) -> 2 | F4: =IF(D4=G4,"✅","❌") -> ✅ | G4: =IFERROR(__xludf.DUMMYFUNCTION("REGEXEXTRACT(PROPER(SUBSTITUTE(TRIM(I4),""."","" "")),""^[^@]+"")"),"Lia Novak") -> Lia Novak | H4: =LOWER(TRIM(I4)) -> lia.novak@gmail.com | I4: lia.novak@gmail.com | J4: =IFERROR(__xludf.DUMMYFUNCTION("IF(REGEXMATCH(TRIM(I4),""^[A-Za-z0-9._%+-]+@[A-Za-z0-9.-]+\.[A-Za-z]{2,}$""),""✅ Valid"",""❌ Invalid"")"),"✅ Valid") -> ✅ Valid | K4: +441895238062 ext 644 | L4: =IFERROR(__xludf.DUMMYFUNCTION("IF(OR(K4=""N/A"", K4=""missing"", K4=""none""), """", REGEXREPLACE( SUBSTITUTE(SUBSTITUTE(SUBSTITUTE(TO_TEXT(K4), CHAR(160),""""), UNICHAR(8239),""""), UNICHAR(8201),""""),""[+\-/(): )]"", """"))"),"441895238062ext644") -> 441895238062ext644 | M4: =IFERROR(__xludf.DUMMYFUNCTION("IF(L4="""","""", REGEXEXTRACT(REGEXREPLACE(L4,""x"", """"), ""[0-9]+""))"),"441895238062") -> 441895238062 | N4: =IF(LEFT(M4,2)="44", RIGHT(M4,LEN(M4)-2),M4) -> 1895238062 | O4: =IFERROR(__xludf.DUMMYFUNCTION("REGEXMATCH(TO_TEXT(N4), ""^07[1-57-9]"")"),FALSE) -> FALSE | P4: =LEN(N4) -> 10 | Q4: =IF(AND(O4=TRUE, P4=11), "✅ VALID", "❌ INVALID") -> ❌ INVALID | R4: UK | S4: 02/24/2022 | T4: =IFERROR(__xludf.DUMMYFUNCTION("IF(ISNUMBER(S4),TEXT(S4,""yyyy-MM-dd""),REGEXREPLACE(REGEXREPLACE(TO_TEXT(S4),""[^0-9a-zA-Z]+"",""-""),""[^0-9]*$"",""""))"),"02-24-2022") -> 02-24-2022 | U4: =TEXT(T4,"yyyy-MM-dd") -> 02-24-2022 | V4: 2022-02-24 | Y4: 2022-02-24
A5: CUST-5003 | B5: ✅ Unique | C5: Vlad Lee | D5: =IFERROR(__xludf.DUMMYFUNCTION("PROPER(REGEXREPLACE(TRIM(C5),""\s+"","" ""))"),"Vlad Lee") -> Vlad Lee | E5: =IFERROR(__xludf.DUMMYFUNCTION("IF(LEN(D5:D701), COUNTA(SPLIT(D5:D701,"" "")), """")"),2.0) -> 2 | F5: =IF(D5=G5,"✅","❌") -> ✅ | G5: =IFERROR(__xludf.DUMMYFUNCTION("REGEXEXTRACT(PROPER(SUBSTITUTE(TRIM(I5),""."","" "")),""^[^@]+"")"),"Vlad Lee") -> Vlad Lee | H5: =LOWER(TRIM(I5)) -> vlad.lee@outlook.com | I5: vlad.lee@outlook.com | J5: =IFERROR(__xludf.DUMMYFUNCTION("IF(REGEXMATCH(TRIM(I5),""^[A-Za-z0-9._%+-]+@[A-Za-z0-9.-]+\.[A-Za-z]{2,}$""),""✅ Valid"",""❌ Invalid"")"),"✅ Valid") -> ✅ Valid | K5: 228-667-113 | L5: =IFERROR(__xludf.DUMMYFUNCTION("IF(OR(K5=""N/A"", K5=""missing"", K5=""none""), """", REGEXREPLACE( SUBSTITUTE(SUBSTITUTE(SUBSTITUTE(TO_TEXT(K5), CHAR(160),""""), UNICHAR(8239),""""), UNICHAR(8201),""""),""[+\-/(): )]"", """"))"),"228667113") -> 228667113 | M5: =IFERROR(__xludf.DUMMYFUNCTION("IF(L5="""","""", REGEXEXTRACT(REGEXREPLACE(L5,""x"", """"), ""[0-9]+""))"),"228667113") -> 228667113 | N5: =IF(LEFT(M5,2)="39", RIGHT(M5,LEN(M5)-2),M5) -> 228667113 | O5: =IFERROR(__xludf.DUMMYFUNCTION("REGEXMATCH(TO_TEXT(N5), ""^3"")"),FALSE) -> FALSE | P5: =LEN(N5) -> 9 | Q5: =IF(AND(O5=TRUE,OR(P5=9, P5=10 )), "✅ VALID", "❌ INVALID") -> ❌ INVALID | R5: Italy | S5: 08.03.2025 | T5: =IFERROR(__xludf.DUMMYFUNCTION("IF(ISNUMBER(S5),TEXT(S5,""yyyy-MM-dd""),REGEXREPLACE(REGEXREPLACE(TO_TEXT(S5),""[^0-9a-zA-Z]+"",""-""),""[^0-9]*$"",""""))"),"08-03-2025") -> 08-03-2025 | U5: 2025-03-08 | Y5: 2025-03-08
A6: CUST-5004 | B6: ✅ Unique | C6: Zack Smith | D6: =IFERROR(__xludf.DUMMYFUNCTION("PROPER(REGEXREPLACE(TRIM(C6),""\s+"","" ""))"),"Zack Smith") -> Zack Smith | E6: =IFERROR(__xludf.DUMMYFUNCTION("IF(LEN(D6:D701), COUNTA(SPLIT(D6:D701,"" "")), """")"),2.0) -> 2 | F6: =IF(D6=G6,"✅","❌") -> ✅ | G6: =IFERROR(__xludf.DUMMYFUNCTION("REGEXEXTRACT(PROPER(SUBSTITUTE(TRIM(I6),""."","" "")),""^[^@]+"")"),"Zack Smith") -> Zack Smith | H6: =LOWER(TRIM(I6)) -> zack.smith@outlookc.om | I6: zack.smith@outlookc.om | J6: =IFERROR(__xludf.DUMMYFUNCTION("IF(REGEXMATCH(TRIM(I6),""^[A-Za-z0-9._%+-]+@[A-Za-z0-9.-]+\.[A-Za-z]{2,}$""),""✅ Valid"",""❌ Invalid"")"),"✅ Valid") -> ✅ Valid | K6: tel:+497822452005 | L6: =IFERROR(__xludf.DUMMYFUNCTION("IF(OR(K6=""N/A"", K6=""missing"", K6=""none""), """", REGEXREPLACE( SUBSTITUTE(SUBSTITUTE(SUBSTITUTE(TO_TEXT(K6), CHAR(160),""""), UNICHAR(8239),""""), UNICHAR(8201),""""),""[+\-/(): )]"", """"))"),"tel497822452005") -> tel497822452005 | M6: =IFERROR(__xludf.DUMMYFUNCTION("IF(L6="""","""", REGEXEXTRACT(REGEXREPLACE(L6,""x"", """"), ""[0-9]+""))"),"497822452005") -> 497822452005 | N6: =IF(LEFT(M6,2)="49", RIGHT(M6,LEN(M6)-2),M6) -> 7822452005 | O6: =IFERROR(__xludf.DUMMYFUNCTION("REGEXMATCH(TO_TEXT(N6), ""^0(15|16|17)"")"),FALSE) -> FALSE | P6: =LEN(N6) -> 10 | Q6: =IF(AND(O6=TRUE,OR(P6=10, P6=11)), "✅ VALID", "❌ INVALID") -> ❌ INVALID | R6: Germany | S6: 44786 | T6: =IFERROR(__xludf.DUMMYFUNCTION("IF(ISNUMBER(S6),TEXT(S6,""yyyy-MM-dd""),REGEXREPLACE(REGEXREPLACE(TO_TEXT(S6),""[^0-9a-zA-Z]+"",""-""),""[^0-9]*$"",""""))"),"2022-08-13") -> 2022-08-13 | U6: 2022-08-13 | Y6: 2022-08-13
A7: CUST-5005 | B7: ✅ Unique | C7: Rita Rodriguez | D7: =IFERROR(__xludf.DUMMYFUNCTION("PROPER(REGEXREPLACE(TRIM(C7),""\s+"","" ""))"),"Rita Rodriguez") -> Rita Rodriguez | E7: =IFERROR(__xludf.DUMMYFUNCTION("IF(LEN(D7:D701), COUNTA(SPLIT(D7:D701,"" "")), """")"),2.0) -> 2 | F7: =IF(D7=G7,"✅","❌") -> ✅ | G7: =IFERROR(__xludf.DUMMYFUNCTION("REGEXEXTRACT(PROPER(SUBSTITUTE(TRIM(I7),""."","" "")),""^[^@]+"")"),"Rita Rodriguez") -> Rita Rodriguez | H7: =LOWER(TRIM(I7)) -> rita.rodriguez@gmail.com | I7: rita.rodriguez@gmail.com | J7: =IFERROR(__xludf.DUMMYFUNCTION("IF(REGEXMATCH(TRIM(I7),""^[A-Za-z0-9._%+-]+@[A-Za-z0-9.-]+\.[A-Za-z]{2,}$""),""✅ Valid"",""❌ Invalid"")"),"✅ Valid") -> ✅ Valid | K7: 9808647248 | L7: =IFERROR(__xludf.DUMMYFUNCTION("IF(OR(K7=""N/A"", K7=""missing"", K7=""none""), """", REGEXREPLACE( SUBSTITUTE(SUBSTITUTE(SUBSTITUTE(TO_TEXT(K7), CHAR(160),""""), UNICHAR(8239),""""), UNICHAR(8201),""""),""[+\-/(): )]"", """"))"),"9808647248") -> 9808647248 | M7: =IFERROR(__xludf.DUMMYFUNCTION("IF(L7="""","""", REGEXEXTRACT(REGEXREPLACE(L7,""x"", """"), ""[0-9]+""))"),"9808647248") -> 9808647248 | N7: =IF(LEFT(M7,1)="1", RIGHT(M7,LEN(M7)-1),M7) -> 9808647248 | O7: =IFERROR(__xludf.DUMMYFUNCTION("REGEXMATCH(TO_TEXT(N7), ""^[2-9][0-9]{9}$"")"),TRUE) -> TRUE | P7: =LEN(N7) -> 10 | Q7: =IF(AND(O7=TRUE, P7=10), "✅ VALID", "❌ INVALID") -> ✅ VALID | R7: USA | S7: 45006 | T7: =IFERROR(__xludf.DUMMYFUNCTION("IF(ISNUMBER(S7),TEXT(S7,""yyyy-MM-dd""),REGEXREPLACE(REGEXREPLACE(TO_TEXT(S7),""[^0-9a-zA-Z]+"",""-""),""[^0-9]*$"",""""))"),"2023-03-21") -> 2023-03-21 | U7: 2023-03-21 | Y7: 2023-03-21
A8: CUST-5006 | B8: ✅ Unique | C8: Gabe Lopze | D8: Gabe Lopez | E8: =IFERROR(__xludf.DUMMYFUNCTION("IF(LEN(D8:D701), COUNTA(SPLIT(D8:D701,"" "")), """")"),2.0) -> 2 | F8: =IF(D8=G8,"✅","❌") -> ✅ | G8: Gabe Lopez | H8: =LOWER(TRIM(I8)) -> gabe.lopez@shop.io | I8: gabe.lopez@shop.io | J8: =IFERROR(__xludf.DUMMYFUNCTION("IF(REGEXMATCH(TRIM(I8),""^[A-Za-z0-9._%+-]+@[A-Za-z0-9.-]+\.[A-Za-z]{2,}$""),""✅ Valid"",""❌ Invalid"")"),"✅ Valid") -> ✅ Valid | K8: +33 045 3496251 | L8: =IFERROR(__xludf.DUMMYFUNCTION("IF(OR(K8=""N/A"", K8=""missing"", K8=""none""), """", REGEXREPLACE( SUBSTITUTE(SUBSTITUTE(SUBSTITUTE(TO_TEXT(K8), CHAR(160),""""), UNICHAR(8239),""""), UNICHAR(8201),""""),""[+\-/(): )]"", """"))"),"330453496251") -> 330453496251 | M8: =IFERROR(__xludf.DUMMYFUNCTION("IF(L8="""","""", REGEXEXTRACT(REGEXREPLACE(L8,""x"", """"), ""[0-9]+""))"),"330453496251") -> 330453496251 | N8: =IF(LEFT(M8,2)="33", RIGHT(M8,LEN(M8)-2),M8) -> 0453496251 | O8: =IFERROR(__xludf.DUMMYFUNCTION("REGEXMATCH(TO_TEXT(N8), ""^0[67]"")"),FALSE) -> FALSE | P8: =LEN(N8) -> 10 | Q8: =IF(AND(O8=TRUE, P8=9), "✅ VALID", "❌ INVALID") -> ❌ INVALID | R8: France | S8: 45652 | T8: =IFERROR(__xludf.DUMMYFUNCTION("IF(ISNUMBER(S8),TEXT(S8,""yyyy-MM-dd""),REGEXREPLACE(REGEXREPLACE(TO_TEXT(S8),""[^0-9a-zA-Z]+"",""-""),""[^0-9]*$"",""""))"),"2024-12-26") -> 2024-12-26 | U8: 2024-12-26 | Y8: 2024-12-26
A9: CUST-5007 | B9: ✅ Unique | C9: Jade Brown | D9: =IFERROR(__xludf.DUMMYFUNCTION("PROPER(REGEXREPLACE(TRIM(C9),""\s+"","" ""))"),"Jade Brown") -> Jade Brown | E9: =IFERROR(__xludf.DUMMYFUNCTION("IF(LEN(D9:D701), COUNTA(SPLIT(D9:D701,"" "")), """")"),2.0) -> 2 | F9: =IF(D9=G9,"✅","❌") -> ❌ | G9: Jad Ebrown | H9: =LOWER(TRIM(I9)) -> jad.ebrown@company.co.uk | I9: JAD.EBROWN@COMPANY.CO.UK | J9: =IFERROR(__xludf.DUMMYFUNCTION("IF(REGEXMATCH(TRIM(I9),""^[A-Za-z0-9._%+-]+@[A-Za-z0-9.-]+\.[A-Za-z]{2,}$""),""✅ Valid"",""❌ Invalid"")"),"✅ Valid") -> ✅ Valid | K9: +35397911194 | L9: =IFERROR(__xludf.DUMMYFUNCTION("IF(OR(K9=""N/A"", K9=""missing"", K9=""none""), """", REGEXREPLACE( SUBSTITUTE(SUBSTITUTE(SUBSTITUTE(TO_TEXT(K9), CHAR(160),""""), UNICHAR(8239),""""), UNICHAR(8201),""""),""[+\-/(): )]"", """"))"),"35397911194") -> 35397911194 | M9: =IFERROR(__xludf.DUMMYFUNCTION("IF(L9="""","""", REGEXEXTRACT(REGEXREPLACE(L9,""x"", """"), ""[0-9]+""))"),"35397911194") -> 35397911194 | N9: =IF(LEFT(M9,3)="353", RIGHT(M9,LEN(M9)-3),M9) -> 97911194 | O9: =IFERROR(__xludf.DUMMYFUNCTION("REGEXMATCH(TO_TEXT(N9), ""^0(83|85|86|87|89)"")"),FALSE) -> FALSE | P9: =LEN(N9) -> 8 | Q9: =IF(AND(O9=TRUE, P6=10), "✅ VALID", "❌ INVALID") -> ❌ INVALID | R9: Ireland | S9: 44932 | T9: =IFERROR(__xludf.DUMMYFUNCTION("IF(ISNUMBER(S9),TEXT(S9,""yyyy-MM-dd""),REGEXREPLACE(REGEXREPLACE(TO_TEXT(S9),""[^0-9a-zA-Z]+"",""-""),""[^0-9]*$"",""""))"),"2023-01-06") -> 2023-01-06 | U9: 2023-01-06 | Y9: 2023-01-06
A10: CUST-5008 | B10: ✅ Unique | C10: Vlad Young | D10: =IFERROR(__xludf.DUMMYFUNCTION("PROPER(REGEXREPLACE(TRIM(C10),""\s+"","" ""))"),"Vlad Young") -> Vlad Young | E10: =IFERROR(__xludf.DUMMYFUNCTION("IF(LEN(D10:D701), COUNTA(SPLIT(D10:D701,"" "")), """")"),2.0) -> 2 | F10: =IF(D10=G10,"✅","❌") -> ✅ | G10: =IFERROR(__xludf.DUMMYFUNCTION("REGEXEXTRACT(PROPER(SUBSTITUTE(TRIM(I10),""."","" "")),""^[^@]+"")"),"Vlad Young") -> Vlad Young | H10: =LOWER(TRIM(I10)) -> vlad.young@example.com | I10: vlad.young@example.com | J10: =IFERROR(__xludf.DUMMYFUNCTION("IF(REGEXMATCH(TRIM(I10),""^[A-Za-z0-9._%+-]+@[A-Za-z0-9.-]+\.[A-Za-z]{2,}$""),""✅ Valid"",""❌ Invalid"")"),"✅ Valid") -> ✅ Valid | K10: (713) 490434 | L10: =IFERROR(__xludf.DUMMYFUNCTION("IF(OR(K10=""N/A"", K10=""missing"", K10=""none""), """", REGEXREPLACE( SUBSTITUTE(SUBSTITUTE(SUBSTITUTE(TO_TEXT(K10), CHAR(160),""""), UNICHAR(8239),""""), UNICHAR(8201),""""),""[+\-/(): )]"", """"))"),"713490434") -> 713490434 | M10: =IFERROR(__xludf.DUMMYFUNCTION("IF(L10="""","""", REGEXEXTRACT(REGEXREPLACE(L10,""x"", """"), ""[0-9]+""))"),"713490434") -> 713490434 | N10: =IF(LEFT(M10,3)="353", RIGHT(M10,LEN(M10)-3),M10) -> 713490434 | O10: =IFERROR(__xludf.DUMMYFUNCTION("REGEXMATCH(TO_TEXT(N10), ""^0(83|85|86|87|89)"")"),FALSE) -> FALSE | P10: =LEN(N10) -> 9 | Q10: =IF(AND(O10=TRUE, P7=10), "✅ VALID", "❌ INVALID") -> ❌ INVALID | R10: Ireland | S10: 44789.78 | T10: =IFERROR(__xludf.DUMMYFUNCTION("IF(ISNUMBER(S10),TEXT(S10,""yyyy-MM-dd""),REGEXREPLACE(REGEXREPLACE(TO_TEXT(S10),""[^0-9a-zA-Z]+"",""-""),""[^0-9]*$"",""""))"),"2022-08-16") -> 2022-08-16 | U10: 2022-08-16 | Y10: 2022-08-16
A11: CUST-5009 | B11: ✅ Unique | C11: Marek Davis | D11: =IFERROR(__xludf.DUMMYFUNCTION("PROPER(REGEXREPLACE(TRIM(C11),""\s+"","" ""))"),"Marek Davis") -> Marek Davis | E11: =IFERROR(__xludf.DUMMYFUNCTION("IF(LEN(D11:D701), COUNTA(SPLIT(D11:D701,"" "")), """")"),2.0) -> 2 | F11: =IF(D11=G11,"✅","❌") -> ✅ | G11: =IFERROR(__xludf.DUMMYFUNCTION("REGEXEXTRACT(PROPER(SUBSTITUTE(TRIM(I11),""."","" "")),""^[^@]+"")"),"Marek Davis") -> Marek Davis | H11: =LOWER(TRIM(I11)) -> marek.davis@gmail.com | I11: marek.davis@gmail.com | J11: =IFERROR(__xludf.DUMMYFUNCTION("IF(REGEXMATCH(TRIM(I11),""^[A-Za-z0-9._%+-]+@[A-Za-z0-9.-]+\.[A-Za-z]{2,}$""),""✅ Valid"",""❌ Invalid"")"),"✅ Valid") -> ✅ Valid | K11: +44-498-57112876 | L11: =IFERROR(__xludf.DUMMYFUNCTION("IF(OR(K11=""N/A"", K11=""missing"", K11=""none""), """", REGEXREPLACE( SUBSTITUTE(SUBSTITUTE(SUBSTITUTE(TO_TEXT(K11), CHAR(160),""""), UNICHAR(8239),""""), UNICHAR(8201),""""),""[+\-/(): )]"", """"))"),"4449857112876") -> 4449857112876 | M11: =IFERROR(__xludf.DUMMYFUNCTION("IF(L11="""","""", REGEXEXTRACT(REGEXREPLACE(L11,""x"", """"), ""[0-9]+""))"),"4449857112876") -> 4449857112876 | N11: =IF(LEFT(M11,2)="44", RIGHT(M11,LEN(M11)-2),M11) -> 49857112876 | O11: =IFERROR(__xludf.DUMMYFUNCTION("REGEXMATCH(TO_TEXT(N11), ""^07[1-57-9]"")"),FALSE) -> FALSE | P11: =LEN(N11) -> 11 | Q11: =IF(AND(O11=TRUE, P11=11), "✅ VALID", "❌ INVALID") -> ❌ INVALID | R11: UK | S11: 45633 | T11: =IFERROR(__xludf.DUMMYFUNCTION("IF(ISNUMBER(S11),TEXT(S11,""yyyy-MM-dd""),REGEXREPLACE(REGEXREPLACE(TO_TEXT(S11),""[^0-9a-zA-Z]+"",""-""),""[^0-9]*$"",""""))"),"2024-12-07") -> 2024-12-07 | U11: 2024-12-07 | Y11: 2024-12-07
A12: CUST-5010 | B12: ✅ Unique | C12: Hanna Kowalski | D12: =IFERROR(__xludf.DUMMYFUNCTION("PROPER(REGEXREPLACE(TRIM(C12),""\s+"","" ""))"),"Hanna Kowalski") -> Hanna Kowalski | E12: =IFERROR(__xludf.DUMMYFUNCTION("IF(LEN(D12:D701), COUNTA(SPLIT(D12:D701,"" "")), """")"),2.0) -> 2 | F12: =IF(D12=G12,"✅","❌") -> ✅ | G12: =IFERROR(__xludf.DUMMYFUNCTION("REGEXEXTRACT(PROPER(SUBSTITUTE(TRIM(I12),""."","" "")),""^[^@]+"")"),"Hanna Kowalski") -> Hanna Kowalski | H12: =LOWER(TRIM(I12)) -> hanna.kowalski@company.co.uk | I12: hanna.kowalski@company.co.uk | J12: =IFERROR(__xludf.DUMMYFUNCTION("IF(REGEXMATCH(TRIM(I12),""^[A-Za-z0-9._%+-]+@[A-Za-z0-9.-]+\.[A-Za-z]{2,}$""),""✅ Valid"",""❌ Invalid"")"),"✅ Valid") -> ✅ Valid | K12: 5x243474533 | L12: =IFERROR(__xludf.DUMMYFUNCTION("IF(OR(K12=""N/A"", K12=""missing"", K12=""none""), """", REGEXREPLACE( SUBSTITUTE(SUBSTITUTE(SUBSTITUTE(TO_TEXT(K12), CHAR(160),""""), UNICHAR(8239),""""), UNICHAR(8201),""""),""[+\-/(): )]"", """"))"),"5x243474533") -> 5x243474533 | M12: =IFERROR(__xludf.DUMMYFUNCTION("IF(L12="""","""", REGEXEXTRACT(REGEXREPLACE(L12,""x"", """"), ""[0-9]+""))"),"5243474533") -> 5243474533 | N12: =IF(LEFT(M12,1)="1", RIGHT(M12,LEN(M12)-1),M12) -> 5243474533 | O12: =IFERROR(__xludf.DUMMYFUNCTION("REGEXMATCH(TO_TEXT(N12), ""^[2-9][0-9]{9}$"")"),TRUE) -> TRUE | P12: =LEN(N12) -> 10 | Q12: =IF(AND(O12=TRUE, P12=10), "✅ VALID", "❌ INVALID") -> ✅ VALID | R12: USA | S12: 45109 | T12: =IFERROR(__xludf.DUMMYFUNCTION("IF(ISNUMBER(S12),TEXT(S12,""yyyy-MM-dd""),REGEXREPLACE(REGEXREPLACE(TO_TEXT(S12),""[^0-9a-zA-Z]+"",""-""),""[^0-9]*$"",""""))"),"2023-07-02") -> 2023-07-02 | U12: 2023-07-02 | Y12: 2023-07-02
A13: CUST-5011 | B13: ✅ Unique | C13: Lia Brown | D13: =IFERROR(__xludf.DUMMYFUNCTION("PROPER(REGEXREPLACE(TRIM(C13),""\s+"","" ""))"),"Lia Brown") -> Lia Brown | E13: =IFERROR(__xludf.DUMMYFUNCTION("IF(LEN(D13:D701), COUNTA(SPLIT(D13:D701,"" "")), """")"),2.0) -> 2 | F13: =IF(D13=G13,"✅","❌") -> ✅ | G13: =IFERROR(__xludf.DUMMYFUNCTION("REGEXEXTRACT(PROPER(SUBSTITUTE(TRIM(I13),""."","" "")),""^[^@]+"")"),"Lia Brown") -> Lia Brown | H13: =LOWER(TRIM(I13)) -> lia.brown@example.com | I13: LIA.BROWN@EXAMPLE.COM | J13: =IFERROR(__xludf.DUMMYFUNCTION("IF(REGEXMATCH(TRIM(I13),""^[A-Za-z0-9._%+-]+@[A-Za-z0-9.-]+\.[A-Za-z]{2,}$""),""✅ Valid"",""❌ Invalid"")"),"✅ Valid") -> ✅ Valid | K13: N/A | L13: =IFERROR(__xludf.DUMMYFUNCTION("IF(OR(K13=""N/A"", K13=""missing"", K13=""none""), """", REGEXREPLACE( SUBSTITUTE(SUBSTITUTE(SUBSTITUTE(TO_TEXT(K13), CHAR(160),""""), UNICHAR(8239),""""), UNICHAR(8201),""""),""[+\-/(): )]"", """"))"),"") | M13: =IFERROR(__xludf.DUMMYFUNCTION("IF(L13="""","""", REGEXEXTRACT(REGEXREPLACE(L13,""x"", """"), ""[0-9]+""))"),"") | N13: =IF(LEFT(M13,2)="33", RIGHT(M13,LEN(M13)-2),M13) | O13: =IFERROR(__xludf.DUMMYFUNCTION("REGEXMATCH(TO_TEXT(N13), ""^0[67]"")"),FALSE) -> FALSE | P13: =LEN(N13) -> 0 | Q13: =IF(AND(O13=TRUE, P13=9), "✅ VALID", "❌ INVALID") -> ❌ INVALID | R13: France | S13: 44794.447 | T13: =IFERROR(__xludf.DUMMYFUNCTION("IF(ISNUMBER(S13),TEXT(S13,""yyyy-MM-dd""),REGEXREPLACE(REGEXREPLACE(TO_TEXT(S13),""[^0-9a-zA-Z]+"",""-""),""[^0-9]*$"",""""))"),"2022-08-21") -> 2022-08-21 | U13: 2022-08-21 | Y13: 2022-08-21
A14: CUST-5012 | B14: ✅ Unique | C14: MAREK DAVIS | D14: =IFERROR(__xludf.DUMMYFUNCTION("PROPER(REGEXREPLACE(TRIM(C14),""\s+"","" ""))"),"Marek Davis") -> Marek Davis | E14: =IFERROR(__xludf.DUMMYFUNCTION("IF(LEN(D14:D701), COUNTA(SPLIT(D14:D701,"" "")), """")"),2.0) -> 2 | F14: =IF(D14=G14,"✅","❌") -> ✅ | G14: =IFERROR(__xludf.DUMMYFUNCTION("REGEXEXTRACT(PROPER(SUBSTITUTE(TRIM(I14),""."","" "")),""^[^@]+"")"),"Marek Davis") -> Marek Davis | H14: =LOWER(TRIM(I14)) -> marek.davis@outlook.com | I14: marek.davis@outlook.com | J14: =IFERROR(__xludf.DUMMYFUNCTION("IF(REGEXMATCH(TRIM(I14),""^[A-Za-z0-9._%+-]+@[A-Za-z0-9.-]+\.[A-Za-z]{2,}$""),""✅ Valid"",""❌ Invalid"")"),"✅ Valid") -> ✅ Valid | K14: +1 899 081892 | L14: =IFERROR(__xludf.DUMMYFUNCTION("IF(OR(K14=""N/A"", K14=""missing"", K14=""none""), """", REGEXREPLACE( SUBSTITUTE(SUBSTITUTE(SUBSTITUTE(TO_TEXT(K14), CHAR(160),""""), UNICHAR(8239),""""), UNICHAR(8201),""""),""[+\-/(): )]"", """"))"),"1899081892") -> 1899081892 | M14: =IFERROR(__xludf.DUMMYFUNCTION("IF(L14="""","""", REGEXEXTRACT(REGEXREPLACE(L14,""x"", """"), ""[0-9]+""))"),"1899081892") -> 1899081892 | N14: =IF(LEFT(M14,1)="1", RIGHT(M14,LEN(M14)-1),M14) -> 899081892 | O14: =IFERROR(__xludf.DUMMYFUNCTION("REGEXMATCH(TO_TEXT(N14), ""^[2-9][0-9]{9}$"")"),FALSE) -> FALSE | P14: =LEN(N14) -> 9 | Q14: =IF(AND(O14=TRUE, P14=10), "✅ VALID", "❌ INVALID") -> ❌ INVALID | R14: USA | S14: 45763 13:29 | T14: =IFERROR(__xludf.DUMMYFUNCTION("IF(ISNUMBER(S14),TEXT(S14,""yyyy-MM-dd""),REGEXREPLACE(REGEXREPLACE(TO_TEXT(S14),""[^0-9a-zA-Z]+"",""-""),""[^0-9]*$"",""""))"),"45763-13-29") -> 45763-13-29 | U14: =TEXT(T14,"yyyy-MM-dd") -> 45763-13-29 | V14: =CONCATENATE(LEFT(U14,5)) -> 45763 | W14: =DATE(1900,1,1) + V14 - 1 -> 45764 | X14: 2025-04-17 | Y14: 2025-04-17
A15: CUST-5013 | B15: ✅ Unique | C15: Lia Lee | D15: =IFERROR(__xludf.DUMMYFUNCTION("PROPER(REGEXREPLACE(TRIM(C15),""\s+"","" ""))"),"Lia Lee") -> Lia Lee | E15: =IFERROR(__xludf.DUMMYFUNCTION("IF(LEN(D15:D701), COUNTA(SPLIT(D15:D701,"" "")), """")"),2.0) -> 2 | F15: =IF(D15=G15,"✅","❌") -> ✅ | G15: =IFERROR(__xludf.DUMMYFUNCTION("REGEXEXTRACT(PROPER(SUBSTITUTE(TRIM(I15),""."","" "")),""^[^@]+"")"),"Lia Lee") -> Lia Lee | H15: =LOWER(TRIM(I15)) -> lia.lee@example.com | I15: lia.lee@example.com | J15: =IFERROR(__xludf.DUMMYFUNCTION("IF(REGEXMATCH(TRIM(I15),""^[A-Za-z0-9._%+-]+@[A-Za-z0-9.-]+\.[A-Za-z]{2,}$""),""✅ Valid"",""❌ Invalid"")"),"✅ Valid") -> ✅ Valid | K15: 734961588 | L15: =IFERROR(__xludf.DUMMYFUNCTION("IF(OR(K15=""N/A"", K15=""missing"", K15=""none""), """", REGEXREPLACE( SUBSTITUTE(SUBSTITUTE(SUBSTITUTE(TO_TEXT(K15), CHAR(160),""""), UNICHAR(8239),""""), UNICHAR(8201),""""),""[+\-/(): )]"", """"))"),"734961588") -> 734961588 | M15: =IFERROR(__xludf.DUMMYFUNCTION("IF(L15="""","""", REGEXEXTRACT(REGEXREPLACE(L15,""x"", """"), ""[0-9]+""))"),"734961588") -> 734961588 | N15: =IF(LEFT(M15,2)="39", RIGHT(M15,LEN(M15)-2),M15) -> 734961588 | O15: =IFERROR(__xludf.DUMMYFUNCTION("REGEXMATCH(TO_TEXT(N15), ""^3"")"),FALSE) -> FALSE | P15: =LEN(N15) -> 9 | Q15: =IF(AND(O15=TRUE,OR(P15=9, P15=10 )), "✅ VALID", "❌ INVALID") -> ❌ INVALID | R15: Italy | S15: 45095 | T15: =IFERROR(__xludf.DUMMYFUNCTION("IF(ISNUMBER(S15),TEXT(S15,""yyyy-MM-dd""),REGEXREPLACE(REGEXREPLACE(TO_TEXT(S15),""[^0-9a-zA-Z]+"",""-""),""[^0-9]*$"",""""))"),"2023-06-18") -> 2023-06-18 | U15: 2023-06-18 | Y15: 2023-06-18
A16: CUST-5014 | B16: ✅ Unique | C16: Lia Young | D16: =IFERROR(__xludf.DUMMYFUNCTION("PROPER(REGEXREPLACE(TRIM(C16),""\s+"","" ""))"),"Lia Young") -> Lia Young | E16: =IFERROR(__xludf.DUMMYFUNCTION("IF(LEN(D16:D701), COUNTA(SPLIT(D16:D701,"" "")), """")"),2.0) -> 2 | F16: =IF(D16=G16,"✅","❌") -> ✅ | G16: =IFERROR(__xludf.DUMMYFUNCTION("REGEXEXTRACT(PROPER(SUBSTITUTE(TRIM(I16),""."","" "")),""^[^@]+"")"),"Lia Young") -> Lia Young | H16: =LOWER(TRIM(I16)) -> lia.young@example.com | I16: lia.young@example.com | J16: =IFERROR(__xludf.DUMMYFUNCTION("IF(REGEXMATCH(TRIM(I16),""^[A-Za-z0-9._%+-]+@[A-Za-z0-9.-]+\.[A-Za-z]{2,}$""),""✅ Valid"",""❌ Invalid"")"),"✅ Valid") -> ✅ Valid | K16: 5519x4599619 | L16: =IFERROR(__xludf.DUMMYFUNCTION("IF(OR(K16=""N/A"", K16=""missing"", K16=""none""), """", REGEXREPLACE( SUBSTITUTE(SUBSTITUTE(SUBSTITUTE(TO_TEXT(K16), CHAR(160),""""), UNICHAR(8239),""""), UNICHAR(8201),""""),""[+\-/(): )]"", """"))"),"5519x4599619") -> 5519x4599619 | M16: =IFERROR(__xludf.DUMMYFUNCTION("IF(L16="""","""", REGEXEXTRACT(REGEXREPLACE(L16,""x"", """"), ""[0-9]+""))"),"55194599619") -> 55194599619 | N16: =IF(LEFT(M16,2)="44", RIGHT(M16,LEN(M16)-2),M16) -> 55194599619 | O16: =IFERROR(__xludf.DUMMYFUNCTION("REGEXMATCH(TO_TEXT(N16), ""^07[1-57-9]"")"),FALSE) -> FALSE | P16: =LEN(N16) -> 11 | Q16: =IF(AND(O16=TRUE, P16=11), "✅ VALID", "❌ INVALID") -> ❌ INVALID | R16: UK | S16: 45496 | T16: =IFERROR(__xludf.DUMMYFUNCTION("IF(ISNUMBER(S16),TEXT(S16,""yyyy-MM-dd""),REGEXREPLACE(REGEXREPLACE(TO_TEXT(S16),""[^0-9a-zA-Z]+"",""-""),""[^0-9]*$"",""""))"),"2024-07-23") -> 2024-07-23 | U16: 2024-07-23 | Y16: 2024-07-23
A17: CUST-5015 | B17: ✅ Unique | C17: Ethan Dubois | D17: =IFERROR(__xludf.DUMMYFUNCTION("PROPER(REGEXREPLACE(TRIM(C17),""\s+"","" ""))"),"Ethan Dubois") -> Ethan Dubois | E17: =IFERROR(__xludf.DUMMYFUNCTION("IF(LEN(D17:D701), COUNTA(SPLIT(D17:D701,"" "")), """")"),2.0) -> 2 | F17: =IF(D17=G17,"✅","❌") -> ✅ | G17: =IFERROR(__xludf.DUMMYFUNCTION("REGEXEXTRACT(PROPER(SUBSTITUTE(TRIM(I17),""."","" "")),""^[^@]+"")"),"Ethan Dubois") -> Ethan Dubois | H17: =LOWER(TRIM(I17)) -> ethan.dubois@yahoo.com | I17: ethan.dubois@yahoo.com | J17: =IFERROR(__xludf.DUMMYFUNCTION("IF(REGEXMATCH(TRIM(I17),""^[A-Za-z0-9._%+-]+@[A-Za-z0-9.-]+\.[A-Za-z]{2,}$""),""✅ Valid"",""❌ Invalid"")"),"✅ Valid") -> ✅ Valid | K17: +34 948 7174624 | L17: =IFERROR(__xludf.DUMMYFUNCTION("IF(OR(K17=""N/A"", K17=""missing"", K17=""none""), """", REGEXREPLACE( SUBSTITUTE(SUBSTITUTE(SUBSTITUTE(TO_TEXT(K17), CHAR(160),""""), UNICHAR(8239),""""), UNICHAR(8201),""""),""[+\-/(): )]"", """"))"),"349487174624") -> 349487174624 | M17: =IFERROR(__xludf.DUMMYFUNCTION("IF(L17="""","""", REGEXEXTRACT(REGEXREPLACE(L17,""x"", """"), ""[0-9]+""))"),"349487174624") -> 349487174624 | N17: =IF(LEFT(M17,2)="34", RIGHT(M17,LEN(M17)-2),M17) -> 9487174624 | O17: =IFERROR(__xludf.DUMMYFUNCTION("REGEXMATCH(TO_TEXT(N17), ""^[67]"")"),FALSE) -> FALSE | P17: =LEN(N17) -> 10 | Q17: =IF(AND(O17=TRUE, P17=9), "✅ VALID", "❌ INVALID") -> ❌ INVALID | R17: Spain | S17: 44809 | T17: =IFERROR(__xludf.DUMMYFUNCTION("IF(ISNUMBER(S17),TEXT(S17,""yyyy-MM-dd""),REGEXREPLACE(REGEXREPLACE(TO_TEXT(S17),""[^0-9a-zA-Z]+"",""-""),""[^0-9]*$"",""""))"),"2022-09-05") -> 2022-09-05 | U17: 2022-09-05 | Y17: 2022-09-05
A18: CUST-5016 | B18: ✅ Unique | C18: Nina Khan | D18: =IFERROR(__xludf.DUMMYFUNCTION("PROPER(REGEXREPLACE(TRIM(C18),""\s+"","" ""))"),"Nina Khan") -> Nina Khan | E18: =IFERROR(__xludf.DUMMYFUNCTION("IF(LEN(D18:D701), COUNTA(SPLIT(D18:D701,"" "")), """")"),2.0) -> 2 | F18: =IF(D18=G18,"✅","❌") -> ✅ | G18: =IFERROR(__xludf.DUMMYFUNCTION("REGEXEXTRACT(PROPER(SUBSTITUTE(TRIM(I18),""."","" "")),""^[^@]+"")"),"Nina Khan") -> Nina Khan | H18: =LOWER(TRIM(I18)) -> nina.khan@example.com | I18: Nina.Khan@Example.Com | J18: =IFERROR(__xludf.DUMMYFUNCTION("IF(REGEXMATCH(TRIM(I18),""^[A-Za-z0-9._%+-]+@[A-Za-z0-9.-]+\.[A-Za-z]{2,}$""),""✅ Valid"",""❌ Invalid"")"),"✅ Valid") -> ✅ Valid | K18: +3920245354 | L18: =IFERROR(__xludf.DUMMYFUNCTION("IF(OR(K18=""N/A"", K18=""missing"", K18=""none""), """", REGEXREPLACE( SUBSTITUTE(SUBSTITUTE(SUBSTITUTE(TO_TEXT(K18), CHAR(160),""""), UNICHAR(8239),""""), UNICHAR(8201),""""),""[+\-/(): )]"", """"))"),"3920245354") -> 3920245354 | M18: =IFERROR(__xludf.DUMMYFUNCTION("IF(L18="""","""", REGEXEXTRACT(REGEXREPLACE(L18,""x"", """"), ""[0-9]+""))"),"3920245354") -> 3920245354 | N18: =IF(LEFT(M18,2)="39", RIGHT(M18,LEN(M18)-2),M18) -> 20245354 | O18: =IFERROR(__xludf.DUMMYFUNCTION("REGEXMATCH(TO_TEXT(N18), ""^3"")"),FALSE) -> FALSE | P18: =LEN(N18) -> 8 | Q18: =IF(AND(O18=TRUE,OR(P18=9, P18=10 )), "✅ VALID", "❌ INVALID") -> ❌ INVALID | R18: Italy | S18: 45844.874 | T18: =IFERROR(__xludf.DUMMYFUNCTION("IF(ISNUMBER(S18),TEXT(S18,""yyyy-MM-dd""),REGEXREPLACE(REGEXREPLACE(TO_TEXT(S18),""[^0-9a-zA-Z]+"",""-""),""[^0-9]*$"",""""))"),"2025-07-06") -> 2025-07-06 | U18: 2025-07-06 | Y18: 2025-07-06
A19: CUST-5017 | B19: ✅ Unique | C19: Rita Lopez | D19: =IFERROR(__xludf.DUMMYFUNCTION("PROPER(REGEXREPLACE(TRIM(C19),""\s+"","" ""))"),"Rita Lopez") -> Rita Lopez | E19: =IFERROR(__xludf.DUMMYFUNCTION("IF(LEN(D19:D701), COUNTA(SPLIT(D19:D701,"" "")), """")"),2.0) -> 2 | F19: =IF(D19=G19,"✅","❌") -> ❌ | G19: Rita Lopze | H19: =LOWER(TRIM(I19)) -> rita.lopze@company.co.uk | I19: RITA.LOPZE@COMPANY.CO.UK | J19: =IFERROR(__xludf.DUMMYFUNCTION("IF(REGEXMATCH(TRIM(I19),""^[A-Za-z0-9._%+-]+@[A-Za-z0-9.-]+\.[A-Za-z]{2,}$""),""✅ Valid"",""❌ Invalid"")"),"✅ Valid") -> ✅ Valid | K19: +353+55796762 | L19: =IFERROR(__xludf.DUMMYFUNCTION("IF(OR(K19=""N/A"", K19=""missing"", K19=""none""), """", REGEXREPLACE( SUBSTITUTE(SUBSTITUTE(SUBSTITUTE(TO_TEXT(K19), CHAR(160),""""), UNICHAR(8239),""""), UNICHAR(8201),""""),""[+\-/(): )]"", """"))"),"35355796762") -> 35355796762 | M19: =IFERROR(__xludf.DUMMYFUNCTION("IF(L19="""","""", REGEXEXTRACT(REGEXREPLACE(L19,""x"", """"), ""[0-9]+""))"),"35355796762") -> 35355796762 | N19: =IF(LEFT(M19,3)="353", RIGHT(M19,LEN(M19)-3),M19) -> 55796762 | O19: =IFERROR(__xludf.DUMMYFUNCTION("REGEXMATCH(TO_TEXT(N19), ""^0(83|85|86|87|89)"")"),FALSE) -> FALSE | P19: =LEN(N19) -> 8 | Q19: =IF(AND(O19=TRUE, P16=10), "✅ VALID", "❌ INVALID") -> ❌ INVALID | R19: Ireland | S19: 45506 | T19: =IFERROR(__xludf.DUMMYFUNCTION("IF(ISNUMBER(S19),TEXT(S19,""yyyy-MM-dd""),REGEXREPLACE(REGEXREPLACE(TO_TEXT(S19),""[^0-9a-zA-Z]+"",""-""),""[^0-9]*$"",""""))"),"2024-08-02") -> 2024-08-02 | U19: 2024-08-02 | Y19: 2024-08-02
A20: CUST-5018 | B20: ✅ Unique | C20: KEN MULLER | D20: =IFERROR(__xludf.DUMMYFUNCTION("PROPER(REGEXREPLACE(TRIM(C20),""\s+"","" ""))"),"Ken Muller") -> Ken Muller | E20: =IFERROR(__xludf.DUMMYFUNCTION("IF(LEN(D20:D701), COUNTA(SPLIT(D20:D701,"" "")), """")"),2.0) -> 2 | F20: =IF(D20=G20,"✅","❌") -> ✅ | G20: =IFERROR(__xludf.DUMMYFUNCTION("REGEXEXTRACT(PROPER(SUBSTITUTE(TRIM(I20),""."","" "")),""^[^@]+"")"),"Ken Muller") -> Ken Muller | H20: =LOWER(TRIM(I20)) -> ken.muller@gmail.com | I20: ken.muller@gmail.com | J20: =IFERROR(__xludf.DUMMYFUNCTION("IF(REGEXMATCH(TRIM(I20),""^[A-Za-z0-9._%+-]+@[A-Za-z0-9.-]+\.[A-Za-z]{2,}$""),""✅ Valid"",""❌ Invalid"")"),"✅ Valid") -> ✅ Valid | K20: +48286084601 | L20: =IFERROR(__xludf.DUMMYFUNCTION("IF(K20=""N/A"", """", REGEXREPLACE( SUBSTITUTE(SUBSTITUTE(SUBSTITUTE(TO_TEXT(K20), CHAR(160),""""), UNICHAR(8239),""""), UNICHAR(8201),""""),""[+\-/(): )]"", """"))"),"48286084601") -> 48286084601 | M20: =IFERROR(__xludf.DUMMYFUNCTION("IF(L20="""","""", REGEXEXTRACT(REGEXREPLACE(L20,""x"", """"), ""[0-9]+""))"),"48286084601") -> 48286084601 | N20: =IF(LEFT(M20,2)="48", RIGHT(M20,LEN(M20)-2),M20) -> 286084601 | O20: =IFERROR(__xludf.DUMMYFUNCTION("REGEXMATCH(TO_TEXT(N20), ""^(5[013679]|6[069]|7[2-9]|88)"")"),FALSE) -> FALSE | Q20: =IF(AND(O20=TRUE, P20=9), "✅ VALID", "❌ INVALID") -> ❌ INVALID | R20: Poland | S20: 44601 | T20: =IFERROR(__xludf.DUMMYFUNCTION("IF(ISNUMBER(S20),TEXT(S20,""yyyy-MM-dd""),REGEXREPLACE(REGEXREPLACE(TO_TEXT(S20),""[^0-9a-zA-Z]+"",""-""),""[^0-9]*$"",""""))"),"2022-02-09") -> 2022-02-09 | U20: 2022-02-09 | Y20: 2022-02-09
A21: CUST-5019 | B21: ✅ Unique | C21: Gabe Khan | D21: =IFERROR(__xludf.DUMMYFUNCTION("PROPER(REGEXREPLACE(TRIM(C21),""\s+"","" ""))"),"Gabe Khan") -> Gabe Khan | E21: =IFERROR(__xludf.DUMMYFUNCTION("IF(LEN(D21:D701), COUNTA(SPLIT(D21:D701,"" "")), """")"),2.0) -> 2 | F21: =IF(D21=G21,"✅","❌") -> ✅ | G21: =IFERROR(__xludf.DUMMYFUNCTION("REGEXEXTRACT(PROPER(SUBSTITUTE(TRIM(I21),""."","" "")),""^[^@]+"")"),"Gabe Khan") -> Gabe Khan | H21: =LOWER(TRIM(I21)) -> gabe.khan@company.co.uk | I21: gabe.khan@company.co.uk | J21: =IFERROR(__xludf.DUMMYFUNCTION("IF(REGEXMATCH(TRIM(I21),""^[A-Za-z0-9._%+-]+@[A-Za-z0-9.-]+\.[A-Za-z]{2,}$""),""✅ Valid"",""❌ Invalid"")"),"✅ Valid") -> ✅ Valid | K21: 759927642 | L21: =IFERROR(__xludf.DUMMYFUNCTION("IF(OR(K21=""N/A"", K21=""missing"", K21=""none""), """", REGEXREPLACE( SUBSTITUTE(SUBSTITUTE(SUBSTITUTE(TO_TEXT(K21), CHAR(160),""""), UNICHAR(8239),""""), UNICHAR(8201),""""),""[+\-/(): )]"", """"))"),"759927642") -> 759927642 | M21: =IFERROR(__xludf.DUMMYFUNCTION("IF(L21="""","""", REGEXEXTRACT(REGEXREPLACE(L21,""x"", """"), ""[0-9]+""))"),"759927642") -> 759927642 | N21: =IF(LEFT(M21,2)="49", RIGHT(M21,LEN(M21)-2),M21) -> 759927642 | O21: =IFERROR(__xludf.DUMMYFUNCTION("REGEXMATCH(TO_TEXT(N21), ""^0(15|16|17)"")"),FALSE) -> FALSE | P21: =LEN(N21) -> 9 | Q21: =IF(AND(O21=TRUE,OR(P21=10, P21=11)), "✅ VALID", "❌ INVALID") -> ❌ INVALID | R21: Germany | S21: 45791 | T21: =IFERROR(__xludf.DUMMYFUNCTION("IF(ISNUMBER(S21),TEXT(S21,""yyyy-MM-dd""),REGEXREPLACE(REGEXREPLACE(TO_TEXT(S21),""[^0-9a-zA-Z]+"",""-""),""[^0-9]*$"",""""))"),"2025-05-14") -> 2025-05-14 | U21: 2025-05-14 | Y21: 2025-05-14
A22: CUST-5020 | B22: ✅ Unique | C22: Xenia Rossi | D22: =IFERROR(__xludf.DUMMYFUNCTION("PROPER(REGEXREPLACE(TRIM(C22),""\s+"","" ""))"),"Xenia Rossi") -> Xenia Rossi | E22: =IFERROR(__xludf.DUMMYFUNCTION("IF(LEN(D22:D701), COUNTA(SPLIT(D22:D701,"" "")), """")"),2.0) -> 2 | F22: =IF(D22=G22,"✅","❌") -> ✅ | G22: =IFERROR(__xludf.DUMMYFUNCTION("REGEXEXTRACT(PROPER(SUBSTITUTE(TRIM(I22),""."","" "")),""^[^@]+"")"),"Xenia Rossi") -> Xenia Rossi | H22: =LOWER(TRIM(I22)) -> xenia.rossi@shop.io | I22: XENIA.ROSSI@SHOP.IO | J22: =IFERROR(__xludf.DUMMYFUNCTION("IF(REGEXMATCH(TRIM(I22),""^[A-Za-z0-9._%+-]+@[A-Za-z0-9.-]+\.[A-Za-z]{2,}$""),""✅ Valid"",""❌ Invalid"")"),"✅ Valid") -> ✅ Valid | K22: 296645265 | L22: =IFERROR(__xludf.DUMMYFUNCTION("IF(OR(K22=""N/A"", K22=""missing"", K22=""none""), """", REGEXREPLACE( SUBSTITUTE(SUBSTITUTE(SUBSTITUTE(TO_TEXT(K22), CHAR(160),""""), UNICHAR(8239),""""), UNICHAR(8201),""""),""[+\-/(): )]"", """"))"),"296645265") -> 296645265 | M22: =IFERROR(__xludf.DUMMYFUNCTION("IF(L22="""","""", REGEXEXTRACT(REGEXREPLACE(L22,""x"", """"), ""[0-9]+""))"),"296645265") -> 296645265 | N22: =IF(LEFT(M22,3)="353", RIGHT(M22,LEN(M22)-3),M22) -> 296645265 | O22: =IFERROR(__xludf.DUMMYFUNCTION("REGEXMATCH(TO_TEXT(N22), ""^0(83|85|86|87|89)"")"),FALSE) -> FALSE | P22: =LEN(N22) -> 9 | Q22: =IF(AND(O22=TRUE, P19=10), "✅ VALID", "❌ INVALID") -> ❌ INVALID | R22: Ireland | S22: 45550 | T22: =IFERROR(__xludf.DUMMYFUNCTION("IF(ISNUMBER(S22),TEXT(S22,""yyyy-MM-dd""),REGEXREPLACE(REGEXREPLACE(TO_TEXT(S22),""[^0-9a-zA-Z]+"",""-""),""[^0-9]*$"",""""))"),"2024-09-15") -> 2024-09-15 | U22: 2024-09-15 | Y22: 2024-09-15
A23: CUST-5021 | B23: ✅ Unique | C23: Uma Brown | D23: =IFERROR(__xludf.DUMMYFUNCTION("PROPER(REGEXREPLACE(TRIM(C23),""\s+"","" ""))"),"Uma Brown") -> Uma Brown | E23: =IFERROR(__xludf.DUMMYFUNCTION("IF(LEN(D23:D701), COUNTA(SPLIT(D23:D701,"" "")), """")"),2.0) -> 2 | F23: =IF(D23=G23,"✅","❌") -> ✅ | G23: =IFERROR(__xludf.DUMMYFUNCTION("REGEXEXTRACT(PROPER(SUBSTITUTE(TRIM(I23),""."","" "")),""^[^@]+"")"),"Uma Brown") -> Uma Brown | H23: =LOWER(TRIM(I23)) -> uma.brown@outlook.com | I23: uma.brown@outlook.com | J23: =IFERROR(__xludf.DUMMYFUNCTION("IF(REGEXMATCH(TRIM(I23),""^[A-Za-z0-9._%+-]+@[A-Za-z0-9.-]+\.[A-Za-z]{2,}$""),""✅ Valid"",""❌ Invalid"")"),"✅ Valid") -> ✅ Valid | K23: missing | L23: =IFERROR(__xludf.DUMMYFUNCTION("IF(OR(K23=""N/A"", K23=""missing"", K23=""none""), """", REGEXREPLACE( SUBSTITUTE(SUBSTITUTE(SUBSTITUTE(TO_TEXT(K23), CHAR(160),""""), UNICHAR(8239),""""), UNICHAR(8201),""""),""[+\-/(): )]"", """"))"),"") | M23: =IFERROR(__xludf.DUMMYFUNCTION("IF(L23="""","""", REGEXEXTRACT(REGEXREPLACE(L23,""x"", """"), ""[0-9]+""))"),"") | N23: =IF(LEFT(M23,2)="39", RIGHT(M23,LEN(M23)-2),M23) | O23: =IFERROR(__xludf.DUMMYFUNCTION("REGEXMATCH(TO_TEXT(N23), ""^3"")"),FALSE) -> FALSE | P23: =LEN(N23) -> 0 | Q23: =IF(AND(O23=TRUE,OR(P23=9, P23=10 )), "✅ VALID", "❌ INVALID") -> ❌ INVALID | R23: Italy | S23: 45446 | T23: =IFERROR(__xludf.DUMMYFUNCTION("IF(ISNUMBER(S23),TEXT(S23,""yyyy-MM-dd""),REGEXREPLACE(REGEXREPLACE(TO_TEXT(S23),""[^0-9a-zA-Z]+"",""-""),""[^0-9]*$"",""""))"),"2024-06-03") -> 2024-06-03 | U23: 2024-06-03 | Y23: 2024-06-03
A24: CUST-5022 | B24: ✅ Unique | C24: Adam Johnson | D24: =IFERROR(__xludf.DUMMYFUNCTION("PROPER(REGEXREPLACE(TRIM(C24),""\s+"","" ""))"),"Adam Johnson") -> Adam Johnson | E24: =IFERROR(__xludf.DUMMYFUNCTION("IF(LEN(D24:D701), COUNTA(SPLIT(D24:D701,"" "")), """")"),2.0) -> 2 | K24: 04528 214 956 | R24: Poland | S24: 24/12/2022
A25: CUST-5023 | B25: ✅ Unique | C25: Jade King | D25: =IFERROR(__xludf.DUMMYFUNCTION("PROPER(REGEXREPLACE(TRIM(C25),""\s+"","" ""))"),"Jade King") -> Jade King | E25: =IFERROR(__xludf.DUMMYFUNCTION("IF(LEN(D25:D701), COUNTA(SPLIT(D25:D701,"" "")), """")"),2.0) -> 2 | F25: =IF(D25=G25,"✅","❌") -> ❌ | G25: Jadek Ing | H25: =LOWER(TRIM(I25)) -> jadek.ing@outlook.com | I25: jadek.ing@outlook.com | J25: =IFERROR(__xludf.DUMMYFUNCTION("IF(REGEXMATCH(TRIM(I25),""^[A-Za-z0-9._%+-]+@[A-Za-z0-9.-]+\.[A-Za-z]{2,}$""),""✅ Valid"",""❌ Invalid"")"),"✅ Valid") -> ✅ Valid | K25: +48-946-661012 | L25: =IFERROR(__xludf.DUMMYFUNCTION("IF(K25=""N/A"", """", REGEXREPLACE( SUBSTITUTE(SUBSTITUTE(SUBSTITUTE(TO_TEXT(K25), CHAR(160),""""), UNICHAR(8239),""""), UNICHAR(8201),""""),""[+\-/(): )]"", """"))"),"48946661012") -> 48946661012 | M25: =IFERROR(__xludf.DUMMYFUNCTION("IF(L25="""","""", REGEXEXTRACT(REGEXREPLACE(L25,""x"", """"), ""[0-9]+""))"),"48946661012") -> 48946661012 | N25: =IF(LEFT(M25,2)="48", RIGHT(M25,LEN(M25)-2),M25) -> 946661012 | O25: =IFERROR(__xludf.DUMMYFUNCTION("REGEXMATCH(TO_TEXT(N25), ""^(5[013679]|6[069]|7[2-9]|88)"")"),FALSE) -> FALSE | Q25: =IF(AND(O25=TRUE, P25=9), "✅ VALID", "❌ INVALID") -> ❌ INVALID | R25: Poland | S25: 45216 | T25: =IFERROR(__xludf.DUMMYFUNCTION("IF(ISNUMBER(S25),TEXT(S25,""yyyy-MM-dd""),REGEXREPLACE(REGEXREPLACE(TO_TEXT(S25),""[^0-9a-zA-Z]+"",""-""),""[^0-9]*$"",""""))"),"2023-10-17") -> 2023-10-17 | U25: 2023-10-17 | Y25: 2023-10-17
A26: CUST-5024 | B26: ✅ Unique | C26: Omar Martinez | D26: =IFERROR(__xludf.DUMMYFUNCTION("PROPER(REGEXREPLACE(TRIM(C26),""\s+"","" ""))"),"Omar Martinez") -> Omar Martinez | E26: =IFERROR(__xludf.DUMMYFUNCTION("IF(LEN(D26:D701), COUNTA(SPLIT(D26:D701,"" "")), """")"),2.0) -> 2 | F26: =IF(D26=G26,"✅","❌") -> ✅ | G26: =IFERROR(__xludf.DUMMYFUNCTION("REGEXEXTRACT(PROPER(SUBSTITUTE(TRIM(I26),""."","" "")),""^[^@]+"")"),"Omar Martinez") -> Omar Martinez | H26: =LOWER(TRIM(I26)) -> omar.martinez@company.co.uk | I26: Omar.Martinez@Company.Co.Uk | J26: =IFERROR(__xludf.DUMMYFUNCTION("IF(REGEXMATCH(TRIM(I26),""^[A-Za-z0-9._%+-]+@[A-Za-z0-9.-]+\.[A-Za-z]{2,}$""),""✅ Valid"",""❌ Invalid"")"),"✅ Valid") -> ✅ Valid | K26: +49-753-01379 | L26: =IFERROR(__xludf.DUMMYFUNCTION("IF(OR(K26=""N/A"", K26=""missing"", K26=""none""), """", REGEXREPLACE( SUBSTITUTE(SUBSTITUTE(SUBSTITUTE(TO_TEXT(K26), CHAR(160),""""), UNICHAR(8239),""""), UNICHAR(8201),""""),""[+\-/(): )]"", """"))"),"4975301379") -> 4975301379 | M26: =IFERROR(__xludf.DUMMYFUNCTION("IF(L26="""","""", REGEXEXTRACT(REGEXREPLACE(L26,""x"", """"), ""[0-9]+""))"),"4975301379") -> 4975301379 | N26: =IF(LEFT(M26,2)="49", RIGHT(M26,LEN(M26)-2),M26) -> 75301379 | O26: =IFERROR(__xludf.DUMMYFUNCTION("REGEXMATCH(TO_TEXT(N26), ""^0(15|16|17)"")"),FALSE) -> FALSE | P26: =LEN(N26) -> 8 | Q26: =IF(AND(O26=TRUE,OR(P26=10, P26=11)), "✅ VALID", "❌ INVALID") -> ❌ INVALID | R26: Germany | S26: 45461 | T26: =IFERROR(__xludf.DUMMYFUNCTION("IF(ISNUMBER(S26),TEXT(S26,""yyyy-MM-dd""),REGEXREPLACE(REGEXREPLACE(TO_TEXT(S26),""[^0-9a-zA-Z]+"",""-""),""[^0-9]*$"",""""))"),"2024-06-18") -> 2024-06-18 | U26: 2024-06-18 | Y26: 2024-06-18
A27: CUST-5025 | B27: ✅ Unique | C27: Qi Kowalczyk | D27: =IFERROR(__xludf.DUMMYFUNCTION("PROPER(REGEXREPLACE(TRIM(C27),""\s+"","" ""))"),"Qi Kowalczyk") -> Qi Kowalczyk | E27: =IFERROR(__xludf.DUMMYFUNCTION("IF(LEN(D27:D701), COUNTA(SPLIT(D27:D701,"" "")), """")"),2.0) -> 2 | F27: =IF(D27=G27,"✅","❌") -> ✅ | G27: =IFERROR(__xludf.DUMMYFUNCTION("REGEXEXTRACT(PROPER(SUBSTITUTE(TRIM(I27),""."","" "")),""^[^@]+"")"),"Qi Kowalczyk") -> Qi Kowalczyk | H27: =LOWER(TRIM(I27)) -> qi.kowalczyk@example.com | I27: qi.kowalczyk@example.com | J27: =IFERROR(__xludf.DUMMYFUNCTION("IF(REGEXMATCH(TRIM(I27),""^[A-Za-z0-9._%+-]+@[A-Za-z0-9.-]+\.[A-Za-z]{2,}$""),""✅ Valid"",""❌ Invalid"")"),"✅ Valid") -> ✅ Valid | K27: tel:+1769121343 | L27: =IFERROR(__xludf.DUMMYFUNCTION("IF(OR(K27=""N/A"", K27=""missing"", K27=""none""), """", REGEXREPLACE( SUBSTITUTE(SUBSTITUTE(SUBSTITUTE(TO_TEXT(K27), CHAR(160),""""), UNICHAR(8239),""""), UNICHAR(8201),""""),""[+\-/(): )]"", """"))"),"tel1769121343") -> tel1769121343 | M27: =IFERROR(__xludf.DUMMYFUNCTION("IF(L27="""","""", REGEXEXTRACT(REGEXREPLACE(L27,""x"", """"), ""[0-9]+""))"),"1769121343") -> 1769121343 | N27: =IF(LEFT(M27,1)="1", RIGHT(M27,LEN(M27)-1),M27) -> 769121343 | O27: =IFERROR(__xludf.DUMMYFUNCTION("REGEXMATCH(TO_TEXT(N27), ""^[2-9][0-9]{9}$"")"),FALSE) -> FALSE | P27: =LEN(N27) -> 9 | Q27: =IF(AND(O27=TRUE, P27=10), "✅ VALID", "❌ INVALID") -> ❌ INVALID | R27: USA | S27: 45276.565 | T27: =IFERROR(__xludf.DUMMYFUNCTION("IF(ISNUMBER(S27),TEXT(S27,""yyyy-MM-dd""),REGEXREPLACE(REGEXREPLACE(TO_TEXT(S27),""[^0-9a-zA-Z]+"",""-""),""[^0-9]*$"",""""))"),"2023-12-16") -> 2023-12-16 | U27: 2023-12-16 | Y27: 2023-12-16
A28: CUST-5026 | B28: ✅ Unique | C28: Adam King | D28: =IFERROR(__xludf.DUMMYFUNCTION("PROPER(REGEXREPLACE(TRIM(C28),""\s+"","" ""))"),"Adam King") -> Adam King | E28: =IFERROR(__xludf.DUMMYFUNCTION("IF(LEN(D28:D701), COUNTA(SPLIT(D28:D701,"" "")), """")"),2.0) -> 2 | F28: =IF(D28=G28,"✅","❌") -> ✅ | G28: =IFERROR(__xludf.DUMMYFUNCTION("REGEXEXTRACT(PROPER(SUBSTITUTE(TRIM(I28),""."","" "")),""^[^@]+"")"),"Adam King") -> Adam King | H28: =LOWER(TRIM(I28)) -> adam.king@company.co.uk | I28: adam.king@company.co.uk | J28: =IFERROR(__xludf.DUMMYFUNCTION("IF(REGEXMATCH(TRIM(I28),""^[A-Za-z0-9._%+-]+@[A-Za-z0-9.-]+\.[A-Za-z]{2,}$""),""✅ Valid"",""❌ Invalid"")"),"✅ Valid") -> ✅ Valid | K28: 46192x638 | L28: =IFERROR(__xludf.DUMMYFUNCTION("IF(OR(K28=""N/A"", K28=""missing"", K28=""none""), """", REGEXREPLACE( SUBSTITUTE(SUBSTITUTE(SUBSTITUTE(TO_TEXT(K28), CHAR(160),""""), UNICHAR(8239),""""), UNICHAR(8201),""""),""[+\-/(): )]"", """"))"),"46192x638") -> 46192x638 | M28: =IFERROR(__xludf.DUMMYFUNCTION("IF(L28="""","""", REGEXEXTRACT(REGEXREPLACE(L28,""x"", """"), ""[0-9]+""))"),"46192638") -> 46192638 | N28: =IF(LEFT(M28,2)="33", RIGHT(M28,LEN(M28)-2),M28) -> 46192638 | O28: =IFERROR(__xludf.DUMMYFUNCTION("REGEXMATCH(TO_TEXT(N28), ""^0[67]"")"),FALSE) -> FALSE | P28: =LEN(N28) -> 8 | Q28: =IF(AND(O28=TRUE, P28=9), "✅ VALID", "❌ INVALID") -> ❌ INVALID | R28: France | S28: 45830 | T28: =IFERROR(__xludf.DUMMYFUNCTION("IF(ISNUMBER(S28),TEXT(S28,""yyyy-MM-dd""),REGEXREPLACE(REGEXREPLACE(TO_TEXT(S28),""[^0-9a-zA-Z]+"",""-""),""[^0-9]*$"",""""))"),"2025-06-22") -> 2025-06-22 | U28: 2025-06-22 | Y28: 2025-06-22
A29: CUST-5027 | B29: ✅ Unique | C29: Daria Kowalski | D29: =IFERROR(__xludf.DUMMYFUNCTION("PROPER(REGEXREPLACE(TRIM(C29),""\s+"","" ""))"),"Daria Kowalski") -> Daria Kowalski | E29: =IFERROR(__xludf.DUMMYFUNCTION("IF(LEN(D29:D701), COUNTA(SPLIT(D29:D701,"" "")), """")"),2.0) -> 2 | F29: =IF(D29=G29,"✅","❌") -> ✅ | G29: =IFERROR(__xludf.DUMMYFUNCTION("REGEXEXTRACT(PROPER(SUBSTITUTE(TRIM(I29),""."","" "")),""^[^@]+"")"),"Daria Kowalski") -> Daria Kowalski | H29: =LOWER(TRIM(I29)) -> daria.kowalski@outlook.com | I29: daria.kowalski@outlook.com | J29: =IFERROR(__xludf.DUMMYFUNCTION("IF(REGEXMATCH(TRIM(I29),""^[A-Za-z0-9._%+-]+@[A-Za-z0-9.-]+\.[A-Za-z]{2,}$""),""✅ Valid"",""❌ Invalid"")"),"✅ Valid") -> ✅ Valid | K29: +1 682 62568391 | L29: =IFERROR(__xludf.DUMMYFUNCTION("IF(OR(K29=""N/A"", K29=""missing"", K29=""none""), """", REGEXREPLACE( SUBSTITUTE(SUBSTITUTE(SUBSTITUTE(TO_TEXT(K29), CHAR(160),""""), UNICHAR(8239),""""), UNICHAR(8201),""""),""[+\-/(): )]"", """"))"),"168262568391") -> 168262568391 | M29: =IFERROR(__xludf.DUMMYFUNCTION("IF(L29="""","""", REGEXEXTRACT(REGEXREPLACE(L29,""x"", """"), ""[0-9]+""))"),"168262568391") -> 168262568391 | N29: =IF(LEFT(M29,1)="1", RIGHT(M29,LEN(M29)-1),M29) -> 68262568391 | O29: =IFERROR(__xludf.DUMMYFUNCTION("REGEXMATCH(TO_TEXT(N29), ""^[2-9][0-9]{9}$"")"),FALSE) -> FALSE | P29: =LEN(N29) -> 11 | Q29: =IF(AND(O29=TRUE, P29=10), "✅ VALID", "❌ INVALID") -> ❌ INVALID | R29: USA | S29: 44807 | T29: =IFERROR(__xludf.DUMMYFUNCTION("IF(ISNUMBER(S29),TEXT(S29,""yyyy-MM-dd""),REGEXREPLACE(REGEXREPLACE(TO_TEXT(S29),""[^0-9a-zA-Z]+"",""-""),""[^0-9]*$"",""""))"),"2022-09-03") -> 2022-09-03 | U29: 2022-09-03 | Y29: 2022-09-03
A30: CUST-5028 | B30: ✅ Unique | C30: Ken Young | D30: =IFERROR(__xludf.DUMMYFUNCTION("PROPER(REGEXREPLACE(TRIM(C30),""\s+"","" ""))"),"Ken Young") -> Ken Young | E30: =IFERROR(__xludf.DUMMYFUNCTION("IF(LEN(D30:D701), COUNTA(SPLIT(D30:D701,"" "")), """")"),2.0) -> 2 | F30: =IF(D30=G30,"✅","❌") -> ✅ | G30: =IFERROR(__xludf.DUMMYFUNCTION("REGEXEXTRACT(PROPER(SUBSTITUTE(TRIM(I30),""."","" "")),""^[^@]+"")"),"Ken Young") -> Ken Young | H30: =LOWER(TRIM(I30)) -> ken.young@company.co.uk | I30: ken.young@company.co.uk | J30: =IFERROR(__xludf.DUMMYFUNCTION("IF(REGEXMATCH(TRIM(I30),""^[A-Za-z0-9._%+-]+@[A-Za-z0-9.-]+\.[A-Za-z]{2,}$""),""✅ Valid"",""❌ Invalid"")"),"✅ Valid") -> ✅ Valid | K30: +353-399-989702 | L30: =IFERROR(__xludf.DUMMYFUNCTION("IF(OR(K30=""N/A"", K30=""missing"", K30=""none""), """", REGEXREPLACE( SUBSTITUTE(SUBSTITUTE(SUBSTITUTE(TO_TEXT(K30), CHAR(160),""""), UNICHAR(8239),""""), UNICHAR(8201),""""),""[+\-/(): )]"", """"))"),"353399989702") -> 353399989702 | M30: =IFERROR(__xludf.DUMMYFUNCTION("IF(L30="""","""", REGEXEXTRACT(REGEXREPLACE(L30,""x"", """"), ""[0-9]+""))"),"353399989702") -> 353399989702 | N30: =IF(LEFT(M30,3)="353", RIGHT(M30,LEN(M30)-3),M30) -> 399989702 | O30: =IFERROR(__xludf.DUMMYFUNCTION("REGEXMATCH(TO_TEXT(N30), ""^0(83|85|86|87|89)"")"),FALSE) -> FALSE | P30: =LEN(N30) -> 9 | Q30: =IF(AND(O30=TRUE, P27=10), "✅ VALID", "❌ INVALID") -> ❌ INVALID | R30: Ireland | S30: 44689 | T30: =IFERROR(__xludf.DUMMYFUNCTION("IF(ISNUMBER(S30),TEXT(S30,""yyyy-MM-dd""),REGEXREPLACE(REGEXREPLACE(TO_TEXT(S30),""[^0-9a-zA-Z]+"",""-""),""[^0-9]*$"",""""))"),"2022-05-08") -> 2022-05-08 | U30: 2022-05-08 | Y30: 2022-05-08
A31: CUST-5029 | B31: ✅ Unique | C31: Vlad Kowalski | D31: =IFERROR(__xludf.DUMMYFUNCTION("PROPER(REGEXREPLACE(TRIM(C31),""\s+"","" ""))"),"Vlad Kowalski") -> Vlad Kowalski | E31: =IFERROR(__xludf.DUMMYFUNCTION("IF(LEN(D31:D701), COUNTA(SPLIT(D31:D701,"" "")), """")"),2.0) -> 2 | F31: =IF(D31=G31,"✅","❌") -> ✅ | G31: =IFERROR(__xludf.DUMMYFUNCTION("REGEXEXTRACT(PROPER(SUBSTITUTE(TRIM(I31),""."","" "")),""^[^@]+"")"),"Vlad Kowalski") -> Vlad Kowalski | H31: =LOWER(TRIM(I31)) -> vlad.kowalski@yahoo.com | I31: vlad.kowalski@yahoo.com | J31: =IFERROR(__xludf.DUMMYFUNCTION("IF(REGEXMATCH(TRIM(I31),""^[A-Za-z0-9._%+-]+@[A-Za-z0-9.-]+\.[A-Za-z]{2,}$""),""✅ Valid"",""❌ Invalid"")"),"✅ Valid") -> ✅ Valid | K31: +1-943-2396635 | L31: =IFERROR(__xludf.DUMMYFUNCTION("IF(OR(K31=""N/A"", K31=""missing"", K31=""none""), """", REGEXREPLACE( SUBSTITUTE(SUBSTITUTE(SUBSTITUTE(TO_TEXT(K31), CHAR(160),""""), UNICHAR(8239),""""), UNICHAR(8201),""""),""[+\-/(): )]"", """"))"),"19432396635") -> 19432396635 | M31: =IFERROR(__xludf.DUMMYFUNCTION("IF(L31="""","""", REGEXEXTRACT(REGEXREPLACE(L31,""x"", """"), ""[0-9]+""))"),"19432396635") -> 19432396635 | N31: =IF(LEFT(M31,1)="1", RIGHT(M31,LEN(M31)-1),M31) -> 9432396635 | O31: =IFERROR(__xludf.DUMMYFUNCTION("REGEXMATCH(TO_TEXT(N31), ""^[2-9][0-9]{9}$"")"),TRUE) -> TRUE | P31: =LEN(N31) -> 10 | Q31: =IF(AND(O31=TRUE, P31=10), "✅ VALID", "❌ INVALID") -> ✅ VALID | R31: USA | S31: 45177 | T31: =IFERROR(__xludf.DUMMYFUNCTION("IF(ISNUMBER(S31),TEXT(S31,""yyyy-MM-dd""),REGEXREPLACE(REGEXREPLACE(TO_TEXT(S31),""[^0-9a-zA-Z]+"",""-""),""[^0-9]*$"",""""))"),"2023-09-08") -> 2023-09-08 | U31: 2023-09-08 | Y31: 2023-09-08
A32: CUST-5030 | B32: ✅ Unique | C32: Sam Johnson | D32: =IFERROR(__xludf.DUMMYFUNCTION("PROPER(REGEXREPLACE(TRIM(C32),""\s+"","" ""))"),"Sam Johnson") -> Sam Johnson | E32: =IFERROR(__xludf.DUMMYFUNCTION("IF(LEN(D32:D701), COUNTA(SPLIT(D32:D701,"" "")), """")"),2.0) -> 2 | F32: =IF(D32=G32,"✅","❌") -> ✅ | G32: =IFERROR(__xludf.DUMMYFUNCTION("REGEXEXTRACT(PROPER(SUBSTITUTE(TRIM(I32),""."","" "")),""^[^@]+"")"),"Sam Johnson") -> Sam Johnson | H32: =LOWER(TRIM(I32)) -> sam.johnson@yahoo.com | I32: sam.johnson@yahoo.com | J32: =IFERROR(__xludf.DUMMYFUNCTION("IF(REGEXMATCH(TRIM(I32),""^[A-Za-z0-9._%+-]+@[A-Za-z0-9.-]+\.[A-Za-z]{2,}$""),""✅ Valid"",""❌ Invalid"")"),"✅ Valid") -> ✅ Valid | K32: (404) 87661 | L32: =IFERROR(__xludf.DUMMYFUNCTION("IF(OR(K32=""N/A"", K32=""missing"", K32=""none""), """", REGEXREPLACE( SUBSTITUTE(SUBSTITUTE(SUBSTITUTE(TO_TEXT(K32), CHAR(160),""""), UNICHAR(8239),""""), UNICHAR(8201),""""),""[+\-/(): )]"", """"))"),"40487661") -> 40487661 | M32: =IFERROR(__xludf.DUMMYFUNCTION("IF(L32="""","""", REGEXEXTRACT(REGEXREPLACE(L32,""x"", """"), ""[0-9]+""))"),"40487661") -> 40487661 | N32: =IF(LEFT(M32,3)="353", RIGHT(M32,LEN(M32)-3),M32) -> 40487661 | O32: =IFERROR(__xludf.DUMMYFUNCTION("REGEXMATCH(TO_TEXT(N32), ""^0(83|85|86|87|89)"")"),FALSE) -> FALSE | P32: =LEN(N32) -> 8 | Q32: =IF(AND(O32=TRUE, P29=10), "✅ VALID", "❌ INVALID") -> ❌ INVALID | R32: Ireland | S32: 11.01.2023 12:33 | T32: =IFERROR(__xludf.DUMMYFUNCTION("IF(ISNUMBER(S32),TEXT(S32,""yyyy-MM-dd""),REGEXREPLACE(REGEXREPLACE(TO_TEXT(S32),""[^0-9a-zA-Z]+"",""-""),""[^0-9]*$"",""""))"),"11-01-2023-12-33") -> 11-01-2023-12-33 | U32: =TEXT(T32,"yyyy-MM-dd") -> 11-01-2023-12-33 | V32: =IFERROR(__xludf.DUMMYFUNCTION("REGEXEXTRACT(U32,""^\d{2}-\d{2}-\d{4}"")"),"11-01-2023") -> 11-01-2023 | W32: 2023-01-11 | Y32: 2023-01-11
A33: CUST-5031 | B33: ✅ Unique | C33: Ken Nowak | D33: =IFERROR(__xludf.DUMMYFUNCTION("PROPER(REGEXREPLACE(TRIM(C33),""\s+"","" ""))"),"Ken Nowak") -> Ken Nowak | E33: =IFERROR(__xludf.DUMMYFUNCTION("IF(LEN(D33:D701), COUNTA(SPLIT(D33:D701,"" "")), """")"),2.0) -> 2 | F33: =IF(D33=G33,"✅","❌") -> ✅ | G33: =IFERROR(__xludf.DUMMYFUNCTION("REGEXEXTRACT(PROPER(SUBSTITUTE(TRIM(I33),""."","" "")),""^[^@]+"")"),"Ken Nowak") -> Ken Nowak | H33: =LOWER(TRIM(I33)) -> ken.nowak@company.co.uk | I33: ken.nowak@company.co.uk | J33: =IFERROR(__xludf.DUMMYFUNCTION("IF(REGEXMATCH(TRIM(I33),""^[A-Za-z0-9._%+-]+@[A-Za-z0-9.-]+\.[A-Za-z]{2,}$""),""✅ Valid"",""❌ Invalid"")"),"✅ Valid") -> ✅ Valid | K33: 858835x482 | L33: =IFERROR(__xludf.DUMMYFUNCTION("IF(OR(K33=""N/A"", K33=""missing"", K33=""none""), """", REGEXREPLACE( SUBSTITUTE(SUBSTITUTE(SUBSTITUTE(TO_TEXT(K33), CHAR(160),""""), UNICHAR(8239),""""), UNICHAR(8201),""""),""[+\-/(): )]"", """"))"),"858835x482") -> 858835x482 | M33: =IFERROR(__xludf.DUMMYFUNCTION("IF(L33="""","""", REGEXEXTRACT(REGEXREPLACE(L33,""x"", """"), ""[0-9]+""))"),"858835482") -> 858835482 | N33: =IF(LEFT(M33,3)="353", RIGHT(M33,LEN(M33)-3),M33) -> 858835482 | O33: =IFERROR(__xludf.DUMMYFUNCTION("REGEXMATCH(TO_TEXT(N33), ""^0(83|85|86|87|89)"")"),FALSE) -> FALSE | P33: =LEN(N33) -> 9 | Q33: =IF(AND(O33=TRUE, P30=10), "✅ VALID", "❌ INVALID") -> ❌ INVALID | R33: Ireland | S33: 44707 | T33: =IFERROR(__xludf.DUMMYFUNCTION("IF(ISNUMBER(S33),TEXT(S33,""yyyy-MM-dd""),REGEXREPLACE(REGEXREPLACE(TO_TEXT(S33),""[^0-9a-zA-Z]+"",""-""),""[^0-9]*$"",""""))"),"2022-05-26") -> 2022-05-26 | U33: 2022-05-26 | Y33: 2022-05-26
A34: CUST-5032 | B34: ✅ Unique | C34: Wiktor Rodriguez | D34: =IFERROR(__xludf.DUMMYFUNCTION("PROPER(REGEXREPLACE(TRIM(C34),""\s+"","" ""))"),"Wiktor Rodriguez") -> Wiktor Rodriguez | E34: =IFERROR(__xludf.DUMMYFUNCTION("IF(LEN(D34:D701), COUNTA(SPLIT(D34:D701,"" "")), """")"),2.0) -> 2 | F34: =IF(D34=G34,"✅","❌") -> ✅ | G34: =IFERROR(__xludf.DUMMYFUNCTION("REGEXEXTRACT(PROPER(SUBSTITUTE(TRIM(I34),""."","" "")),""^[^@]+"")"),"Wiktor Rodriguez") -> Wiktor Rodriguez | H34: =LOWER(TRIM(I34)) -> wiktor.rodriguez@example.com | I34: wiktor.rodriguez@example.com | J34: =IFERROR(__xludf.DUMMYFUNCTION("IF(REGEXMATCH(TRIM(I34),""^[A-Za-z0-9._%+-]+@[A-Za-z0-9.-]+\.[A-Za-z]{2,}$""),""✅ Valid"",""❌ Invalid"")"),"✅ Valid") -> ✅ Valid | K34: +44 309 8554497 | L34: =IFERROR(__xludf.DUMMYFUNCTION("IF(OR(K34=""N/A"", K34=""missing"", K34=""none""), """", REGEXREPLACE( SUBSTITUTE(SUBSTITUTE(SUBSTITUTE(TO_TEXT(K34), CHAR(160),""""), UNICHAR(8239),""""), UNICHAR(8201),""""),""[+\-/(): )]"", """"))"),"443098554497") -> 443098554497 | M34: =IFERROR(__xludf.DUMMYFUNCTION("IF(L34="""","""", REGEXEXTRACT(REGEXREPLACE(L34,""x"", """"), ""[0-9]+""))"),"443098554497") -> 443098554497 | N34: =IF(LEFT(M34,2)="44", RIGHT(M34,LEN(M34)-2),M34) -> 3098554497 | O34: =IFERROR(__xludf.DUMMYFUNCTION("REGEXMATCH(TO_TEXT(N34), ""^07[1-57-9]"")"),FALSE) -> FALSE | P34: =LEN(N34) -> 10 | Q34: =IF(AND(O34=TRUE, P34=11), "✅ VALID", "❌ INVALID") -> ❌ INVALID | R34: UK | S34: 44655 | T34: =IFERROR(__xludf.DUMMYFUNCTION("IF(ISNUMBER(S34),TEXT(S34,""yyyy-MM-dd""),REGEXREPLACE(REGEXREPLACE(TO_TEXT(S34),""[^0-9a-zA-Z]+"",""-""),""[^0-9]*$"",""""))"),"2022-04-04") -> 2022-04-04 | U34: 2022-04-04 | Y34: 2022-04-04
A35: CUST-5033 | B35: ✅ Unique | C35: Omar Rodriguez | D35: =IFERROR(__xludf.DUMMYFUNCTION("PROPER(REGEXREPLACE(TRIM(C35),""\s+"","" ""))"),"Omar Rodriguez") -> Omar Rodriguez | E35: =IFERROR(__xludf.DUMMYFUNCTION("IF(LEN(D35:D701), COUNTA(SPLIT(D35:D701,"" "")), """")"),2.0) -> 2 | F35: =IF(D35=G35,"✅","❌") -> ✅ | G35: =IFERROR(__xludf.DUMMYFUNCTION("REGEXEXTRACT(PROPER(SUBSTITUTE(TRIM(I35),""."","" "")),""^[^@]+"")"),"Omar Rodriguez") -> Omar Rodriguez | H35: =LOWER(TRIM(I35)) -> omar.rodriguez@example.com | I35: omar.rodriguez@example.com | J35: =IFERROR(__xludf.DUMMYFUNCTION("IF(REGEXMATCH(TRIM(I35),""^[A-Za-z0-9._%+-]+@[A-Za-z0-9.-]+\.[A-Za-z]{2,}$""),""✅ Valid"",""❌ Invalid"")"),"✅ Valid") -> ✅ Valid | K35: (496) 820240 | L35: =IFERROR(__xludf.DUMMYFUNCTION("IF(OR(K35=""N/A"", K35=""missing"", K35=""none""), """", REGEXREPLACE( SUBSTITUTE(SUBSTITUTE(SUBSTITUTE(TO_TEXT(K35), CHAR(160),""""), UNICHAR(8239),""""), UNICHAR(8201),""""),""[+\-/(): )]"", """"))"),"496820240") -> 496820240 | M35: =IFERROR(__xludf.DUMMYFUNCTION("IF(L35="""","""", REGEXEXTRACT(REGEXREPLACE(L35,""x"", """"), ""[0-9]+""))"),"496820240") -> 496820240 | N35: =IF(LEFT(M35,2)="33", RIGHT(M35,LEN(M35)-2),M35) -> 496820240 | O35: =IFERROR(__xludf.DUMMYFUNCTION("REGEXMATCH(TO_TEXT(N35), ""^0[67]"")"),FALSE) -> FALSE | P35: =LEN(N35) -> 9 | Q35: =IF(AND(O35=TRUE, P35=9), "✅ VALID", "❌ INVALID") -> ❌ INVALID | R35: France | S35: 44921 | T35: =IFERROR(__xludf.DUMMYFUNCTION("IF(ISNUMBER(S35),TEXT(S35,""yyyy-MM-dd""),REGEXREPLACE(REGEXREPLACE(TO_TEXT(S35),""[^0-9a-zA-Z]+"",""-""),""[^0-9]*$"",""""))"),"2022-12-26") -> 2022-12-26 | U35: 2022-12-26 | Y35: 2022-12-26
A36: CUST-5034 | B36: ✅ Unique | C36: Ken Nowak | D36: =IFERROR(__xludf.DUMMYFUNCTION("PROPER(REGEXREPLACE(TRIM(C36),""\s+"","" ""))"),"Ken Nowak") -> Ken Nowak | E36: =IFERROR(__xludf.DUMMYFUNCTION("IF(LEN(D36:D701), COUNTA(SPLIT(D36:D701,"" "")), """")"),2.0) -> 2 | F36: =IF(D36=G36,"✅","❌") -> ✅ | G36: =IFERROR(__xludf.DUMMYFUNCTION("REGEXEXTRACT(PROPER(SUBSTITUTE(TRIM(I36),""."","" "")),""^[^@]+"")"),"Ken Nowak") -> Ken Nowak | H36: =LOWER(TRIM(I36)) -> ken.nowak@outlook.com | I36: ken.nowak@outlook.com | J36: =IFERROR(__xludf.DUMMYFUNCTION("IF(REGEXMATCH(TRIM(I36),""^[A-Za-z0-9._%+-]+@[A-Za-z0-9.-]+\.[A-Za-z]{2,}$""),""✅ Valid"",""❌ Invalid"")"),"✅ Valid") -> ✅ Valid | K36: +353-876-052466 | L36: =IFERROR(__xludf.DUMMYFUNCTION("IF(OR(K36=""N/A"", K36=""missing"", K36=""none""), """", REGEXREPLACE( SUBSTITUTE(SUBSTITUTE(SUBSTITUTE(TO_TEXT(K36), CHAR(160),""""), UNICHAR(8239),""""), UNICHAR(8201),""""),""[+\-/(): )]"", """"))"),"353876052466") -> 353876052466 | M36: =IFERROR(__xludf.DUMMYFUNCTION("IF(L36="""","""", REGEXEXTRACT(REGEXREPLACE(L36,""x"", """"), ""[0-9]+""))"),"353876052466") -> 353876052466 | N36: =IF(LEFT(M36,3)="353", RIGHT(M36,LEN(M36)-3),M36) -> 876052466 | O36: =IFERROR(__xludf.DUMMYFUNCTION("REGEXMATCH(TO_TEXT(N36), ""^0(83|85|86|87|89)"")"),FALSE) -> FALSE | P36: =LEN(N36) -> 9 | Q36: =IF(AND(O36=TRUE, P33=10), "✅ VALID", "❌ INVALID") -> ❌ INVALID | R36: Ireland | S36: 45705 | T36: =IFERROR(__xludf.DUMMYFUNCTION("IF(ISNUMBER(S36),TEXT(S36,""yyyy-MM-dd""),REGEXREPLACE(REGEXREPLACE(TO_TEXT(S36),""[^0-9a-zA-Z]+"",""-""),""[^0-9]*$"",""""))"),"2025-02-17") -> 2025-02-17 | U36: 2025-02-17 | Y36: 2025-02-17
A37: CUST-5035 | B37: ✅ Unique | C37: Ethan Lee | D37: =IFERROR(__xludf.DUMMYFUNCTION("PROPER(REGEXREPLACE(TRIM(C37),""\s+"","" ""))"),"Ethan Lee") -> Ethan Lee | E37: =IFERROR(__xludf.DUMMYFUNCTION("IF(LEN(D37:D701), COUNTA(SPLIT(D37:D701,"" "")), """")"),2.0) -> 2 | F37: =IF(D37=G37,"✅","❌") -> ✅ | G37: =IFERROR(__xludf.DUMMYFUNCTION("REGEXEXTRACT(PROPER(SUBSTITUTE(TRIM(I37),""."","" "")),""^[^@]+"")"),"Ethan Lee") -> Ethan Lee | H37: =LOWER(TRIM(I37)) -> ethan.lee@shop.io | I37: ethan.lee@shop.io | J37: =IFERROR(__xludf.DUMMYFUNCTION("IF(REGEXMATCH(TRIM(I37),""^[A-Za-z0-9._%+-]+@[A-Za-z0-9.-]+\.[A-Za-z]{2,}$""),""✅ Valid"",""❌ Invalid"")"),"✅ Valid") -> ✅ Valid | K37: (162) 0538179 | L37: =IFERROR(__xludf.DUMMYFUNCTION("IF(OR(K37=""N/A"", K37=""missing"", K37=""none""), """", REGEXREPLACE( SUBSTITUTE(SUBSTITUTE(SUBSTITUTE(TO_TEXT(K37), CHAR(160),""""), UNICHAR(8239),""""), UNICHAR(8201),""""),""[+\-/(): )]"", """"))"),"1620538179") -> 1620538179 | M37: =IFERROR(__xludf.DUMMYFUNCTION("IF(L37="""","""", REGEXEXTRACT(REGEXREPLACE(L37,""x"", """"), ""[0-9]+""))"),"1620538179") -> 1620538179 | N37: =IF(LEFT(M37,2)="33", RIGHT(M37,LEN(M37)-2),M37) -> 1620538179 | O37: =IFERROR(__xludf.DUMMYFUNCTION("REGEXMATCH(TO_TEXT(N37), ""^0[67]"")"),FALSE) -> FALSE | P37: =LEN(N37) -> 10 | Q37: =IF(AND(O37=TRUE, P37=9), "✅ VALID", "❌ INVALID") -> ❌ INVALID | R37: France | S37: 45104 | T37: =IFERROR(__xludf.DUMMYFUNCTION("IF(ISNUMBER(S37),TEXT(S37,""yyyy-MM-dd""),REGEXREPLACE(REGEXREPLACE(TO_TEXT(S37),""[^0-9a-zA-Z]+"",""-""),""[^0-9]*$"",""""))"),"2023-06-27") -> 2023-06-27 | U37: 2023-06-27 | Y37: 2023-06-27
A38: CUST-5036 | B38: ✅ Unique | C38: Lia Novak | D38: =IFERROR(__xludf.DUMMYFUNCTION("PROPER(REGEXREPLACE(TRIM(C38),""\s+"","" ""))"),"Lia Novak") -> Lia Novak | E38: =IFERROR(__xludf.DUMMYFUNCTION("IF(LEN(D38:D701), COUNTA(SPLIT(D38:D701,"" "")), """")"),2.0) -> 2 | F38: =IF(D38=G38,"✅","❌") -> ✅ | G38: =IFERROR(__xludf.DUMMYFUNCTION("REGEXEXTRACT(PROPER(SUBSTITUTE(TRIM(I38),""."","" "")),""^[^@]+"")"),"Lia Novak") -> Lia Novak | H38: =LOWER(TRIM(I38)) -> lia.novak@yahoo.com | I38: lia.novak@yahoo.com | J38: =IFERROR(__xludf.DUMMYFUNCTION("IF(REGEXMATCH(TRIM(I38),""^[A-Za-z0-9._%+-]+@[A-Za-z0-9.-]+\.[A-Za-z]{2,}$""),""✅ Valid"",""❌ Invalid"")"),"✅ Valid") -> ✅ Valid | K38: 609-367-23 | L38: =IFERROR(__xludf.DUMMYFUNCTION("IF(OR(K38=""N/A"", K38=""missing"", K38=""none""), """", REGEXREPLACE( SUBSTITUTE(SUBSTITUTE(SUBSTITUTE(TO_TEXT(K38), CHAR(160),""""), UNICHAR(8239),""""), UNICHAR(8201),""""),""[+\-/(): )]"", """"))"),"60936723") -> 60936723 | M38: =IFERROR(__xludf.DUMMYFUNCTION("IF(L38="""","""", REGEXEXTRACT(REGEXREPLACE(L38,""x"", """"), ""[0-9]+""))"),"60936723") -> 60936723 | N38: =IF(LEFT(M38,2)="44", RIGHT(M38,LEN(M38)-2),M38) -> 60936723 | O38: =IFERROR(__xludf.DUMMYFUNCTION("REGEXMATCH(TO_TEXT(N38), ""^07[1-57-9]"")"),FALSE) -> FALSE | P38: =LEN(N38) -> 8 | Q38: =IF(AND(O38=TRUE, P38=11), "✅ VALID", "❌ INVALID") -> ❌ INVALID | R38: UK | S38: 12/13/2024 | T38: =IFERROR(__xludf.DUMMYFUNCTION("IF(ISNUMBER(S38),TEXT(S38,""yyyy-MM-dd""),REGEXREPLACE(REGEXREPLACE(TO_TEXT(S38),""[^0-9a-zA-Z]+"",""-""),""[^0-9]*$"",""""))"),"12-13-2024") -> 12-13-2024 | U38: =TEXT(T38,"yyyy-MM-dd") -> 12-13-2024 | V38: 2024-12-13 | Y38: 2024-12-13
A39: CUST-5037 | B39: ✅ Unique | C39: Omar Young | D39: =IFERROR(__xludf.DUMMYFUNCTION("PROPER(REGEXREPLACE(TRIM(C39),""\s+"","" ""))"),"Omar Young") -> Omar Young | E39: =IFERROR(__xludf.DUMMYFUNCTION("IF(LEN(D39:D701), COUNTA(SPLIT(D39:D701,"" "")), """")"),2.0) -> 2 | F39: =IF(D39=G39,"✅","❌") -> ✅ | G39: =IFERROR(__xludf.DUMMYFUNCTION("REGEXEXTRACT(PROPER(SUBSTITUTE(TRIM(I39),""."","" "")),""^[^@]+"")"),"Omar Young") -> Omar Young | H39: =LOWER(TRIM(I39)) -> omar.young@company.co.uk | I39: omar.young@company.co.uk | J39: =IFERROR(__xludf.DUMMYFUNCTION("IF(REGEXMATCH(TRIM(I39),""^[A-Za-z0-9._%+-]+@[A-Za-z0-9.-]+\.[A-Za-z]{2,}$""),""✅ Valid"",""❌ Invalid"")"),"✅ Valid") -> ✅ Valid | K39: +44-412-8260468 | L39: =IFERROR(__xludf.DUMMYFUNCTION("IF(OR(K39=""N/A"", K39=""missing"", K39=""none""), """", REGEXREPLACE( SUBSTITUTE(SUBSTITUTE(SUBSTITUTE(TO_TEXT(K39), CHAR(160),""""), UNICHAR(8239),""""), UNICHAR(8201),""""),""[+\-/(): )]"", """"))"),"444128260468") -> 444128260468 | M39: =IFERROR(__xludf.DUMMYFUNCTION("IF(L39="""","""", REGEXEXTRACT(REGEXREPLACE(L39,""x"", """"), ""[0-9]+""))"),"444128260468") -> 444128260468 | N39: =IF(LEFT(M39,2)="44", RIGHT(M39,LEN(M39)-2),M39) -> 4128260468 | O39: =IFERROR(__xludf.DUMMYFUNCTION("REGEXMATCH(TO_TEXT(N39), ""^07[1-57-9]"")"),FALSE) -> FALSE | P39: =LEN(N39) -> 10 | Q39: =IF(AND(O39=TRUE, P39=11), "✅ VALID", "❌ INVALID") -> ❌ INVALID | R39: UK | S39: 45477.742 | T39: =IFERROR(__xludf.DUMMYFUNCTION("IF(ISNUMBER(S39),TEXT(S39,""yyyy-MM-dd""),REGEXREPLACE(REGEXREPLACE(TO_TEXT(S39),""[^0-9a-zA-Z]+"",""-""),""[^0-9]*$"",""""))"),"2024-07-04") -> 2024-07-04 | U39: 2024-07-04 | Y39: 2024-07-04
A40: CUST-5038 | B40: ✅ Unique | C40: Ken Williams | D40: =IFERROR(__xludf.DUMMYFUNCTION("PROPER(REGEXREPLACE(TRIM(C40),""\s+"","" ""))"),"Ken Williams") -> Ken Williams | E40: =IFERROR(__xludf.DUMMYFUNCTION("IF(LEN(D40:D701), COUNTA(SPLIT(D40:D701,"" "")), """")"),2.0) -> 2 | F40: =IF(D40=G40,"✅","❌") -> ✅ | G40: =IFERROR(__xludf.DUMMYFUNCTION("REGEXEXTRACT(PROPER(SUBSTITUTE(TRIM(I40),""."","" "")),""^[^@]+"")"),"Ken Williams") -> Ken Williams | H40: =LOWER(TRIM(I40)) -> ken.williams@company.co.uk | I40: ken.williams@company.co.uk | J40: =IFERROR(__xludf.DUMMYFUNCTION("IF(REGEXMATCH(TRIM(I40),""^[A-Za-z0-9._%+-]+@[A-Za-z0-9.-]+\.[A-Za-z]{2,}$""),""✅ Valid"",""❌ Invalid"")"),"✅ Valid") -> ✅ Valid | K40: 23x012131 | L40: =IFERROR(__xludf.DUMMYFUNCTION("IF(OR(K40=""N/A"", K40=""missing"", K40=""none""), """", REGEXREPLACE( SUBSTITUTE(SUBSTITUTE(SUBSTITUTE(TO_TEXT(K40), CHAR(160),""""), UNICHAR(8239),""""), UNICHAR(8201),""""),""[+\-/(): )]"", """"))"),"23x012131") -> 23x012131 | M40: =IFERROR(__xludf.DUMMYFUNCTION("IF(L40="""","""", REGEXEXTRACT(REGEXREPLACE(L40,""x"", """"), ""[0-9]+""))"),"23012131") -> 23012131 | N40: =IF(LEFT(M40,2)="34", RIGHT(M40,LEN(M40)-2),M40) -> 23012131 | O40: =IFERROR(__xludf.DUMMYFUNCTION("REGEXMATCH(TO_TEXT(N40), ""^[67]"")"),FALSE) -> FALSE | P40: =LEN(N40) -> 8 | Q40: =IF(AND(O40=TRUE, P40=9), "✅ VALID", "❌ INVALID") -> ❌ INVALID | R40: Spain | S40: 44835 | T40: =IFERROR(__xludf.DUMMYFUNCTION("IF(ISNUMBER(S40),TEXT(S40,""yyyy-MM-dd""),REGEXREPLACE(REGEXREPLACE(TO_TEXT(S40),""[^0-9a-zA-Z]+"",""-""),""[^0-9]*$"",""""))"),"2022-10-01") -> 2022-10-01 | U40: 2022-10-01 | Y40: 2022-10-01
A41: CUST-5039 | B41: ✅ Unique | C41: Igor Dubois | D41: =IFERROR(__xludf.DUMMYFUNCTION("PROPER(REGEXREPLACE(TRIM(C41),""\s+"","" ""))"),"Igor Dubois") -> Igor Dubois | E41: =IFERROR(__xludf.DUMMYFUNCTION("IF(LEN(D41:D701), COUNTA(SPLIT(D41:D701,"" "")), """")"),2.0) -> 2 | F41: =IF(D41=G41,"✅","❌") -> ✅ | G41: =IFERROR(__xludf.DUMMYFUNCTION("REGEXEXTRACT(PROPER(SUBSTITUTE(TRIM(I41),""."","" "")),""^[^@]+"")"),"Igor Dubois") -> Igor Dubois | H41: =LOWER(TRIM(I41)) -> igor.dubois@company.co.uk | I41: igor.dubois@company.co.uk | J41: =IFERROR(__xludf.DUMMYFUNCTION("IF(REGEXMATCH(TRIM(I41),""^[A-Za-z0-9._%+-]+@[A-Za-z0-9.-]+\.[A-Za-z]{2,}$""),""✅ Valid"",""❌ Invalid"")"),"✅ Valid") -> ✅ Valid | K41: tel:+1333089616 | L41: =IFERROR(__xludf.DUMMYFUNCTION("IF(OR(K41=""N/A"", K41=""missing"", K41=""none""), """", REGEXREPLACE( SUBSTITUTE(SUBSTITUTE(SUBSTITUTE(TO_TEXT(K41), CHAR(160),""""), UNICHAR(8239),""""), UNICHAR(8201),""""),""[+\-/(): )]"", """"))"),"tel1333089616") -> tel1333089616 | M41: =IFERROR(__xludf.DUMMYFUNCTION("IF(L41="""","""", REGEXEXTRACT(REGEXREPLACE(L41,""x"", """"), ""[0-9]+""))"),"1333089616") -> 1333089616 | N41: =IF(LEFT(M41,1)="1", RIGHT(M41,LEN(M41)-1),M41) -> 333089616 | O41: =IFERROR(__xludf.DUMMYFUNCTION("REGEXMATCH(TO_TEXT(N41), ""^[2-9][0-9]{9}$"")"),FALSE) -> FALSE | P41: =LEN(N41) -> 9 | Q41: =IF(AND(O41=TRUE, P41=10), "✅ VALID", "❌ INVALID") -> ❌ INVALID | R41: USA | S41: 44763 | T41: =IFERROR(__xludf.DUMMYFUNCTION("IF(ISNUMBER(S41),TEXT(S41,""yyyy-MM-dd""),REGEXREPLACE(REGEXREPLACE(TO_TEXT(S41),""[^0-9a-zA-Z]+"",""-""),""[^0-9]*$"",""""))"),"2022-07-21") -> 2022-07-21 | U41: 2022-07-21 | Y41: 2022-07-21
A42: CUST-5040 | B42: ✅ Unique | C42: Daria Young | D42: =IFERROR(__xludf.DUMMYFUNCTION("PROPER(REGEXREPLACE(TRIM(C42),""\s+"","" ""))"),"Daria Young") -> Daria Young | E42: =IFERROR(__xludf.DUMMYFUNCTION("IF(LEN(D42:D701), COUNTA(SPLIT(D42:D701,"" "")), """")"),2.0) -> 2 | F42: =IF(D42=G42,"✅","❌") -> ✅ | G42: =IFERROR(__xludf.DUMMYFUNCTION("REGEXEXTRACT(PROPER(SUBSTITUTE(TRIM(I42),""."","" "")),""^[^@]+"")"),"Daria Young") -> Daria Young | H42: =LOWER(TRIM(I42)) -> daria.young@comapny.co.uk | I42: Daria.Young@Comapny.Co.Uk | J42: =IFERROR(__xludf.DUMMYFUNCTION("IF(REGEXMATCH(TRIM(I42),""^[A-Za-z0-9._%+-]+@[A-Za-z0-9.-]+\.[A-Za-z]{2,}$""),""✅ Valid"",""❌ Invalid"")"),"✅ Valid") -> ✅ Valid | K42: 091-063-6077 | L42: =IFERROR(__xludf.DUMMYFUNCTION("IF(OR(K42=""N/A"", K42=""missing"", K42=""none""), """", REGEXREPLACE( SUBSTITUTE(SUBSTITUTE(SUBSTITUTE(TO_TEXT(K42), CHAR(160),""""), UNICHAR(8239),""""), UNICHAR(8201),""""),""[+\-/(): )]"", """"))"),"0910636077") -> 0910636077 | M42: =IFERROR(__xludf.DUMMYFUNCTION("IF(L42="""","""", REGEXEXTRACT(REGEXREPLACE(L42,""x"", """"), ""[0-9]+""))"),"0910636077") -> 0910636077 | N42: =IF(LEFT(M42,3)="353", RIGHT(M42,LEN(M42)-3),M42) -> 0910636077 | O42: =IFERROR(__xludf.DUMMYFUNCTION("REGEXMATCH(TO_TEXT(N42), ""^0(83|85|86|87|89)"")"),FALSE) -> FALSE | P42: =LEN(N42) -> 10 | Q42: =IF(AND(O42=TRUE, P39=10), "✅ VALID", "❌ INVALID") -> ❌ INVALID | R42: Ireland | S42: 44904 | T42: =IFERROR(__xludf.DUMMYFUNCTION("IF(ISNUMBER(S42),TEXT(S42,""yyyy-MM-dd""),REGEXREPLACE(REGEXREPLACE(TO_TEXT(S42),""[^0-9a-zA-Z]+"",""-""),""[^0-9]*$"",""""))"),"2022-12-09") -> 2022-12-09 | U42: 2022-12-09 | Y42: 2022-12-09
A43: CUST-5041 | B43: ✅ Unique | C43: Sam Lopez | D43: =IFERROR(__xludf.DUMMYFUNCTION("PROPER(REGEXREPLACE(TRIM(C43),""\s+"","" ""))"),"Sam Lopez") -> Sam Lopez | E43: =IFERROR(__xludf.DUMMYFUNCTION("IF(LEN(D43:D701), COUNTA(SPLIT(D43:D701,"" "")), """")"),2.0) -> 2 | F43: =IF(D43=G43,"✅","❌") -> ✅ | G43: =IFERROR(__xludf.DUMMYFUNCTION("REGEXEXTRACT(PROPER(SUBSTITUTE(TRIM(I43),""."","" "")),""^[^@]+"")"),"Sam Lopez") -> Sam Lopez | H43: =LOWER(TRIM(I43)) -> sam.lopez@gmail.com | I43: sam.lopez@gmail.com | J43: =IFERROR(__xludf.DUMMYFUNCTION("IF(REGEXMATCH(TRIM(I43),""^[A-Za-z0-9._%+-]+@[A-Za-z0-9.-]+\.[A-Za-z]{2,}$""),""✅ Valid"",""❌ Invalid"")"),"✅ Valid") -> ✅ Valid | K43: 517-931-223 | L43: =IFERROR(__xludf.DUMMYFUNCTION("IF(OR(K43=""N/A"", K43=""missing"", K43=""none""), """", REGEXREPLACE( SUBSTITUTE(SUBSTITUTE(SUBSTITUTE(TO_TEXT(K43), CHAR(160),""""), UNICHAR(8239),""""), UNICHAR(8201),""""),""[+\-/(): )]"", """"))"),"517931223") -> 517931223 | M43: =IFERROR(__xludf.DUMMYFUNCTION("IF(L43="""","""", REGEXEXTRACT(REGEXREPLACE(L43,""x"", """"), ""[0-9]+""))"),"517931223") -> 517931223 | N43: =IF(LEFT(M43,2)="39", RIGHT(M43,LEN(M43)-2),M43) -> 517931223 | O43: =IFERROR(__xludf.DUMMYFUNCTION("REGEXMATCH(TO_TEXT(N43), ""^3"")"),FALSE) -> FALSE | P43: =LEN(N43) -> 9 | Q43: =IF(AND(O43=TRUE,OR(P43=9, P43=10 )), "✅ VALID", "❌ INVALID") -> ❌ INVALID | R43: Italy | S43: 22.01.2023 | T43: =IFERROR(__xludf.DUMMYFUNCTION("IF(ISNUMBER(S43),TEXT(S43,""yyyy-MM-dd""),REGEXREPLACE(REGEXREPLACE(TO_TEXT(S43),""[^0-9a-zA-Z]+"",""-""),""[^0-9]*$"",""""))"),"22-01-2023") -> 22-01-2023 | U43: 2023-01-22 | Y43: 2023-01-22
A44: CUST-5042 | B44: ✅ Unique | C44: Gabe Davis | D44: =IFERROR(__xludf.DUMMYFUNCTION("PROPER(REGEXREPLACE(TRIM(C44),""\s+"","" ""))"),"Gabe Davis") -> Gabe Davis | E44: =IFERROR(__xludf.DUMMYFUNCTION("IF(LEN(D44:D701), COUNTA(SPLIT(D44:D701,"" "")), """")"),2.0) -> 2 | F44: =IF(D44=G44,"✅","❌") -> ✅ | G44: =IFERROR(__xludf.DUMMYFUNCTION("REGEXEXTRACT(PROPER(SUBSTITUTE(TRIM(I44),""."","" "")),""^[^@]+"")"),"Gabe Davis") -> Gabe Davis | H44: =LOWER(TRIM(I44)) -> gabe.davis@example.com | I44: gabe.davis@example.com | J44: =IFERROR(__xludf.DUMMYFUNCTION("IF(REGEXMATCH(TRIM(I44),""^[A-Za-z0-9._%+-]+@[A-Za-z0-9.-]+\.[A-Za-z]{2,}$""),""✅ Valid"",""❌ Invalid"")"),"✅ Valid") -> ✅ Valid | K44: +440412651844 | L44: =IFERROR(__xludf.DUMMYFUNCTION("IF(OR(K44=""N/A"", K44=""missing"", K44=""none""), """", REGEXREPLACE( SUBSTITUTE(SUBSTITUTE(SUBSTITUTE(TO_TEXT(K44), CHAR(160),""""), UNICHAR(8239),""""), UNICHAR(8201),""""),""[+\-/(): )]"", """"))"),"440412651844") -> 440412651844 | M44: =IFERROR(__xludf.DUMMYFUNCTION("IF(L44="""","""", REGEXEXTRACT(REGEXREPLACE(L44,""x"", """"), ""[0-9]+""))"),"440412651844") -> 440412651844 | N44: =IF(LEFT(M44,2)="44", RIGHT(M44,LEN(M44)-2),M44) -> 0412651844 | O44: =IFERROR(__xludf.DUMMYFUNCTION("REGEXMATCH(TO_TEXT(N44), ""^07[1-57-9]"")"),FALSE) -> FALSE | P44: =LEN(N44) -> 10 | Q44: =IF(AND(O44=TRUE, P44=11), "✅ VALID", "❌ INVALID") -> ❌ INVALID | R44: UK | S44: 26.08.2025 | T44: =IFERROR(__xludf.DUMMYFUNCTION("IF(ISNUMBER(S44),TEXT(S44,""yyyy-MM-dd""),REGEXREPLACE(REGEXREPLACE(TO_TEXT(S44),""[^0-9a-zA-Z]+"",""-""),""[^0-9]*$"",""""))"),"26-08-2025") -> 26-08-2025 | U44: 2025-08-26 | Y44: 2025-08-26
A45: CUST-5043 | B45: ✅ Unique | C45: Rita Garcia | D45: =IFERROR(__xludf.DUMMYFUNCTION("PROPER(REGEXREPLACE(TRIM(C45),""\s+"","" ""))"),"Rita Garcia") -> Rita Garcia | E45: =IFERROR(__xludf.DUMMYFUNCTION("IF(LEN(D45:D701), COUNTA(SPLIT(D45:D701,"" "")), """")"),2.0) -> 2 | F45: =IF(D45=G45,"✅","❌") -> ✅ | G45: =IFERROR(__xludf.DUMMYFUNCTION("REGEXEXTRACT(PROPER(SUBSTITUTE(TRIM(I45),""."","" "")),""^[^@]+"")"),"Rita Garcia") -> Rita Garcia | H45: =LOWER(TRIM(I45)) -> rita.garcia@example.com | I45: Rita.Garcia@Example.Com | J45: =IFERROR(__xludf.DUMMYFUNCTION("IF(REGEXMATCH(TRIM(I45),""^[A-Za-z0-9._%+-]+@[A-Za-z0-9.-]+\.[A-Za-z]{2,}$""),""✅ Valid"",""❌ Invalid"")"),"✅ Valid") -> ✅ Valid | K45: 72548960491 | L45: =IFERROR(__xludf.DUMMYFUNCTION("IF(OR(K45=""N/A"", K45=""missing"", K45=""none""), """", REGEXREPLACE( SUBSTITUTE(SUBSTITUTE(SUBSTITUTE(TO_TEXT(K45), CHAR(160),""""), UNICHAR(8239),""""), UNICHAR(8201),""""),""[+\-/(): )]"", """"))"),"72548960491") -> 72548960491 | M45: =IFERROR(__xludf.DUMMYFUNCTION("IF(L45="""","""", REGEXEXTRACT(REGEXREPLACE(L45,""x"", """"), ""[0-9]+""))"),"72548960491") -> 72548960491 | N45: =IF(LEFT(M45,2)="49", RIGHT(M45,LEN(M45)-2),M45) -> 72548960491 | O45: =IFERROR(__xludf.DUMMYFUNCTION("REGEXMATCH(TO_TEXT(N45), ""^0(15|16|17)"")"),FALSE) -> FALSE | P45: =LEN(N45) -> 11 | Q45: =IF(AND(O45=TRUE,OR(P45=10, P45=11)), "✅ VALID", "❌ INVALID") -> ❌ INVALID | R45: Germany | S45: 05/20/2024 | T45: =IFERROR(__xludf.DUMMYFUNCTION("IF(ISNUMBER(S45),TEXT(S45,""yyyy-MM-dd""),REGEXREPLACE(REGEXREPLACE(TO_TEXT(S45),""[^0-9a-zA-Z]+"",""-""),""[^0-9]*$"",""""))"),"05-20-2024") -> 05-20-2024 | U45: =TEXT(T45,"yyyy-MM-dd") -> 05-20-2024 | V45: 2024-05-20 | Y45: 2024-05-20
A46: CUST-5044 | B46: ✅ Unique | C46: Gabe Davis | D46: =IFERROR(__xludf.DUMMYFUNCTION("PROPER(REGEXREPLACE(TRIM(C46),""\s+"","" ""))"),"Gabe Davis") -> Gabe Davis | E46: =IFERROR(__xludf.DUMMYFUNCTION("IF(LEN(D46:D701), COUNTA(SPLIT(D46:D701,"" "")), """")"),2.0) -> 2 | F46: =IF(D46=G46,"✅","❌") -> ✅ | G46: =IFERROR(__xludf.DUMMYFUNCTION("REGEXEXTRACT(PROPER(SUBSTITUTE(TRIM(I46),""."","" "")),""^[^@]+"")"),"Gabe Davis") -> Gabe Davis | H46: =LOWER(TRIM(I46)) -> gabe.davis@example.com | I46: gabe.davis@example.com | J46: =IFERROR(__xludf.DUMMYFUNCTION("IF(REGEXMATCH(TRIM(I46),""^[A-Za-z0-9._%+-]+@[A-Za-z0-9.-]+\.[A-Za-z]{2,}$""),""✅ Valid"",""❌ Invalid"")"),"✅ Valid") -> ✅ Valid | K46: missing | L46: =IFERROR(__xludf.DUMMYFUNCTION("IF(OR(K46=""N/A"", K46=""missing"", K46=""none""), """", REGEXREPLACE( SUBSTITUTE(SUBSTITUTE(SUBSTITUTE(TO_TEXT(K46), CHAR(160),""""), UNICHAR(8239),""""), UNICHAR(8201),""""),""[+\-/(): )]"", """"))"),"") | M46: =IFERROR(__xludf.DUMMYFUNCTION("IF(L46="""","""", REGEXEXTRACT(REGEXREPLACE(L46,""x"", """"), ""[0-9]+""))"),"") | N46: =IF(LEFT(M46,2)="49", RIGHT(M46,LEN(M46)-2),M46) | O46: =IFERROR(__xludf.DUMMYFUNCTION("REGEXMATCH(TO_TEXT(N46), ""^0(15|16|17)"")"),FALSE) -> FALSE | P46: =LEN(N46) -> 0 | Q46: =IF(AND(O46=TRUE,OR(P46=10, P46=11)), "✅ VALID", "❌ INVALID") -> ❌ INVALID | R46: Germany | S46: 09.11.2022 17:56 | T46: =IFERROR(__xludf.DUMMYFUNCTION("IF(ISNUMBER(S46),TEXT(S46,""yyyy-MM-dd""),REGEXREPLACE(REGEXREPLACE(TO_TEXT(S46),""[^0-9a-zA-Z]+"",""-""),""[^0-9]*$"",""""))"),"09-11-2022-17-56") -> 09-11-2022-17-56 | U46: =TEXT(T46,"yyyy-MM-dd") -> 09-11-2022-17-56 | V46: =IFERROR(__xludf.DUMMYFUNCTION("REGEXEXTRACT(U46,""^\d{2}-\d{2}-\d{4}"")"),"09-11-2022") -> 09-11-2022 | W46: 2022-11-09 | Y46: 2022-11-09
A47: CUST-5045 | B47: ✅ Unique | C47: Omar Rodriguez | D47: =IFERROR(__xludf.DUMMYFUNCTION("PROPER(REGEXREPLACE(TRIM(C47),""\s+"","" ""))"),"Omar Rodriguez") -> Omar Rodriguez | E47: =IFERROR(__xludf.DUMMYFUNCTION("IF(LEN(D47:D701), COUNTA(SPLIT(D47:D701,"" "")), """")"),2.0) -> 2 | F47: =IF(D47=G47,"✅","❌") -> ✅ | G47: =IFERROR(__xludf.DUMMYFUNCTION("REGEXEXTRACT(PROPER(SUBSTITUTE(TRIM(I47),""."","" "")),""^[^@]+"")"),"Omar Rodriguez") -> Omar Rodriguez | H47: =LOWER(TRIM(I47)) -> omar.rodriguez@yahoo.com | I47: omar.rodriguez@yahoo.com | J47: =IFERROR(__xludf.DUMMYFUNCTION("IF(REGEXMATCH(TRIM(I47),""^[A-Za-z0-9._%+-]+@[A-Za-z0-9.-]+\.[A-Za-z]{2,}$""),""✅ Valid"",""❌ Invalid"")"),"✅ Valid") -> ✅ Valid | L47: =IFERROR(__xludf.DUMMYFUNCTION("IF(OR(K47=""N/A"", K47=""missing"", K47=""none""), """", REGEXREPLACE( SUBSTITUTE(SUBSTITUTE(SUBSTITUTE(TO_TEXT(K47), CHAR(160),""""), UNICHAR(8239),""""), UNICHAR(8201),""""),""[+\-/(): )]"", """"))"),"") | M47: =IFERROR(__xludf.DUMMYFUNCTION("IF(L47="""","""", REGEXEXTRACT(REGEXREPLACE(L47,""x"", """"), ""[0-9]+""))"),"") | N47: =IF(LEFT(M47,2)="33", RIGHT(M47,LEN(M47)-2),M47) | O47: =IFERROR(__xludf.DUMMYFUNCTION("REGEXMATCH(TO_TEXT(N47), ""^0[67]"")"),FALSE) -> FALSE | P47: =LEN(N47) -> 0 | Q47: =IF(AND(O47=TRUE, P47=9), "✅ VALID", "❌ INVALID") -> ❌ INVALID | R47: France | S47: 45459.876 | T47: =IFERROR(__xludf.DUMMYFUNCTION("IF(ISNUMBER(S47),TEXT(S47,""yyyy-MM-dd""),REGEXREPLACE(REGEXREPLACE(TO_TEXT(S47),""[^0-9a-zA-Z]+"",""-""),""[^0-9]*$"",""""))"),"2024-06-16") -> 2024-06-16 | U47: 2024-06-16 | Y47: 2024-06-16
A48: CUST-5046 | B48: ✅ Unique | C48: Daria Dubois | D48: =IFERROR(__xludf.DUMMYFUNCTION("PROPER(REGEXREPLACE(TRIM(C48),""\s+"","" ""))"),"Daria Dubois") -> Daria Dubois | E48: =IFERROR(__xludf.DUMMYFUNCTION("IF(LEN(D48:D701), COUNTA(SPLIT(D48:D701,"" "")), """")"),2.0) -> 2 | F48: =IF(D48=G48,"✅","❌") -> ✅ | G48: =IFERROR(__xludf.DUMMYFUNCTION("REGEXEXTRACT(PROPER(SUBSTITUTE(TRIM(I48),""."","" "")),""^[^@]+"")"),"Daria Dubois") -> Daria Dubois | H48: =LOWER(TRIM(I48)) -> daria.dubois@outlook.com | I48: daria.dubois@outlook.com | J48: =IFERROR(__xludf.DUMMYFUNCTION("IF(REGEXMATCH(TRIM(I48),""^[A-Za-z0-9._%+-]+@[A-Za-z0-9.-]+\.[A-Za-z]{2,}$""),""✅ Valid"",""❌ Invalid"")"),"✅ Valid") -> ✅ Valid | K48: +4800345674 | L48: =IFERROR(__xludf.DUMMYFUNCTION("IF(K48=""N/A"", """", REGEXREPLACE( SUBSTITUTE(SUBSTITUTE(SUBSTITUTE(TO_TEXT(K48), CHAR(160),""""), UNICHAR(8239),""""), UNICHAR(8201),""""),""[+\-/(): )]"", """"))"),"4800345674") -> 4800345674 | M48: =IFERROR(__xludf.DUMMYFUNCTION("IF(L48="""","""", REGEXEXTRACT(REGEXREPLACE(L48,""x"", """"), ""[0-9]+""))"),"4800345674") -> 4800345674 | N48: =IF(LEFT(M48,2)="48", RIGHT(M48,LEN(M48)-2),M48) -> 00345674 | O48: =IFERROR(__xludf.DUMMYFUNCTION("REGEXMATCH(TO_TEXT(N48), ""^(5[013679]|6[069]|7[2-9]|88)"")"),FALSE) -> FALSE | Q48: =IF(AND(O48=TRUE, P48=9), "✅ VALID", "❌ INVALID") -> ❌ INVALID | R48: Poland | S48: 44934 | T48: =IFERROR(__xludf.DUMMYFUNCTION("IF(ISNUMBER(S48),TEXT(S48,""yyyy-MM-dd""),REGEXREPLACE(REGEXREPLACE(TO_TEXT(S48),""[^0-9a-zA-Z]+"",""-""),""[^0-9]*$"",""""))"),"2023-01-08") -> 2023-01-08 | U48: 2023-01-08 | Y48: 2023-01-08
A49: CUST-5047 | B49: ✅ Unique | C49: Marek King | D49: =IFERROR(__xludf.DUMMYFUNCTION("PROPER(REGEXREPLACE(TRIM(C49),""\s+"","" ""))"),"Marek King") -> Marek King | E49: =IFERROR(__xludf.DUMMYFUNCTION("IF(LEN(D49:D701), COUNTA(SPLIT(D49:D701,"" "")), """")"),2.0) -> 2 | F49: =IF(D49=G49,"✅","❌") -> ❌ | G49: Marek Knig | H49: =LOWER(TRIM(I49)) -> marek.knig@yahoo.com | I49: marek.knig@yahoo.com | J49: =IFERROR(__xludf.DUMMYFUNCTION("IF(REGEXMATCH(TRIM(I49),""^[A-Za-z0-9._%+-]+@[A-Za-z0-9.-]+\.[A-Za-z]{2,}$""),""✅ Valid"",""❌ Invalid"")"),"✅ Valid") -> ✅ Valid | K49: +48+536804542 | L49: =IFERROR(__xludf.DUMMYFUNCTION("IF(K49=""N/A"", """", REGEXREPLACE( SUBSTITUTE(SUBSTITUTE(SUBSTITUTE(TO_TEXT(K49), CHAR(160),""""), UNICHAR(8239),""""), UNICHAR(8201),""""),""[+\-/(): )]"", """"))"),"48536804542") -> 48536804542 | M49: =IFERROR(__xludf.DUMMYFUNCTION("IF(L49="""","""", REGEXEXTRACT(REGEXREPLACE(L49,""x"", """"), ""[0-9]+""))"),"48536804542") -> 48536804542 | N49: =IF(LEFT(M49,2)="48", RIGHT(M49,LEN(M49)-2),M49) -> 536804542 | O49: =IFERROR(__xludf.DUMMYFUNCTION("REGEXMATCH(TO_TEXT(N49), ""^(5[013679]|6[069]|7[2-9]|88)"")"),TRUE) -> TRUE | P49: =LEN(N49) -> 9 | Q49: =IF(AND(O49=TRUE, P49=9), "✅ VALID", "❌ INVALID") -> ✅ VALID | R49: Poland | S49: 44845 | T49: =IFERROR(__xludf.DUMMYFUNCTION("IF(ISNUMBER(S49),TEXT(S49,""yyyy-MM-dd""),REGEXREPLACE(REGEXREPLACE(TO_TEXT(S49),""[^0-9a-zA-Z]+"",""-""),""[^0-9]*$"",""""))"),"2022-10-11") -> 2022-10-11 | U49: 2022-10-11 | Y49: 2022-10-11
A50: CUST-5048 | B50: ✅ Unique | C50: Adam Rodriguez | D50: =IFERROR(__xludf.DUMMYFUNCTION("PROPER(REGEXREPLACE(TRIM(C50),""\s+"","" ""))"),"Adam Rodriguez") -> Adam Rodriguez | E50: =IFERROR(__xludf.DUMMYFUNCTION("IF(LEN(D50:D701), COUNTA(SPLIT(D50:D701,"" "")), """")"),2.0) -> 2 | F50: =IF(D50=G50,"✅","❌") -> ✅ | G50: =IFERROR(__xludf.DUMMYFUNCTION("REGEXEXTRACT(PROPER(SUBSTITUTE(TRIM(I50),""."","" "")),""^[^@]+"")"),"Adam Rodriguez") -> Adam Rodriguez | H50: =LOWER(TRIM(I50)) -> adam.rodriguez@company.co.uk | I50: adam.rodriguez@company.co.uk | J50: =IFERROR(__xludf.DUMMYFUNCTION("IF(REGEXMATCH(TRIM(I50),""^[A-Za-z0-9._%+-]+@[A-Za-z0-9.-]+\.[A-Za-z]{2,}$""),""✅ Valid"",""❌ Invalid"")"),"✅ Valid") -> ✅ Valid | K50: +44 31-99-94-89-82-3 | L50: =IFERROR(__xludf.DUMMYFUNCTION("IF(OR(K50=""N/A"", K50=""missing"", K50=""none""), """", REGEXREPLACE( SUBSTITUTE(SUBSTITUTE(SUBSTITUTE(TO_TEXT(K50), CHAR(160),""""), UNICHAR(8239),""""), UNICHAR(8201),""""),""[+\-/(): )]"", """"))"),"4431999489823") -> 4431999489823 | M50: =IFERROR(__xludf.DUMMYFUNCTION("IF(L50="""","""", REGEXEXTRACT(REGEXREPLACE(L50,""x"", """"), ""[0-9]+""))"),"4431999489823") -> 4431999489823 | N50: =IF(LEFT(M50,2)="44", RIGHT(M50,LEN(M50)-2),M50) -> 31999489823 | O50: =IFERROR(__xludf.DUMMYFUNCTION("REGEXMATCH(TO_TEXT(N50), ""^07[1-57-9]"")"),FALSE) -> FALSE | P50: =LEN(N50) -> 11 | Q50: =IF(AND(O50=TRUE, P50=11), "✅ VALID", "❌ INVALID") -> ❌ INVALID | R50: UK | S50: 45161 | T50: =IFERROR(__xludf.DUMMYFUNCTION("IF(ISNUMBER(S50),TEXT(S50,""yyyy-MM-dd""),REGEXREPLACE(REGEXREPLACE(TO_TEXT(S50),""[^0-9a-zA-Z]+"",""-""),""[^0-9]*$"",""""))"),"2023-08-23") -> 2023-08-23 | U50: 2023-08-23 | Y50: 2023-08-23
A51: CUST-5049 | B51: ✅ Unique | C51: Hanna Muller | D51: =IFERROR(__xludf.DUMMYFUNCTION("PROPER(REGEXREPLACE(TRIM(C51),""\s+"","" ""))"),"Hanna Muller") -> Hanna Muller | E51: =IFERROR(__xludf.DUMMYFUNCTION("IF(LEN(D51:D701), COUNTA(SPLIT(D51:D701,"" "")), """")"),2.0) -> 2 | F51: =IF(D51=G51,"✅","❌") -> ✅ | G51: =IFERROR(__xludf.DUMMYFUNCTION("REGEXEXTRACT(PROPER(SUBSTITUTE(TRIM(I51),""."","" "")),""^[^@]+"")"),"Hanna Muller") -> Hanna Muller | H51: =LOWER(TRIM(I51)) -> hanna.muller@shop.io | I51: hanna.muller@shop.io | J51: =IFERROR(__xludf.DUMMYFUNCTION("IF(REGEXMATCH(TRIM(I51),""^[A-Za-z0-9._%+-]+@[A-Za-z0-9.-]+\.[A-Za-z]{2,}$""),""✅ Valid"",""❌ Invalid"")"),"✅ Valid") -> ✅ Valid | K51: +353 415 419 920 7 | L51: =IFERROR(__xludf.DUMMYFUNCTION("IF(OR(K51=""N/A"", K51=""missing"", K51=""none""), """", REGEXREPLACE( SUBSTITUTE(SUBSTITUTE(SUBSTITUTE(TO_TEXT(K51), CHAR(160),""""), UNICHAR(8239),""""), UNICHAR(8201),""""),""[+\-/(): )]"", """"))"),"3534154199207") -> 3534154199207 | M51: =IFERROR(__xludf.DUMMYFUNCTION("IF(L51="""","""", REGEXEXTRACT(REGEXREPLACE(L51,""x"", """"), ""[0-9]+""))"),"3534154199207") -> 3534154199207 | N51: =IF(LEFT(M51,3)="353", RIGHT(M51,LEN(M51)-3),M51) -> 4154199207 | O51: =IFERROR(__xludf.DUMMYFUNCTION("REGEXMATCH(TO_TEXT(N51), ""^0(83|85|86|87|89)"")"),FALSE) -> FALSE | P51: =LEN(N51) -> 10 | Q51: =IF(AND(O51=TRUE, P48=10), "✅ VALID", "❌ INVALID") -> ❌ INVALID | R51: Ireland | S51: 45501 | T51: =IFERROR(__xludf.DUMMYFUNCTION("IF(ISNUMBER(S51),TEXT(S51,""yyyy-MM-dd""),REGEXREPLACE(REGEXREPLACE(TO_TEXT(S51),""[^0-9a-zA-Z]+"",""-""),""[^0-9]*$"",""""))"),"2024-07-28") -> 2024-07-28 | U51: 2024-07-28 | Y51: 2024-07-28
A52: CUST-5050 | B52: ✅ Unique | C52: Gabe Kowalczyk | D52: =IFERROR(__xludf.DUMMYFUNCTION("PROPER(REGEXREPLACE(TRIM(C52),""\s+"","" ""))"),"Gabe Kowalczyk") -> Gabe Kowalczyk | E52: =IFERROR(__xludf.DUMMYFUNCTION("IF(LEN(D52:D701), COUNTA(SPLIT(D52:D701,"" "")), """")"),2.0) -> 2 | F52: =IF(D52=G52,"✅","❌") -> ✅ | G52: =IFERROR(__xludf.DUMMYFUNCTION("REGEXEXTRACT(PROPER(SUBSTITUTE(TRIM(I52),""."","" "")),""^[^@]+"")"),"Gabe Kowalczyk") -> Gabe Kowalczyk | H52: =LOWER(TRIM(I52)) -> gabe.kowalczyk@company.co.uk | I52: gabe.kowalczyk@company.co.uk | J52: =IFERROR(__xludf.DUMMYFUNCTION("IF(REGEXMATCH(TRIM(I52),""^[A-Za-z0-9._%+-]+@[A-Za-z0-9.-]+\.[A-Za-z]{2,}$""),""✅ Valid"",""❌ Invalid"")"),"✅ Valid") -> ✅ Valid | K52: +44 0226 8109 4 | L52: =IFERROR(__xludf.DUMMYFUNCTION("IF(OR(K52=""N/A"", K52=""missing"", K52=""none""), """", REGEXREPLACE( SUBSTITUTE(SUBSTITUTE(SUBSTITUTE(TO_TEXT(K52), CHAR(160),""""), UNICHAR(8239),""""), UNICHAR(8201),""""),""[+\-/(): )]"", """"))"),"44022681094") -> 44022681094 | M52: =IFERROR(__xludf.DUMMYFUNCTION("IF(L52="""","""", REGEXEXTRACT(REGEXREPLACE(L52,""x"", """"), ""[0-9]+""))"),"44022681094") -> 44022681094 | N52: =IF(LEFT(M52,2)="44", RIGHT(M52,LEN(M52)-2),M52) -> 022681094 | O52: =IFERROR(__xludf.DUMMYFUNCTION("REGEXMATCH(TO_TEXT(N52), ""^07[1-57-9]"")"),FALSE) -> FALSE | P52: =LEN(N52) -> 9 | Q52: =IF(AND(O52=TRUE, P52=11), "✅ VALID", "❌ INVALID") -> ❌ INVALID | R52: UK | S52: 01/17/2023 22:49 | T52: =IFERROR(__xludf.DUMMYFUNCTION("IF(ISNUMBER(S52),TEXT(S52,""yyyy-MM-dd""),REGEXREPLACE(REGEXREPLACE(TO_TEXT(S52),""[^0-9a-zA-Z]+"",""-""),""[^0-9]*$"",""""))"),"01-17-2023-22-49") -> 01-17-2023-22-49 | U52: =TEXT(T52,"yyyy-MM-dd") -> 01-17-2023-22-49 | V52: =IFERROR(__xludf.DUMMYFUNCTION("REGEXEXTRACT(U52,""^\d{2}-\d{2}-\d{4}"")"),"01-17-2023") -> 01-17-2023 | W52: =TEXT(V52,"yyyy-MM-dd") -> 01-17-2023 | X52: 2023-01-17 | Y52: 2023-01-17
A53: CUST-5051 | B53: ✅ Unique | C53: Omar Novak | D53: =IFERROR(__xludf.DUMMYFUNCTION("PROPER(REGEXREPLACE(TRIM(C53),""\s+"","" ""))"),"Omar Novak") -> Omar Novak | E53: =IFERROR(__xludf.DUMMYFUNCTION("IF(LEN(D53:D701), COUNTA(SPLIT(D53:D701,"" "")), """")"),2.0) -> 2 | F53: =IF(D53=G53,"✅","❌") -> ✅ | G53: =IFERROR(__xludf.DUMMYFUNCTION("REGEXEXTRACT(PROPER(SUBSTITUTE(TRIM(I53),""."","" "")),""^[^@]+"")"),"Omar Novak") -> Omar Novak | H53: =LOWER(TRIM(I53)) -> omar.novak@yahoo.com | I53: omar.novak@yahoo.com | J53: =IFERROR(__xludf.DUMMYFUNCTION("IF(REGEXMATCH(TRIM(I53),""^[A-Za-z0-9._%+-]+@[A-Za-z0-9.-]+\.[A-Za-z]{2,}$""),""✅ Valid"",""❌ Invalid"")"),"✅ Valid") -> ✅ Valid | K53: +175558712905 | L53: =IFERROR(__xludf.DUMMYFUNCTION("IF(OR(K53=""N/A"", K53=""missing"", K53=""none""), """", REGEXREPLACE( SUBSTITUTE(SUBSTITUTE(SUBSTITUTE(TO_TEXT(K53), CHAR(160),""""), UNICHAR(8239),""""), UNICHAR(8201),""""),""[+\-/(): )]"", """"))"),"175558712905") -> 175558712905 | M53: =IFERROR(__xludf.DUMMYFUNCTION("IF(L53="""","""", REGEXEXTRACT(REGEXREPLACE(L53,""x"", """"), ""[0-9]+""))"),"175558712905") -> 175558712905 | N53: =IF(LEFT(M53,1)="1", RIGHT(M53,LEN(M53)-1),M53) -> 75558712905 | O53: =IFERROR(__xludf.DUMMYFUNCTION("REGEXMATCH(TO_TEXT(N53), ""^[2-9][0-9]{9}$"")"),FALSE) -> FALSE | P53: =LEN(N53) -> 11 | Q53: =IF(AND(O53=TRUE, P53=10), "✅ VALID", "❌ INVALID") -> ❌ INVALID | R53: USA | S53: 44786 | T53: =IFERROR(__xludf.DUMMYFUNCTION("IF(ISNUMBER(S53),TEXT(S53,""yyyy-MM-dd""),REGEXREPLACE(REGEXREPLACE(TO_TEXT(S53),""[^0-9a-zA-Z]+"",""-""),""[^0-9]*$"",""""))"),"2022-08-13") -> 2022-08-13 | U53: 2022-08-13 | Y53: 2022-08-13
A54: CUST-5052 | B54: ✅ Unique | C54: Zack Kowalczyk | D54: =IFERROR(__xludf.DUMMYFUNCTION("PROPER(REGEXREPLACE(TRIM(C54),""\s+"","" ""))"),"Zack Kowalczyk") -> Zack Kowalczyk | E54: =IFERROR(__xludf.DUMMYFUNCTION("IF(LEN(D54:D701), COUNTA(SPLIT(D54:D701,"" "")), """")"),2.0) -> 2 | F54: =IF(D54=G54,"✅","❌") -> ✅ | G54: =IFERROR(__xludf.DUMMYFUNCTION("REGEXEXTRACT(PROPER(SUBSTITUTE(TRIM(I54),""."","" "")),""^[^@]+"")"),"Zack Kowalczyk") -> Zack Kowalczyk | H54: =LOWER(TRIM(I54)) -> zack.kowalczyk@company.co.uk | I54: ZACK.KOWALCZYK@COMPANY.CO.UK | J54: =IFERROR(__xludf.DUMMYFUNCTION("IF(REGEXMATCH(TRIM(I54),""^[A-Za-z0-9._%+-]+@[A-Za-z0-9.-]+\.[A-Za-z]{2,}$""),""✅ Valid"",""❌ Invalid"")"),"✅ Valid") -> ✅ Valid | K54: tel:+39442504542 | L54: =IFERROR(__xludf.DUMMYFUNCTION("IF(OR(K54=""N/A"", K54=""missing"", K54=""none""), """", REGEXREPLACE( SUBSTITUTE(SUBSTITUTE(SUBSTITUTE(TO_TEXT(K54), CHAR(160),""""), UNICHAR(8239),""""), UNICHAR(8201),""""),""[+\-/(): )]"", """"))"),"tel39442504542") -> tel39442504542 | M54: =IFERROR(__xludf.DUMMYFUNCTION("IF(L54="""","""", REGEXEXTRACT(REGEXREPLACE(L54,""x"", """"), ""[0-9]+""))"),"39442504542") -> 39442504542 | N54: =IF(LEFT(M54,2)="39", RIGHT(M54,LEN(M54)-2),M54) -> 442504542 | O54: =IFERROR(__xludf.DUMMYFUNCTION("REGEXMATCH(TO_TEXT(N54), ""^3"")"),FALSE) -> FALSE | P54: =LEN(N54) -> 9 | Q54: =IF(AND(O54=TRUE,OR(P54=9, P54=10 )), "✅ VALID", "❌ INVALID") -> ❌ INVALID | R54: Italy | S54: 44852 | T54: =IFERROR(__xludf.DUMMYFUNCTION("IF(ISNUMBER(S54),TEXT(S54,""yyyy-MM-dd""),REGEXREPLACE(REGEXREPLACE(TO_TEXT(S54),""[^0-9a-zA-Z]+"",""-""),""[^0-9]*$"",""""))"),"2022-10-18") -> 2022-10-18 | U54: 2022-10-18 | Y54: 2022-10-18
A55: CUST-5053 | B55: ✅ Unique | C55: Qi Martinez | D55: =IFERROR(__xludf.DUMMYFUNCTION("PROPER(REGEXREPLACE(TRIM(C55),""\s+"","" ""))"),"Qi Martinez") -> Qi Martinez | E55: =IFERROR(__xludf.DUMMYFUNCTION("IF(LEN(D55:D701), COUNTA(SPLIT(D55:D701,"" "")), """")"),2.0) -> 2 | F55: =IF(D55=G55,"✅","❌") -> ✅ | G55: =IFERROR(__xludf.DUMMYFUNCTION("REGEXEXTRACT(PROPER(SUBSTITUTE(TRIM(I55),""."","" "")),""^[^@]+"")"),"Qi Martinez") -> Qi Martinez | H55: =LOWER(TRIM(I55)) -> qi.martinez@yahoo.com | I55: qi.martinez@yahoo.com | J55: =IFERROR(__xludf.DUMMYFUNCTION("IF(REGEXMATCH(TRIM(I55),""^[A-Za-z0-9._%+-]+@[A-Za-z0-9.-]+\.[A-Za-z]{2,}$""),""✅ Valid"",""❌ Invalid"")"),"✅ Valid") -> ✅ Valid | K55: +49+176536364 | L55: =IFERROR(__xludf.DUMMYFUNCTION("IF(OR(K55=""N/A"", K55=""missing"", K55=""none""), """", REGEXREPLACE( SUBSTITUTE(SUBSTITUTE(SUBSTITUTE(TO_TEXT(K55), CHAR(160),""""), UNICHAR(8239),""""), UNICHAR(8201),""""),""[+\-/(): )]"", """"))"),"49176536364") -> 49176536364 | M55: =IFERROR(__xludf.DUMMYFUNCTION("IF(L55="""","""", REGEXEXTRACT(REGEXREPLACE(L55,""x"", """"), ""[0-9]+""))"),"49176536364") -> 49176536364 | N55: =IF(LEFT(M55,2)="49", RIGHT(M55,LEN(M55)-2),M55) -> 176536364 | O55: =IFERROR(__xludf.DUMMYFUNCTION("REGEXMATCH(TO_TEXT(N55), ""^0(15|16|17)"")"),FALSE) -> FALSE | P55: =LEN(N55) -> 9 | Q55: =IF(AND(O55=TRUE,OR(P55=10, P55=11)), "✅ VALID", "❌ INVALID") -> ❌ INVALID | R55: Germany | S55: 45497.401 | T55: =IFERROR(__xludf.DUMMYFUNCTION("IF(ISNUMBER(S55),TEXT(S55,""yyyy-MM-dd""),REGEXREPLACE(REGEXREPLACE(TO_TEXT(S55),""[^0-9a-zA-Z]+"",""-""),""[^0-9]*$"",""""))"),"2024-07-24") -> 2024-07-24 | U55: 2024-07-24 | Y55: 2024-07-24
A56: CUST-5054 | B56: ✅ Unique | C56: Xenia Rossi | D56: =IFERROR(__xludf.DUMMYFUNCTION("PROPER(REGEXREPLACE(TRIM(C56),""\s+"","" ""))"),"Xenia Rossi") -> Xenia Rossi | E56: =IFERROR(__xludf.DUMMYFUNCTION("IF(LEN(D56:D701), COUNTA(SPLIT(D56:D701,"" "")), """")"),2.0) -> 2 | F56: =IF(D56=G56,"✅","❌") -> ✅ | G56: =IFERROR(__xludf.DUMMYFUNCTION("REGEXEXTRACT(PROPER(SUBSTITUTE(TRIM(I56),""."","" "")),""^[^@]+"")"),"Xenia Rossi") -> Xenia Rossi | H56: =LOWER(TRIM(I56)) -> xenia.rossi@company.co.uk | I56: xenia.rossi@company.co.uk | J56: =IFERROR(__xludf.DUMMYFUNCTION("IF(REGEXMATCH(TRIM(I56),""^[A-Za-z0-9._%+-]+@[A-Za-z0-9.-]+\.[A-Za-z]{2,}$""),""✅ Valid"",""❌ Invalid"")"),"✅ Valid") -> ✅ Valid | K56: +48 196 677212 | L56: =IFERROR(__xludf.DUMMYFUNCTION("IF(K56=""N/A"", """", REGEXREPLACE( SUBSTITUTE(SUBSTITUTE(SUBSTITUTE(TO_TEXT(K56), CHAR(160),""""), UNICHAR(8239),""""), UNICHAR(8201),""""),""[+\-/(): )]"", """"))"),"48196677212") -> 48196677212 | M56: =IFERROR(__xludf.DUMMYFUNCTION("IF(L56="""","""", REGEXEXTRACT(REGEXREPLACE(L56,""x"", """"), ""[0-9]+""))"),"48196677212") -> 48196677212 | N56: =IF(LEFT(M56,2)="48", RIGHT(M56,LEN(M56)-2),M56) -> 196677212 | O56: =IFERROR(__xludf.DUMMYFUNCTION("REGEXMATCH(TO_TEXT(N56), ""^(5[013679]|6[069]|7[2-9]|88)"")"),FALSE) -> FALSE | Q56: =IF(AND(O56=TRUE, P56=9), "✅ VALID", "❌ INVALID") -> ❌ INVALID | R56: Poland | S56: 45233 | T56: =IFERROR(__xludf.DUMMYFUNCTION("IF(ISNUMBER(S56),TEXT(S56,""yyyy-MM-dd""),REGEXREPLACE(REGEXREPLACE(TO_TEXT(S56),""[^0-9a-zA-Z]+"",""-""),""[^0-9]*$"",""""))"),"2023-11-03") -> 2023-11-03 | U56: 2023-11-03 | Y56: 2023-11-03
A57: CUST-5055 | B57: ✅ Unique | C57: Jade Loepz | D57: =IFERROR(__xludf.DUMMYFUNCTION("PROPER(REGEXREPLACE(TRIM(C57),""\s+"","" ""))"),"Jade Loepz") -> Jade Loepz | E57: =IFERROR(__xludf.DUMMYFUNCTION("IF(LEN(D57:D701), COUNTA(SPLIT(D57:D701,"" "")), """")"),2.0) -> 2 | K57: +1-423-203-8499 | R57: Italy | S57: 04/01/2025
A58: CUST-5056 | B58: ✅ Unique | C58: Zack Muller | D58: =IFERROR(__xludf.DUMMYFUNCTION("PROPER(REGEXREPLACE(TRIM(C58),""\s+"","" ""))"),"Zack Muller") -> Zack Muller | E58: =IFERROR(__xludf.DUMMYFUNCTION("IF(LEN(D58:D701), COUNTA(SPLIT(D58:D701,"" "")), """")"),2.0) -> 2 | F58: =IF(D58=G58,"✅","❌") -> ✅ | G58: =IFERROR(__xludf.DUMMYFUNCTION("REGEXEXTRACT(PROPER(SUBSTITUTE(TRIM(I58),""."","" "")),""^[^@]+"")"),"Zack Muller") -> Zack Muller | H58: =LOWER(TRIM(I58)) -> zack.muller@shop.io | I58: Zack.Muller@Shop.Io | J58: =IFERROR(__xludf.DUMMYFUNCTION("IF(REGEXMATCH(TRIM(I58),""^[A-Za-z0-9._%+-]+@[A-Za-z0-9.-]+\.[A-Za-z]{2,}$""),""✅ Valid"",""❌ Invalid"")"),"✅ Valid") -> ✅ Valid | K58: +1 554 46009220 | L58: =IFERROR(__xludf.DUMMYFUNCTION("IF(OR(K58=""N/A"", K58=""missing"", K58=""none""), """", REGEXREPLACE( SUBSTITUTE(SUBSTITUTE(SUBSTITUTE(TO_TEXT(K58), CHAR(160),""""), UNICHAR(8239),""""), UNICHAR(8201),""""),""[+\-/(): )]"", """"))"),"155446009220") -> 155446009220 | M58: =IFERROR(__xludf.DUMMYFUNCTION("IF(L58="""","""", REGEXEXTRACT(REGEXREPLACE(L58,""x"", """"), ""[0-9]+""))"),"155446009220") -> 155446009220 | N58: =IF(LEFT(M58,1)="1", RIGHT(M58,LEN(M58)-1),M58) -> 55446009220 | O58: =IFERROR(__xludf.DUMMYFUNCTION("REGEXMATCH(TO_TEXT(N58), ""^[2-9][0-9]{9}$"")"),FALSE) -> FALSE | P58: =LEN(N58) -> 11 | Q58: =IF(AND(O58=TRUE, P58=10), "✅ VALID", "❌ INVALID") -> ❌ INVALID | R58: USA | S58: 45073 | T58: =IFERROR(__xludf.DUMMYFUNCTION("IF(ISNUMBER(S58),TEXT(S58,""yyyy-MM-dd""),REGEXREPLACE(REGEXREPLACE(TO_TEXT(S58),""[^0-9a-zA-Z]+"",""-""),""[^0-9]*$"",""""))"),"2023-05-27") -> 2023-05-27 | U58: 2023-05-27 | Y58: 2023-05-27
A59: CUST-5057 | B59: ✅ Unique | C59: Carlos Lee | D59: =IFERROR(__xludf.DUMMYFUNCTION("PROPER(REGEXREPLACE(TRIM(C59),""\s+"","" ""))"),"Carlos Lee") -> Carlos Lee | E59: =IFERROR(__xludf.DUMMYFUNCTION("IF(LEN(D59:D701), COUNTA(SPLIT(D59:D701,"" "")), """")"),2.0) -> 2 | F59: =IF(D59=G59,"✅","❌") -> ✅ | G59: =IFERROR(__xludf.DUMMYFUNCTION("REGEXEXTRACT(PROPER(SUBSTITUTE(TRIM(I59),""."","" "")),""^[^@]+"")"),"Carlos Lee") -> Carlos Lee | H59: =LOWER(TRIM(I59)) -> carlos.lee@company.co.uk | I59: carlos.lee@company.co.uk | J59: =IFERROR(__xludf.DUMMYFUNCTION("IF(REGEXMATCH(TRIM(I59),""^[A-Za-z0-9._%+-]+@[A-Za-z0-9.-]+\.[A-Za-z]{2,}$""),""✅ Valid"",""❌ Invalid"")"),"✅ Valid") -> ✅ Valid | K59: 4443668488407 | L59: =IFERROR(__xludf.DUMMYFUNCTION("IF(OR(K59=""N/A"", K59=""missing"", K59=""none""), """", REGEXREPLACE( SUBSTITUTE(SUBSTITUTE(SUBSTITUTE(TO_TEXT(K59), CHAR(160),""""), UNICHAR(8239),""""), UNICHAR(8201),""""),""[+\-/(): )]"", """"))"),"4443668488407") -> 4443668488407 | M59: =IFERROR(__xludf.DUMMYFUNCTION("IF(L59="""","""", REGEXEXTRACT(REGEXREPLACE(L59,""x"", """"), ""[0-9]+""))"),"4443668488407") -> 4443668488407 | N59: =IF(LEFT(M59,2)="44", RIGHT(M59,LEN(M59)-2),M59) -> 43668488407 | O59: =IFERROR(__xludf.DUMMYFUNCTION("REGEXMATCH(TO_TEXT(N59), ""^07[1-57-9]"")"),FALSE) -> FALSE | P59: =LEN(N59) -> 11 | Q59: =IF(AND(O59=TRUE, P59=11), "✅ VALID", "❌ INVALID") -> ❌ INVALID | R59: UK | S59: 44725.516 | T59: =IFERROR(__xludf.DUMMYFUNCTION("IF(ISNUMBER(S59),TEXT(S59,""yyyy-MM-dd""),REGEXREPLACE(REGEXREPLACE(TO_TEXT(S59),""[^0-9a-zA-Z]+"",""-""),""[^0-9]*$"",""""))"),"2022-06-13") -> 2022-06-13 | U59: 2022-06-13 | Y59: 2022-06-13
A60: CUST-5058 | B60: ✅ Unique | C60: Carlos Lee | D60: =IFERROR(__xludf.DUMMYFUNCTION("PROPER(REGEXREPLACE(TRIM(C60),""\s+"","" ""))"),"Carlos Lee") -> Carlos Lee | E60: =IFERROR(__xludf.DUMMYFUNCTION("IF(LEN(D60:D701), COUNTA(SPLIT(D60:D701,"" "")), """")"),2.0) -> 2 | F60: =IF(D60=G60,"✅","❌") -> ✅ | G60: =IFERROR(__xludf.DUMMYFUNCTION("REGEXEXTRACT(PROPER(SUBSTITUTE(TRIM(I60),""."","" "")),""^[^@]+"")"),"Carlos Lee") -> Carlos Lee | H60: =LOWER(TRIM(I60)) -> carlos.lee@company.co.uk | I60: carlos.lee@company.co.uk | J60: =IFERROR(__xludf.DUMMYFUNCTION("IF(REGEXMATCH(TRIM(I60),""^[A-Za-z0-9._%+-]+@[A-Za-z0-9.-]+\.[A-Za-z]{2,}$""),""✅ Valid"",""❌ Invalid"")"),"✅ Valid") -> ✅ Valid | K60: +44+7536233404 | L60: =IFERROR(__xludf.DUMMYFUNCTION("IF(OR(K60=""N/A"", K60=""missing"", K60=""none""), """", REGEXREPLACE( SUBSTITUTE(SUBSTITUTE(SUBSTITUTE(TO_TEXT(K60), CHAR(160),""""), UNICHAR(8239),""""), UNICHAR(8201),""""),""[+\-/(): )]"", """"))"),"447536233404") -> 447536233404 | M60: =IFERROR(__xludf.DUMMYFUNCTION("IF(L60="""","""", REGEXEXTRACT(REGEXREPLACE(L60,""x"", """"), ""[0-9]+""))"),"447536233404") -> 447536233404 | N60: =IF(LEFT(M60,2)="44", RIGHT(M60,LEN(M60)-2),M60) -> 7536233404 | O60: =IFERROR(__xludf.DUMMYFUNCTION("REGEXMATCH(TO_TEXT(N60), ""^07[1-57-9]"")"),FALSE) -> FALSE | P60: =LEN(N60) -> 10 | Q60: =IF(AND(O60=TRUE, P60=11), "✅ VALID", "❌ INVALID") -> ❌ INVALID | R60: UK | S60: 44725.516 | T60: =IFERROR(__xludf.DUMMYFUNCTION("IF(ISNUMBER(S60),TEXT(S60,""yyyy-MM-dd""),REGEXREPLACE(REGEXREPLACE(TO_TEXT(S60),""[^0-9a-zA-Z]+"",""-""),""[^0-9]*$"",""""))"),"2022-06-13") -> 2022-06-13 | U60: 2022-06-13 | Y60: 2022-06-13
A61: CUST-5059 | B61: ✅ Unique | C61: Zack Taylor | D61: =IFERROR(__xludf.DUMMYFUNCTION("PROPER(REGEXREPLACE(TRIM(C61),""\s+"","" ""))"),"Zack Taylor") -> Zack Taylor | E61: =IFERROR(__xludf.DUMMYFUNCTION("IF(LEN(D61:D701), COUNTA(SPLIT(D61:D701,"" "")), """")"),2.0) -> 2 | F61: =IF(D61=G61,"✅","❌") -> ✅ | G61: =IFERROR(__xludf.DUMMYFUNCTION("REGEXEXTRACT(PROPER(SUBSTITUTE(TRIM(I61),""."","" "")),""^[^@]+"")"),"Zack Taylor") -> Zack Taylor | H61: =LOWER(TRIM(I61)) -> zack.taylor@outloo.kcom | I61: zack.taylor@outloo.kcom | J61: =IFERROR(__xludf.DUMMYFUNCTION("IF(REGEXMATCH(TRIM(I61),""^[A-Za-z0-9._%+-]+@[A-Za-z0-9.-]+\.[A-Za-z]{2,}$""),""✅ Valid"",""❌ Invalid"")"),"✅ Valid") -> ✅ Valid | K61: +353+59277378 | L61: =IFERROR(__xludf.DUMMYFUNCTION("IF(OR(K61=""N/A"", K61=""missing"", K61=""none""), """", REGEXREPLACE( SUBSTITUTE(SUBSTITUTE(SUBSTITUTE(TO_TEXT(K61), CHAR(160),""""), UNICHAR(8239),""""), UNICHAR(8201),""""),""[+\-/(): )]"", """"))"),"35359277378") -> 35359277378 | M61: =IFERROR(__xludf.DUMMYFUNCTION("IF(L61="""","""", REGEXEXTRACT(REGEXREPLACE(L61,""x"", """"), ""[0-9]+""))"),"35359277378") -> 35359277378 | N61: =IF(LEFT(M61,3)="353", RIGHT(M61,LEN(M61)-3),M61) -> 59277378 | O61: =IFERROR(__xludf.DUMMYFUNCTION("REGEXMATCH(TO_TEXT(N61), ""^0(83|85|86|87|89)"")"),FALSE) -> FALSE | P61: =LEN(N61) -> 8 | Q61: =IF(AND(O61=TRUE, P58=10), "✅ VALID", "❌ INVALID") -> ❌ INVALID | R61: Ireland | S61: 12.02.2022 21:07 | T61: =IFERROR(__xludf.DUMMYFUNCTION("IF(ISNUMBER(S61),TEXT(S61,""yyyy-MM-dd""),REGEXREPLACE(REGEXREPLACE(TO_TEXT(S61),""[^0-9a-zA-Z]+"",""-""),""[^0-9]*$"",""""))"),"12-02-2022-21-07") -> 12-02-2022-21-07 | U61: =TEXT(T61,"yyyy-MM-dd") -> 12-02-2022-21-07 | V61: =IFERROR(__xludf.DUMMYFUNCTION("REGEXEXTRACT(U61,""^\d{2}-\d{2}-\d{4}"")"),"12-02-2022") -> 12-02-2022 | W61: 2022-02-12 | Y61: 2022-02-12
A62: CUST-5060 | B62: ✅ Unique | C62: Lia Williams | D62: =IFERROR(__xludf.DUMMYFUNCTION("PROPER(REGEXREPLACE(TRIM(C62),""\s+"","" ""))"),"Lia Williams") -> Lia Williams | E62: =IFERROR(__xludf.DUMMYFUNCTION("IF(LEN(D62:D701), COUNTA(SPLIT(D62:D701,"" "")), """")"),2.0) -> 2 | F62: =IF(D62=G62,"✅","❌") -> ✅ | G62: =IFERROR(__xludf.DUMMYFUNCTION("REGEXEXTRACT(PROPER(SUBSTITUTE(TRIM(I62),""."","" "")),""^[^@]+"")"),"Lia Williams") -> Lia Williams | H62: =LOWER(TRIM(I62)) -> lia.williams@gmail.com | I62: lia.williams@gmail.com | J62: =IFERROR(__xludf.DUMMYFUNCTION("IF(REGEXMATCH(TRIM(I62),""^[A-Za-z0-9._%+-]+@[A-Za-z0-9.-]+\.[A-Za-z]{2,}$""),""✅ Valid"",""❌ Invalid"")"),"✅ Valid") -> ✅ Valid | K62: +484482770584 | L62: =IFERROR(__xludf.DUMMYFUNCTION("IF(K62=""N/A"", """", REGEXREPLACE( SUBSTITUTE(SUBSTITUTE(SUBSTITUTE(TO_TEXT(K62), CHAR(160),""""), UNICHAR(8239),""""), UNICHAR(8201),""""),""[+\-/(): )]"", """"))"),"484482770584") -> 484482770584 | M62: =IFERROR(__xludf.DUMMYFUNCTION("IF(L62="""","""", REGEXEXTRACT(REGEXREPLACE(L62,""x"", """"), ""[0-9]+""))"),"484482770584") -> 484482770584 | N62: =IF(LEFT(M62,2)="48", RIGHT(M62,LEN(M62)-2),M62) -> 4482770584 | O62: =IFERROR(__xludf.DUMMYFUNCTION("REGEXMATCH(TO_TEXT(N62), ""^(5[013679]|6[069]|7[2-9]|88)"")"),FALSE) -> FALSE | Q62: =IF(AND(O62=TRUE, P62=9), "✅ VALID", "❌ INVALID") -> ❌ INVALID | R62: Poland | S62: 45649 | T62: =IFERROR(__xludf.DUMMYFUNCTION("IF(ISNUMBER(S62),TEXT(S62,""yyyy-MM-dd""),REGEXREPLACE(REGEXREPLACE(TO_TEXT(S62),""[^0-9a-zA-Z]+"",""-""),""[^0-9]*$"",""""))"),"2024-12-23") -> 2024-12-23 | U62: 2024-12-23 | Y62: 2024-12-23
A63: CUST-5061 | B63: ✅ Unique | C63: Hanna Dubois | D63: =IFERROR(__xludf.DUMMYFUNCTION("PROPER(REGEXREPLACE(TRIM(C63),""\s+"","" ""))"),"Hanna Dubois") -> Hanna Dubois | E63: =IFERROR(__xludf.DUMMYFUNCTION("IF(LEN(D63:D701), COUNTA(SPLIT(D63:D701,"" "")), """")"),2.0) -> 2 | F63: =IF(D63=G63,"✅","❌") -> ✅ | G63: =IFERROR(__xludf.DUMMYFUNCTION("REGEXEXTRACT(PROPER(SUBSTITUTE(TRIM(I63),""."","" "")),""^[^@]+"")"),"Hanna Dubois") -> Hanna Dubois | H63: =LOWER(TRIM(I63)) -> hanna.dubois@shop.io | I63: Hanna.Dubois@Shop.Io | J63: =IFERROR(__xludf.DUMMYFUNCTION("IF(REGEXMATCH(TRIM(I63),""^[A-Za-z0-9._%+-]+@[A-Za-z0-9.-]+\.[A-Za-z]{2,}$""),""✅ Valid"",""❌ Invalid"")"),"✅ Valid") -> ✅ Valid | K63: +4407459439187 | L63: =IFERROR(__xludf.DUMMYFUNCTION("IF(OR(K63=""N/A"", K63=""missing"", K63=""none""), """", REGEXREPLACE( SUBSTITUTE(SUBSTITUTE(SUBSTITUTE(TO_TEXT(K63), CHAR(160),""""), UNICHAR(8239),""""), UNICHAR(8201),""""),""[+\-/(): )]"", """"))"),"4407459439187") -> 4407459439187 | M63: =IFERROR(__xludf.DUMMYFUNCTION("IF(L63="""","""", REGEXEXTRACT(REGEXREPLACE(L63,""x"", """"), ""[0-9]+""))"),"4407459439187") -> 4407459439187 | N63: =IF(LEFT(M63,2)="44", RIGHT(M63,LEN(M63)-2),M63) -> 07459439187 | O63: =IFERROR(__xludf.DUMMYFUNCTION("REGEXMATCH(TO_TEXT(N63), ""^07[1-57-9]"")"),TRUE) -> TRUE | P63: =LEN(N63) -> 11 | Q63: =IF(AND(O63=TRUE, P63=11), "✅ VALID", "❌ INVALID") -> ✅ VALID | R63: UK | S63: 45569.029 | T63: =IFERROR(__xludf.DUMMYFUNCTION("IF(ISNUMBER(S63),TEXT(S63,""yyyy-MM-dd""),REGEXREPLACE(REGEXREPLACE(TO_TEXT(S63),""[^0-9a-zA-Z]+"",""-""),""[^0-9]*$"",""""))"),"2024-10-04") -> 2024-10-04 | U63: 2024-10-04 | Y63: 2024-10-04
A64: CUST-5062 | B64: ✅ Unique | C64: Adam Garcia | D64: =IFERROR(__xludf.DUMMYFUNCTION("PROPER(REGEXREPLACE(TRIM(C64),""\s+"","" ""))"),"Adam Garcia") -> Adam Garcia | E64: =IFERROR(__xludf.DUMMYFUNCTION("IF(LEN(D64:D701), COUNTA(SPLIT(D64:D701,"" "")), """")"),2.0) -> 2 | F64: =IF(D64=G64,"✅","❌") -> ✅ | G64: =IFERROR(__xludf.DUMMYFUNCTION("REGEXEXTRACT(PROPER(SUBSTITUTE(TRIM(I64),""."","" "")),""^[^@]+"")"),"Adam Garcia") -> Adam Garcia | H64: =LOWER(TRIM(I64)) -> adam.garcia@outlook.com | I64: adam.garcia@outlook.com | J64: =IFERROR(__xludf.DUMMYFUNCTION("IF(REGEXMATCH(TRIM(I64),""^[A-Za-z0-9._%+-]+@[A-Za-z0-9.-]+\.[A-Za-z]{2,}$""),""✅ Valid"",""❌ Invalid"")"),"✅ Valid") -> ✅ Valid | K64: +35381990402 | L64: =IFERROR(__xludf.DUMMYFUNCTION("IF(OR(K64=""N/A"", K64=""missing"", K64=""none""), """", REGEXREPLACE( SUBSTITUTE(SUBSTITUTE(SUBSTITUTE(TO_TEXT(K64), CHAR(160),""""), UNICHAR(8239),""""), UNICHAR(8201),""""),""[+\-/(): )]"", """"))"),"35381990402") -> 35381990402 | M64: =IFERROR(__xludf.DUMMYFUNCTION("IF(L64="""","""", REGEXEXTRACT(REGEXREPLACE(L64,""x"", """"), ""[0-9]+""))"),"35381990402") -> 35381990402 | N64: =IF(LEFT(M64,3)="353", RIGHT(M64,LEN(M64)-3),M64) -> 81990402 | O64: =IFERROR(__xludf.DUMMYFUNCTION("REGEXMATCH(TO_TEXT(N64), ""^0(83|85|86|87|89)"")"),FALSE) -> FALSE | P64: =LEN(N64) -> 8 | Q64: =IF(AND(O64=TRUE, P61=10), "✅ VALID", "❌ INVALID") -> ❌ INVALID | R64: Ireland | S64: 44572 | T64: =IFERROR(__xludf.DUMMYFUNCTION("IF(ISNUMBER(S64),TEXT(S64,""yyyy-MM-dd""),REGEXREPLACE(REGEXREPLACE(TO_TEXT(S64),""[^0-9a-zA-Z]+"",""-""),""[^0-9]*$"",""""))"),"2022-01-11") -> 2022-01-11 | U64: 2022-01-11 | Y64: 2022-01-11
A65: CUST-5063 | B65: ✅ Unique | C65: Wiktor Nowak | D65: =IFERROR(__xludf.DUMMYFUNCTION("PROPER(REGEXREPLACE(TRIM(C65),""\s+"","" ""))"),"Wiktor Nowak") -> Wiktor Nowak | E65: =IFERROR(__xludf.DUMMYFUNCTION("IF(LEN(D65:D701), COUNTA(SPLIT(D65:D701,"" "")), """")"),2.0) -> 2 | F65: =IF(D65=G65,"✅","❌") -> ✅ | G65: =IFERROR(__xludf.DUMMYFUNCTION("REGEXEXTRACT(PROPER(SUBSTITUTE(TRIM(I65),""."","" "")),""^[^@]+"")"),"Wiktor Nowak") -> Wiktor Nowak | H65: =LOWER(TRIM(I65)) -> wiktor.nowak@company.co.uk | I65: wiktor.nowak@company.co.uk | J65: =IFERROR(__xludf.DUMMYFUNCTION("IF(REGEXMATCH(TRIM(I65),""^[A-Za-z0-9._%+-]+@[A-Za-z0-9.-]+\.[A-Za-z]{2,}$""),""✅ Valid"",""❌ Invalid"")"),"✅ Valid") -> ✅ Valid | K65: +49 05-62-19-14-8 | L65: =IFERROR(__xludf.DUMMYFUNCTION("IF(OR(K65=""N/A"", K65=""missing"", K65=""none""), """", REGEXREPLACE( SUBSTITUTE(SUBSTITUTE(SUBSTITUTE(TO_TEXT(K65), CHAR(160),""""), UNICHAR(8239),""""), UNICHAR(8201),""""),""[+\-/(): )]"", """"))"),"49056219148") -> 49056219148 | M65: =IFERROR(__xludf.DUMMYFUNCTION("IF(L65="""","""", REGEXEXTRACT(REGEXREPLACE(L65,""x"", """"), ""[0-9]+""))"),"49056219148") -> 49056219148 | N65: =IF(LEFT(M65,2)="49", RIGHT(M65,LEN(M65)-2),M65) -> 056219148 | O65: =IFERROR(__xludf.DUMMYFUNCTION("REGEXMATCH(TO_TEXT(N65), ""^0(15|16|17)"")"),FALSE) -> FALSE | P65: =LEN(N65) -> 9 | Q65: =IF(AND(O65=TRUE,OR(P65=10, P65=11)), "✅ VALID", "❌ INVALID") -> ❌ INVALID | R65: Germany | S65: 45397 | T65: =IFERROR(__xludf.DUMMYFUNCTION("IF(ISNUMBER(S65),TEXT(S65,""yyyy-MM-dd""),REGEXREPLACE(REGEXREPLACE(TO_TEXT(S65),""[^0-9a-zA-Z]+"",""-""),""[^0-9]*$"",""""))"),"2024-04-15") -> 2024-04-15 | U65: 2024-04-15 | Y65: 2024-04-15
A66: CUST-5064 | B66: ✅ Unique | C66: LiaK owalski | D66: Lia Kowalski | E66: =IFERROR(__xludf.DUMMYFUNCTION("IF(LEN(D66:D701), COUNTA(SPLIT(D66:D701,"" "")), """")"),2.0) -> 2 | F66: =IF(D66=G66,"✅","❌") -> ✅ | G66: Lia Kowalski | H66: =LOWER(TRIM(I66)) -> lia.kowalski@company.co.uk | I66: LIA.KOWALSKI@COMPANY.CO.UK | J66: =IFERROR(__xludf.DUMMYFUNCTION("IF(REGEXMATCH(TRIM(I66),""^[A-Za-z0-9._%+-]+@[A-Za-z0-9.-]+\.[A-Za-z]{2,}$""),""✅ Valid"",""❌ Invalid"")"),"✅ Valid") -> ✅ Valid | K66: 48124487 | L66: =IFERROR(__xludf.DUMMYFUNCTION("IF(K66=""N/A"", """", REGEXREPLACE( SUBSTITUTE(SUBSTITUTE(SUBSTITUTE(TO_TEXT(K66), CHAR(160),""""), UNICHAR(8239),""""), UNICHAR(8201),""""),""[+\-/(): )]"", """"))"),"48124487") -> 48124487 | M66: =IFERROR(__xludf.DUMMYFUNCTION("IF(L66="""","""", REGEXEXTRACT(REGEXREPLACE(L66,""x"", """"), ""[0-9]+""))"),"48124487") -> 48124487 | N66: =IF(LEFT(M66,2)="48", RIGHT(M66,LEN(M66)-2),M66) -> 124487 | O66: =IFERROR(__xludf.DUMMYFUNCTION("REGEXMATCH(TO_TEXT(N66), ""^(5[013679]|6[069]|7[2-9]|88)"")"),FALSE) -> FALSE | Q66: =IF(AND(O66=TRUE, P66=9), "✅ VALID", "❌ INVALID") -> ❌ INVALID | R66: Poland | S66: 44948 00:22 | T66: =IFERROR(__xludf.DUMMYFUNCTION("IF(ISNUMBER(S66),TEXT(S66,""yyyy-MM-dd""),REGEXREPLACE(REGEXREPLACE(TO_TEXT(S66),""[^0-9a-zA-Z]+"",""-""),""[^0-9]*$"",""""))"),"44948-00-22") -> 44948-00-22 | U66: =TEXT(T66,"yyyy-MM-dd") -> 44948-00-22 | V66: =CONCATENATE(LEFT(U66,5)) -> 44948 | W66: =DATE(1900,1,1) + V66 - 1 -> 44949 | X66: 2023-01-23 | Y66: 2023-01-23
A67: CUST-5065 | B67: ✅ Unique | C67: Carlos Johnson | D67: =IFERROR(__xludf.DUMMYFUNCTION("PROPER(REGEXREPLACE(TRIM(C67),""\s+"","" ""))"),"Carlos Johnson") -> Carlos Johnson | E67: =IFERROR(__xludf.DUMMYFUNCTION("IF(LEN(D67:D701), COUNTA(SPLIT(D67:D701,"" "")), """")"),2.0) -> 2 | F67: =IF(D67=G67,"✅","❌") -> ❌ | G67: Calros Johnson | H67: =LOWER(TRIM(I67)) -> calros.johnson@outlook.com | I67: calros.johnson@outlook.com | J67: =IFERROR(__xludf.DUMMYFUNCTION("IF(REGEXMATCH(TRIM(I67),""^[A-Za-z0-9._%+-]+@[A-Za-z0-9.-]+\.[A-Za-z]{2,}$""),""✅ Valid"",""❌ Invalid"")"),"✅ Valid") -> ✅ Valid | K67: +48 6785 4897 | L67: =IFERROR(__xludf.DUMMYFUNCTION("IF(K67=""N/A"", """", REGEXREPLACE( SUBSTITUTE(SUBSTITUTE(SUBSTITUTE(TO_TEXT(K67), CHAR(160),""""), UNICHAR(8239),""""), UNICHAR(8201),""""),""[+\-/(): )]"", """"))"),"4867854897") -> 4867854897 | M67: =IFERROR(__xludf.DUMMYFUNCTION("IF(L67="""","""", REGEXEXTRACT(REGEXREPLACE(L67,""x"", """"), ""[0-9]+""))"),"4867854897") -> 4867854897 | N67: =IF(LEFT(M67,2)="48", RIGHT(M67,LEN(M67)-2),M67) -> 67854897 | O67: =IFERROR(__xludf.DUMMYFUNCTION("REGEXMATCH(TO_TEXT(N67), ""^(5[013679]|6[069]|7[2-9]|88)"")"),FALSE) -> FALSE | Q67: =IF(AND(O67=TRUE, P67=9), "✅ VALID", "❌ INVALID") -> ❌ INVALID | R67: Poland | S67: 45809.217 | T67: =IFERROR(__xludf.DUMMYFUNCTION("IF(ISNUMBER(S67),TEXT(S67,""yyyy-MM-dd""),REGEXREPLACE(REGEXREPLACE(TO_TEXT(S67),""[^0-9a-zA-Z]+"",""-""),""[^0-9]*$"",""""))"),"2025-06-01") -> 2025-06-01 | U67: 2025-06-01 | Y67: 2025-06-01
A68: CUST-5066 | B68: ✅ Unique | C68: Uma Kowalski | D68: =IFERROR(__xludf.DUMMYFUNCTION("PROPER(REGEXREPLACE(TRIM(C68),""\s+"","" ""))"),"Uma Kowalski") -> Uma Kowalski | E68: =IFERROR(__xludf.DUMMYFUNCTION("IF(LEN(D68:D701), COUNTA(SPLIT(D68:D701,"" "")), """")"),2.0) -> 2 | F68: =IF(D68=G68,"✅","❌") -> ✅ | G68: =IFERROR(__xludf.DUMMYFUNCTION("REGEXEXTRACT(PROPER(SUBSTITUTE(TRIM(I68),""."","" "")),""^[^@]+"")"),"Uma Kowalski") -> Uma Kowalski | H68: =LOWER(TRIM(I68)) -> uma.kowalski@gmail.com | I68: uma.kowalski@gmail.com | J68: =IFERROR(__xludf.DUMMYFUNCTION("IF(REGEXMATCH(TRIM(I68),""^[A-Za-z0-9._%+-]+@[A-Za-z0-9.-]+\.[A-Za-z]{2,}$""),""✅ Valid"",""❌ Invalid"")"),"✅ Valid") -> ✅ Valid | K68: +33914861762 | L68: =IFERROR(__xludf.DUMMYFUNCTION("IF(OR(K68=""N/A"", K68=""missing"", K68=""none""), """", REGEXREPLACE( SUBSTITUTE(SUBSTITUTE(SUBSTITUTE(TO_TEXT(K68), CHAR(160),""""), UNICHAR(8239),""""), UNICHAR(8201),""""),""[+\-/(): )]"", """"))"),"33914861762") -> 33914861762 | M68: =IFERROR(__xludf.DUMMYFUNCTION("IF(L68="""","""", REGEXEXTRACT(REGEXREPLACE(L68,""x"", """"), ""[0-9]+""))"),"33914861762") -> 33914861762 | N68: =IF(LEFT(M68,2)="33", RIGHT(M68,LEN(M68)-2),M68) -> 914861762 | O68: =IFERROR(__xludf.DUMMYFUNCTION("REGEXMATCH(TO_TEXT(N68), ""^0[67]"")"),FALSE) -> FALSE | P68: =LEN(N68) -> 9 | Q68: =IF(AND(O68=TRUE, P68=9), "✅ VALID", "❌ INVALID") -> ❌ INVALID | R68: France | S68: 45569.585 | T68: =IFERROR(__xludf.DUMMYFUNCTION("IF(ISNUMBER(S68),TEXT(S68,""yyyy-MM-dd""),REGEXREPLACE(REGEXREPLACE(TO_TEXT(S68),""[^0-9a-zA-Z]+"",""-""),""[^0-9]*$"",""""))"),"2024-10-04") -> 2024-10-04 | U68: 2024-10-04 | Y68: 2024-10-04
A69: CUST-5067 | B69: ✅ Unique | C69: Rita Rodriguez | D69: =IFERROR(__xludf.DUMMYFUNCTION("PROPER(REGEXREPLACE(TRIM(C69),""\s+"","" ""))"),"Rita Rodriguez") -> Rita Rodriguez | E69: =IFERROR(__xludf.DUMMYFUNCTION("IF(LEN(D69:D701), COUNTA(SPLIT(D69:D701,"" "")), """")"),2.0) -> 2 | F69: =IF(D69=G69,"✅","❌") -> ✅ | G69: =IFERROR(__xludf.DUMMYFUNCTION("REGEXEXTRACT(PROPER(SUBSTITUTE(TRIM(I69),""."","" "")),""^[^@]+"")"),"Rita Rodriguez") -> Rita Rodriguez | H69: =LOWER(TRIM(I69)) -> rita.rodriguez@company.co.uk | I69: rita.rodriguez@company.co.uk | J69: =IFERROR(__xludf.DUMMYFUNCTION("IF(REGEXMATCH(TRIM(I69),""^[A-Za-z0-9._%+-]+@[A-Za-z0-9.-]+\.[A-Za-z]{2,}$""),""✅ Valid"",""❌ Invalid"")"),"✅ Valid") -> ✅ Valid | K69: +48+195449215 | L69: =IFERROR(__xludf.DUMMYFUNCTION("IF(K69=""N/A"", """", REGEXREPLACE( SUBSTITUTE(SUBSTITUTE(SUBSTITUTE(TO_TEXT(K69), CHAR(160),""""), UNICHAR(8239),""""), UNICHAR(8201),""""),""[+\-/(): )]"", """"))"),"48195449215") -> 48195449215 | M69: =IFERROR(__xludf.DUMMYFUNCTION("IF(L69="""","""", REGEXEXTRACT(REGEXREPLACE(L69,""x"", """"), ""[0-9]+""))"),"48195449215") -> 48195449215 | N69: =IF(LEFT(M69,2)="48", RIGHT(M69,LEN(M69)-2),M69) -> 195449215 | O69: =IFERROR(__xludf.DUMMYFUNCTION("REGEXMATCH(TO_TEXT(N69), ""^(5[013679]|6[069]|7[2-9]|88)"")"),FALSE) -> FALSE | Q69: =IF(AND(O69=TRUE, P69=9), "✅ VALID", "❌ INVALID") -> ❌ INVALID | R69: Poland | S69: 44897 | T69: =IFERROR(__xludf.DUMMYFUNCTION("IF(ISNUMBER(S69),TEXT(S69,""yyyy-MM-dd""),REGEXREPLACE(REGEXREPLACE(TO_TEXT(S69),""[^0-9a-zA-Z]+"",""-""),""[^0-9]*$"",""""))"),"2022-12-02") -> 2022-12-02 | U69: 2022-12-02 | Y69: 2022-12-02
A70: CUST-5068 | B70: ✅ Unique | C70: Zack Lopez | D70: =IFERROR(__xludf.DUMMYFUNCTION("PROPER(REGEXREPLACE(TRIM(C70),""\s+"","" ""))"),"Zack Lopez") -> Zack Lopez | E70: =IFERROR(__xludf.DUMMYFUNCTION("IF(LEN(D70:D701), COUNTA(SPLIT(D70:D701,"" "")), """")"),2.0) -> 2 | F70: =IF(D70=G70,"✅","❌") -> ✅ | G70: =IFERROR(__xludf.DUMMYFUNCTION("REGEXEXTRACT(PROPER(SUBSTITUTE(TRIM(I70),""."","" "")),""^[^@]+"")"),"Zack Lopez") -> Zack Lopez | H70: =LOWER(TRIM(I70)) -> zack.lopez@company.co.uk | I70: zack.lopez@company.co.uk | J70: =IFERROR(__xludf.DUMMYFUNCTION("IF(REGEXMATCH(TRIM(I70),""^[A-Za-z0-9._%+-]+@[A-Za-z0-9.-]+\.[A-Za-z]{2,}$""),""✅ Valid"",""❌ Invalid"")"),"✅ Valid") -> ✅ Valid | K70: 23866267 | L70: =IFERROR(__xludf.DUMMYFUNCTION("IF(K70=""N/A"", """", REGEXREPLACE( SUBSTITUTE(SUBSTITUTE(SUBSTITUTE(TO_TEXT(K70), CHAR(160),""""), UNICHAR(8239),""""), UNICHAR(8201),""""),""[+\-/(): )]"", """"))"),"23866267") -> 23866267 | M70: =IFERROR(__xludf.DUMMYFUNCTION("IF(L70="""","""", REGEXEXTRACT(REGEXREPLACE(L70,""x"", """"), ""[0-9]+""))"),"23866267") -> 23866267 | N70: =IF(LEFT(M70,2)="48", RIGHT(M70,LEN(M70)-2),M70) -> 23866267 | O70: =IFERROR(__xludf.DUMMYFUNCTION("REGEXMATCH(TO_TEXT(N70), ""^(5[013679]|6[069]|7[2-9]|88)"")"),FALSE) -> FALSE | Q70: =IF(AND(O70=TRUE, P70=9), "✅ VALID", "❌ INVALID") -> ❌ INVALID | R70: Poland | S70: 45128 | T70: =IFERROR(__xludf.DUMMYFUNCTION("IF(ISNUMBER(S70),TEXT(S70,""yyyy-MM-dd""),REGEXREPLACE(REGEXREPLACE(TO_TEXT(S70),""[^0-9a-zA-Z]+"",""-""),""[^0-9]*$"",""""))"),"2023-07-21") -> 2023-07-21 | U70: 2023-07-21 | Y70: 2023-07-21
A71: CUST-5069 | B71: ✅ Unique | C71: Omar Lopez | D71: =IFERROR(__xludf.DUMMYFUNCTION("PROPER(REGEXREPLACE(TRIM(C71),""\s+"","" ""))"),"Omar Lopez") -> Omar Lopez | E71: =IFERROR(__xludf.DUMMYFUNCTION("IF(LEN(D71:D701), COUNTA(SPLIT(D71:D701,"" "")), """")"),2.0) -> 2 | F71: =IF(D71=G71,"✅","❌") -> ✅ | G71: =IFERROR(__xludf.DUMMYFUNCTION("REGEXEXTRACT(PROPER(SUBSTITUTE(TRIM(I71),""."","" "")),""^[^@]+"")"),"Omar Lopez") -> Omar Lopez | H71: =LOWER(TRIM(I71)) -> omar.lopez@yahoo.com | I71: omar.lopez@yahoo.com | J71: =IFERROR(__xludf.DUMMYFUNCTION("IF(REGEXMATCH(TRIM(I71),""^[A-Za-z0-9._%+-]+@[A-Za-z0-9.-]+\.[A-Za-z]{2,}$""),""✅ Valid"",""❌ Invalid"")"),"✅ Valid") -> ✅ Valid | K71: 686511739 | L71: =IFERROR(__xludf.DUMMYFUNCTION("IF(OR(K71=""N/A"", K71=""missing"", K71=""none""), """", REGEXREPLACE( SUBSTITUTE(SUBSTITUTE(SUBSTITUTE(TO_TEXT(K71), CHAR(160),""""), UNICHAR(8239),""""), UNICHAR(8201),""""),""[+\-/(): )]"", """"))"),"686511739") -> 686511739 | M71: =IFERROR(__xludf.DUMMYFUNCTION("IF(L71="""","""", REGEXEXTRACT(REGEXREPLACE(L71,""x"", """"), ""[0-9]+""))"),"686511739") -> 686511739 | N71: =IF(LEFT(M71,2)="33", RIGHT(M71,LEN(M71)-2),M71) -> 686511739 | O71: =IFERROR(__xludf.DUMMYFUNCTION("REGEXMATCH(TO_TEXT(N71), ""^0[67]"")"),FALSE) -> FALSE | P71: =LEN(N71) -> 9 | Q71: =IF(AND(O71=TRUE, P71=9), "✅ VALID", "❌ INVALID") -> ❌ INVALID | R71: France | S71: 44982 | T71: =IFERROR(__xludf.DUMMYFUNCTION("IF(ISNUMBER(S71),TEXT(S71,""yyyy-MM-dd""),REGEXREPLACE(REGEXREPLACE(TO_TEXT(S71),""[^0-9a-zA-Z]+"",""-""),""[^0-9]*$"",""""))"),"2023-02-25") -> 2023-02-25 | U71: 2023-02-25 | Y71: 2023-02-25
A72: CUST-5070 | B72: ✅ Unique | C72: Rita Williams | D72: =IFERROR(__xludf.DUMMYFUNCTION("PROPER(REGEXREPLACE(TRIM(C72),""\s+"","" ""))"),"Rita Williams") -> Rita Williams | E72: =IFERROR(__xludf.DUMMYFUNCTION("IF(LEN(D72:D701), COUNTA(SPLIT(D72:D701,"" "")), """")"),2.0) -> 2 | F72: =IF(D72=G72,"✅","❌") -> ✅ | G72: =IFERROR(__xludf.DUMMYFUNCTION("REGEXEXTRACT(PROPER(SUBSTITUTE(TRIM(I72),""."","" "")),""^[^@]+"")"),"Rita Williams") -> Rita Williams | H72: =LOWER(TRIM(I72)) -> rita.williams@yahoo.com | I72: rita.williams@yahoo.com | J72: =IFERROR(__xludf.DUMMYFUNCTION("IF(REGEXMATCH(TRIM(I72),""^[A-Za-z0-9._%+-]+@[A-Za-z0-9.-]+\.[A-Za-z]{2,}$""),""✅ Valid"",""❌ Invalid"")"),"✅ Valid") -> ✅ Valid | K72: 98062194381 | L72: =IFERROR(__xludf.DUMMYFUNCTION("IF(OR(K72=""N/A"", K72=""missing"", K72=""none""), """", REGEXREPLACE( SUBSTITUTE(SUBSTITUTE(SUBSTITUTE(TO_TEXT(K72), CHAR(160),""""), UNICHAR(8239),""""), UNICHAR(8201),""""),""[+\-/(): )]"", """"))"),"98062194381") -> 98062194381 | M72: =IFERROR(__xludf.DUMMYFUNCTION("IF(L72="""","""", REGEXEXTRACT(REGEXREPLACE(L72,""x"", """"), ""[0-9]+""))"),"98062194381") -> 98062194381 | N72: =IF(LEFT(M72,2)="49", RIGHT(M72,LEN(M72)-2),M72) -> 98062194381 | O72: =IFERROR(__xludf.DUMMYFUNCTION("REGEXMATCH(TO_TEXT(N72), ""^0(15|16|17)"")"),FALSE) -> FALSE | P72: =LEN(N72) -> 11 | Q72: =IF(AND(O72=TRUE,OR(P72=10, P72=11)), "✅ VALID", "❌ INVALID") -> ❌ INVALID | R72: Germany | S72: 45718 | T72: =IFERROR(__xludf.DUMMYFUNCTION("IF(ISNUMBER(S72),TEXT(S72,""yyyy-MM-dd""),REGEXREPLACE(REGEXREPLACE(TO_TEXT(S72),""[^0-9a-zA-Z]+"",""-""),""[^0-9]*$"",""""))"),"2025-03-02") -> 2025-03-02 | U72: 2025-03-02 | Y72: 2025-03-02
A73: CUST-5071 | B73: ✅ Unique | C73: ZACK KOWALCZYK | D73: =IFERROR(__xludf.DUMMYFUNCTION("PROPER(REGEXREPLACE(TRIM(C73),""\s+"","" ""))"),"Zack Kowalczyk") -> Zack Kowalczyk | E73: =IFERROR(__xludf.DUMMYFUNCTION("IF(LEN(D73:D701), COUNTA(SPLIT(D73:D701,"" "")), """")"),2.0) -> 2 | F73: =IF(D73=G73,"✅","❌") -> ✅ | G73: =IFERROR(__xludf.DUMMYFUNCTION("REGEXEXTRACT(PROPER(SUBSTITUTE(TRIM(I73),""."","" "")),""^[^@]+"")"),"Zack Kowalczyk") -> Zack Kowalczyk | H73: =LOWER(TRIM(I73)) -> zack.kowalczyk@company.co.uk | I73: zack.kowalczyk@company.co.uk | J73: =IFERROR(__xludf.DUMMYFUNCTION("IF(REGEXMATCH(TRIM(I73),""^[A-Za-z0-9._%+-]+@[A-Za-z0-9.-]+\.[A-Za-z]{2,}$""),""✅ Valid"",""❌ Invalid"")"),"✅ Valid") -> ✅ Valid | K73: 4831399994 | L73: =IFERROR(__xludf.DUMMYFUNCTION("IF(K73=""N/A"", """", REGEXREPLACE( SUBSTITUTE(SUBSTITUTE(SUBSTITUTE(TO_TEXT(K73), CHAR(160),""""), UNICHAR(8239),""""), UNICHAR(8201),""""),""[+\-/(): )]"", """"))"),"4831399994") -> 4831399994 | M73: =IFERROR(__xludf.DUMMYFUNCTION("IF(L73="""","""", REGEXEXTRACT(REGEXREPLACE(L73,""x"", """"), ""[0-9]+""))"),"4831399994") -> 4831399994 | N73: =IF(LEFT(M73,2)="48", RIGHT(M73,LEN(M73)-2),M73) -> 31399994 | O73: =IFERROR(__xludf.DUMMYFUNCTION("REGEXMATCH(TO_TEXT(N73), ""^(5[013679]|6[069]|7[2-9]|88)"")"),FALSE) -> FALSE | Q73: =IF(AND(O73=TRUE, P73=9), "✅ VALID", "❌ INVALID") -> ❌ INVALID | R73: Poland | S73: 02/25/2025 | T73: =IFERROR(__xludf.DUMMYFUNCTION("IF(ISNUMBER(S73),TEXT(S73,""yyyy-MM-dd""),REGEXREPLACE(REGEXREPLACE(TO_TEXT(S73),""[^0-9a-zA-Z]+"",""-""),""[^0-9]*$"",""""))"),"02-25-2025") -> 02-25-2025 | U73: =TEXT(T73,"yyyy-MM-dd") -> 02-25-2025 | V73: 2025-02-25 | Y73: 2025-02-25
A74: CUST-5072 | B74: ✅ Unique | C74: CARLOS MULLER | D74: =IFERROR(__xludf.DUMMYFUNCTION("PROPER(REGEXREPLACE(TRIM(C74),""\s+"","" ""))"),"Carlos Muller") -> Carlos Muller | E74: =IFERROR(__xludf.DUMMYFUNCTION("IF(LEN(D74:D701), COUNTA(SPLIT(D74:D701,"" "")), """")"),2.0) -> 2 | K74: +1-796-665-6440 | R74: Italy | S74: 2024/04/23 09:42
A75: CUST-5073 | B75: ✅ Unique | C75: Wiktor Young | D75: =IFERROR(__xludf.DUMMYFUNCTION("PROPER(REGEXREPLACE(TRIM(C75),""\s+"","" ""))"),"Wiktor Young") -> Wiktor Young | E75: =IFERROR(__xludf.DUMMYFUNCTION("IF(LEN(D75:D701), COUNTA(SPLIT(D75:D701,"" "")), """")"),2.0) -> 2 | F75: =IF(D75=G75,"✅","❌") -> ❌ | G75: Witkor Young | H75: =LOWER(TRIM(I75)) -> witkor.young@yahoo.com | I75: witkor.young@yahoo.com | J75: =IFERROR(__xludf.DUMMYFUNCTION("IF(REGEXMATCH(TRIM(I75),""^[A-Za-z0-9._%+-]+@[A-Za-z0-9.-]+\.[A-Za-z]{2,}$""),""✅ Valid"",""❌ Invalid"")"),"✅ Valid") -> ✅ Valid | K75: 3346058891 | L75: =IFERROR(__xludf.DUMMYFUNCTION("IF(OR(K75=""N/A"", K75=""missing"", K75=""none""), """", REGEXREPLACE( SUBSTITUTE(SUBSTITUTE(SUBSTITUTE(TO_TEXT(K75), CHAR(160),""""), UNICHAR(8239),""""), UNICHAR(8201),""""),""[+\-/(): )]"", """"))"),"3346058891") -> 3346058891 | M75: =IFERROR(__xludf.DUMMYFUNCTION("IF(L75="""","""", REGEXEXTRACT(REGEXREPLACE(L75,""x"", """"), ""[0-9]+""))"),"3346058891") -> 3346058891 | N75: =IF(LEFT(M75,2)="33", RIGHT(M75,LEN(M75)-2),M75) -> 46058891 | O75: =IFERROR(__xludf.DUMMYFUNCTION("REGEXMATCH(TO_TEXT(N75), ""^0[67]"")"),FALSE) -> FALSE | P75: =LEN(N75) -> 8 | Q75: =IF(AND(O75=TRUE, P75=9), "✅ VALID", "❌ INVALID") -> ❌ INVALID | R75: France | S75: 44919 | T75: =IFERROR(__xludf.DUMMYFUNCTION("IF(ISNUMBER(S75),TEXT(S75,""yyyy-MM-dd""),REGEXREPLACE(REGEXREPLACE(TO_TEXT(S75),""[^0-9a-zA-Z]+"",""-""),""[^0-9]*$"",""""))"),"2022-12-24") -> 2022-12-24 | U75: 2022-12-24 | Y75: 2022-12-24
A76: CUST-5074 | B76: ✅ Unique | C76: Bella Kowalski | D76: =IFERROR(__xludf.DUMMYFUNCTION("PROPER(REGEXREPLACE(TRIM(C76),""\s+"","" ""))"),"Bella Kowalski") -> Bella Kowalski | E76: =IFERROR(__xludf.DUMMYFUNCTION("IF(LEN(D76:D701), COUNTA(SPLIT(D76:D701,"" "")), """")"),2.0) -> 2 | F76: =IF(D76=G76,"✅","❌") -> ✅ | G76: =IFERROR(__xludf.DUMMYFUNCTION("REGEXEXTRACT(PROPER(SUBSTITUTE(TRIM(I76),""."","" "")),""^[^@]+"")"),"Bella Kowalski") -> Bella Kowalski | H76: =LOWER(TRIM(I76)) -> bella.kowalski@outlook.com | I76: bella.kowalski@outlook.com | J76: =IFERROR(__xludf.DUMMYFUNCTION("IF(REGEXMATCH(TRIM(I76),""^[A-Za-z0-9._%+-]+@[A-Za-z0-9.-]+\.[A-Za-z]{2,}$""),""✅ Valid"",""❌ Invalid"")"),"✅ Valid") -> ✅ Valid | K76: 341x2756733 | L76: =IFERROR(__xludf.DUMMYFUNCTION("IF(OR(K76=""N/A"", K76=""missing"", K76=""none""), """", REGEXREPLACE( SUBSTITUTE(SUBSTITUTE(SUBSTITUTE(TO_TEXT(K76), CHAR(160),""""), UNICHAR(8239),""""), UNICHAR(8201),""""),""[+\-/(): )]"", """"))"),"341x2756733") -> 341x2756733 | M76: =IFERROR(__xludf.DUMMYFUNCTION("IF(L76="""","""", REGEXEXTRACT(REGEXREPLACE(L76,""x"", """"), ""[0-9]+""))"),"3412756733") -> 3412756733 | N76: =IF(LEFT(M76,1)="1", RIGHT(M76,LEN(M76)-1),M76) -> 3412756733 | O76: =IFERROR(__xludf.DUMMYFUNCTION("REGEXMATCH(TO_TEXT(N76), ""^[2-9][0-9]{9}$"")"),TRUE) -> TRUE | P76: =LEN(N76) -> 10 | Q76: =IF(AND(O76=TRUE, P76=10), "✅ VALID", "❌ INVALID") -> ✅ VALID | R76: USA | S76: 45800.332 | T76: =IFERROR(__xludf.DUMMYFUNCTION("IF(ISNUMBER(S76),TEXT(S76,""yyyy-MM-dd""),REGEXREPLACE(REGEXREPLACE(TO_TEXT(S76),""[^0-9a-zA-Z]+"",""-""),""[^0-9]*$"",""""))"),"2025-05-23") -> 2025-05-23 | U76: 2025-05-23 | Y76: 2025-05-23
A77: CUST-5075 | B77: ✅ Unique | C77: Daria Rossi | D77: =IFERROR(__xludf.DUMMYFUNCTION("PROPER(REGEXREPLACE(TRIM(C77),""\s+"","" ""))"),"Daria Rossi") -> Daria Rossi | E77: =IFERROR(__xludf.DUMMYFUNCTION("IF(LEN(D77:D701), COUNTA(SPLIT(D77:D701,"" "")), """")"),2.0) -> 2 | F77: =IF(D77=G77,"✅","❌") -> ✅ | G77: =IFERROR(__xludf.DUMMYFUNCTION("REGEXEXTRACT(PROPER(SUBSTITUTE(TRIM(I77),""."","" "")),""^[^@]+"")"),"Daria Rossi") -> Daria Rossi | H77: =LOWER(TRIM(I77)) -> daria.rossi@outlook.com | I77: DARIA.ROSSI@OUTLOOK.COM | J77: =IFERROR(__xludf.DUMMYFUNCTION("IF(REGEXMATCH(TRIM(I77),""^[A-Za-z0-9._%+-]+@[A-Za-z0-9.-]+\.[A-Za-z]{2,}$""),""✅ Valid"",""❌ Invalid"")"),"✅ Valid") -> ✅ Valid | K77: 552-643-64 | L77: =IFERROR(__xludf.DUMMYFUNCTION("IF(OR(K77=""N/A"", K77=""missing"", K77=""none""), """", REGEXREPLACE( SUBSTITUTE(SUBSTITUTE(SUBSTITUTE(TO_TEXT(K77), CHAR(160),""""), UNICHAR(8239),""""), UNICHAR(8201),""""),""[+\-/(): )]"", """"))"),"55264364") -> 55264364 | M77: =IFERROR(__xludf.DUMMYFUNCTION("IF(L77="""","""", REGEXEXTRACT(REGEXREPLACE(L77,""x"", """"), ""[0-9]+""))"),"55264364") -> 55264364 | N77: =IF(LEFT(M77,3)="353", RIGHT(M77,LEN(M77)-3),M77) -> 55264364 | O77: =IFERROR(__xludf.DUMMYFUNCTION("REGEXMATCH(TO_TEXT(N77), ""^0(83|85|86|87|89)"")"),FALSE) -> FALSE | P77: =LEN(N77) -> 8 | Q77: =IF(AND(O77=TRUE, P74=10), "✅ VALID", "❌ INVALID") -> ❌ INVALID | R77: Ireland | S77: 44658 | T77: =IFERROR(__xludf.DUMMYFUNCTION("IF(ISNUMBER(S77),TEXT(S77,""yyyy-MM-dd""),REGEXREPLACE(REGEXREPLACE(TO_TEXT(S77),""[^0-9a-zA-Z]+"",""-""),""[^0-9]*$"",""""))"),"2022-04-07") -> 2022-04-07 | U77: 2022-04-07 | Y77: 2022-04-07
A78: CUST-5076 | B78: ✅ Unique | C78: ETHAN GARCIA | D78: =IFERROR(__xludf.DUMMYFUNCTION("PROPER(REGEXREPLACE(TRIM(C78),""\s+"","" ""))"),"Ethan Garcia") -> Ethan Garcia | E78: =IFERROR(__xludf.DUMMYFUNCTION("IF(LEN(D78:D701), COUNTA(SPLIT(D78:D701,"" "")), """")"),2.0) -> 2 | F78: =IF(D78=G78,"✅","❌") -> ✅ | G78: =IFERROR(__xludf.DUMMYFUNCTION("REGEXEXTRACT(PROPER(SUBSTITUTE(TRIM(I78),""."","" "")),""^[^@]+"")"),"Ethan Garcia") -> Ethan Garcia | H78: =LOWER(TRIM(I78)) -> ethan.garcia@company.co.uk | I78: ethan.garcia@company.co.uk | J78: =IFERROR(__xludf.DUMMYFUNCTION("IF(REGEXMATCH(TRIM(I78),""^[A-Za-z0-9._%+-]+@[A-Za-z0-9.-]+\.[A-Za-z]{2,}$""),""✅ Valid"",""❌ Invalid"")"),"✅ Valid") -> ✅ Valid | K78: +33 647 944 770 | L78: =IFERROR(__xludf.DUMMYFUNCTION("IF(OR(K78=""N/A"", K78=""missing"", K78=""none""), """", REGEXREPLACE( SUBSTITUTE(SUBSTITUTE(SUBSTITUTE(TO_TEXT(K78), CHAR(160),""""), UNICHAR(8239),""""), UNICHAR(8201),""""),""[+\-/(): )]"", """"))"),"33647944770") -> 33647944770 | M78: =IFERROR(__xludf.DUMMYFUNCTION("IF(L78="""","""", REGEXEXTRACT(REGEXREPLACE(L78,""x"", """"), ""[0-9]+""))"),"33647944770") -> 33647944770 | N78: =IF(LEFT(M78,2)="33", RIGHT(M78,LEN(M78)-2),M78) -> 647944770 | O78: =IFERROR(__xludf.DUMMYFUNCTION("REGEXMATCH(TO_TEXT(N78), ""^0[67]"")"),FALSE) -> FALSE | P78: =LEN(N78) -> 9 | Q78: =IF(AND(O78=TRUE, P78=9), "✅ VALID", "❌ INVALID") -> ❌ INVALID | R78: France | S78: 45668 | T78: =IFERROR(__xludf.DUMMYFUNCTION("IF(ISNUMBER(S78),TEXT(S78,""yyyy-MM-dd""),REGEXREPLACE(REGEXREPLACE(TO_TEXT(S78),""[^0-9a-zA-Z]+"",""-""),""[^0-9]*$"",""""))"),"2025-01-11") -> 2025-01-11 | U78: 2025-01-11 | Y78: 2025-01-11
A79: CUST-5077 | B79: ✅ Unique | C79: Carlos Davis | D79: =IFERROR(__xludf.DUMMYFUNCTION("PROPER(REGEXREPLACE(TRIM(C79),""\s+"","" ""))"),"Carlos Davis") -> Carlos Davis | E79: =IFERROR(__xludf.DUMMYFUNCTION("IF(LEN(D79:D701), COUNTA(SPLIT(D79:D701,"" "")), """")"),2.0) -> 2 | F79: =IF(D79=G79,"✅","❌") -> ✅ | G79: =IFERROR(__xludf.DUMMYFUNCTION("REGEXEXTRACT(PROPER(SUBSTITUTE(TRIM(I79),""."","" "")),""^[^@]+"")"),"Carlos Davis") -> Carlos Davis | H79: =LOWER(TRIM(I79)) -> carlos.davis@yahoo.com | I79: CARLOS.DAVIS@YAHOO.COM | J79: =IFERROR(__xludf.DUMMYFUNCTION("IF(REGEXMATCH(TRIM(I79),""^[A-Za-z0-9._%+-]+@[A-Za-z0-9.-]+\.[A-Za-z]{2,}$""),""✅ Valid"",""❌ Invalid"")"),"✅ Valid") -> ✅ Valid | K79: missing | L79: =IFERROR(__xludf.DUMMYFUNCTION("IF(OR(K79=""N/A"", K79=""missing"", K79=""none""), """", REGEXREPLACE( SUBSTITUTE(SUBSTITUTE(SUBSTITUTE(TO_TEXT(K79), CHAR(160),""""), UNICHAR(8239),""""), UNICHAR(8201),""""),""[+\-/(): )]"", """"))"),"") | M79: =IFERROR(__xludf.DUMMYFUNCTION("IF(L79="""","""", REGEXEXTRACT(REGEXREPLACE(L79,""x"", """"), ""[0-9]+""))"),"") | N79: =IF(LEFT(M79,2)="44", RIGHT(M79,LEN(M79)-2),M79) | O79: =IFERROR(__xludf.DUMMYFUNCTION("REGEXMATCH(TO_TEXT(N79), ""^07[1-57-9]"")"),FALSE) -> FALSE | P79: =LEN(N79) -> 0 | Q79: =IF(AND(O79=TRUE, P79=11), "✅ VALID", "❌ INVALID") -> ❌ INVALID | R79: UK | S79: 03.04.2025 | T79: =IFERROR(__xludf.DUMMYFUNCTION("IF(ISNUMBER(S79),TEXT(S79,""yyyy-MM-dd""),REGEXREPLACE(REGEXREPLACE(TO_TEXT(S79),""[^0-9a-zA-Z]+"",""-""),""[^0-9]*$"",""""))"),"03-04-2025") -> 03-04-2025 | U79: 2025-04-03 | Y79: 2025-04-03
A80: CUST-5078 | B80: ✅ Unique | C80: Tara Khan | D80: =IFERROR(__xludf.DUMMYFUNCTION("PROPER(REGEXREPLACE(TRIM(C80),""\s+"","" ""))"),"Tara Khan") -> Tara Khan | E80: =IFERROR(__xludf.DUMMYFUNCTION("IF(LEN(D80:D701), COUNTA(SPLIT(D80:D701,"" "")), """")"),2.0) -> 2 | F80: =IF(D80=G80,"✅","❌") -> ✅ | G80: =IFERROR(__xludf.DUMMYFUNCTION("REGEXEXTRACT(PROPER(SUBSTITUTE(TRIM(I80),""."","" "")),""^[^@]+"")"),"Tara Khan") -> Tara Khan | H80: =LOWER(TRIM(I80)) -> tara.khan@company.co.uk | I80: tara.khan@company.co.uk | J80: =IFERROR(__xludf.DUMMYFUNCTION("IF(REGEXMATCH(TRIM(I80),""^[A-Za-z0-9._%+-]+@[A-Za-z0-9.-]+\.[A-Za-z]{2,}$""),""✅ Valid"",""❌ Invalid"")"),"✅ Valid") -> ✅ Valid | K80: +3538375201287 | L80: =IFERROR(__xludf.DUMMYFUNCTION("IF(OR(K80=""N/A"", K80=""missing"", K80=""none""), """", REGEXREPLACE( SUBSTITUTE(SUBSTITUTE(SUBSTITUTE(TO_TEXT(K80), CHAR(160),""""), UNICHAR(8239),""""), UNICHAR(8201),""""),""[+\-/(): )]"", """"))"),"3538375201287") -> 3538375201287 | M80: =IFERROR(__xludf.DUMMYFUNCTION("IF(L80="""","""", REGEXEXTRACT(REGEXREPLACE(L80,""x"", """"), ""[0-9]+""))"),"3538375201287") -> 3538375201287 | N80: =IF(LEFT(M80,3)="353", RIGHT(M80,LEN(M80)-3),M80) -> 8375201287 | O80: =IFERROR(__xludf.DUMMYFUNCTION("REGEXMATCH(TO_TEXT(N80), ""^0(83|85|86|87|89)"")"),FALSE) -> FALSE | P80: =LEN(N80) -> 10 | Q80: =IF(AND(O80=TRUE, P77=10), "✅ VALID", "❌ INVALID") -> ❌ INVALID | R80: Ireland | S80: 06/19/2023 | T80: =IFERROR(__xludf.DUMMYFUNCTION("IF(ISNUMBER(S80),TEXT(S80,""yyyy-MM-dd""),REGEXREPLACE(REGEXREPLACE(TO_TEXT(S80),""[^0-9a-zA-Z]+"",""-""),""[^0-9]*$"",""""))"),"06-19-2023") -> 06-19-2023 | U80: =TEXT(T80,"yyyy-MM-dd") -> 06-19-2023 | V80: 2023-06-19 | Y80: 2023-06-19
A81: CUST-5079 | B81: ✅ Unique | C81: Adam Kowalczyk | D81: =IFERROR(__xludf.DUMMYFUNCTION("PROPER(REGEXREPLACE(TRIM(C81),""\s+"","" ""))"),"Adam Kowalczyk") -> Adam Kowalczyk | E81: =IFERROR(__xludf.DUMMYFUNCTION("IF(LEN(D81:D701), COUNTA(SPLIT(D81:D701,"" "")), """")"),2.0) -> 2 | F81: =IF(D81=G81,"✅","❌") -> ✅ | G81: =IFERROR(__xludf.DUMMYFUNCTION("REGEXEXTRACT(PROPER(SUBSTITUTE(TRIM(I81),""."","" "")),""^[^@]+"")"),"Adam Kowalczyk") -> Adam Kowalczyk | H81: =LOWER(TRIM(I81)) -> adam.kowalczyk@example.com | I81: adam.kowalczyk@example.com | J81: =IFERROR(__xludf.DUMMYFUNCTION("IF(REGEXMATCH(TRIM(I81),""^[A-Za-z0-9._%+-]+@[A-Za-z0-9.-]+\.[A-Za-z]{2,}$""),""✅ Valid"",""❌ Invalid"")"),"✅ Valid") -> ✅ Valid | K81: (350) 382681- | L81: =IFERROR(__xludf.DUMMYFUNCTION("IF(OR(K81=""N/A"", K81=""missing"", K81=""none""), """", REGEXREPLACE( SUBSTITUTE(SUBSTITUTE(SUBSTITUTE(TO_TEXT(K81), CHAR(160),""""), UNICHAR(8239),""""), UNICHAR(8201),""""),""[+\-/(): )]"", """"))"),"350382681") -> 350382681 | M81: =IFERROR(__xludf.DUMMYFUNCTION("IF(L81="""","""", REGEXEXTRACT(REGEXREPLACE(L81,""x"", """"), ""[0-9]+""))"),"350382681") -> 350382681 | N81: =IF(LEFT(M81,2)="39", RIGHT(M81,LEN(M81)-2),M81) -> 350382681 | O81: =IFERROR(__xludf.DUMMYFUNCTION("REGEXMATCH(TO_TEXT(N81), ""^3"")"),TRUE) -> TRUE | P81: =LEN(N81) -> 9 | Q81: =IF(AND(O81=TRUE,OR(P81=9, P81=10 )), "✅ VALID", "❌ INVALID") -> ✅ VALID | R81: Italy | S81: 03/16/2022 | T81: =IFERROR(__xludf.DUMMYFUNCTION("IF(ISNUMBER(S81),TEXT(S81,""yyyy-MM-dd""),REGEXREPLACE(REGEXREPLACE(TO_TEXT(S81),""[^0-9a-zA-Z]+"",""-""),""[^0-9]*$"",""""))"),"03-16-2022") -> 03-16-2022 | U81: =TEXT(T81,"yyyy-MM-dd") -> 03-16-2022 | V81: 2022-03-16 | Y81: 2022-03-16
A82: CUST-5080 | B82: ✅ Unique | C82: Hanna Johnson | D82: =IFERROR(__xludf.DUMMYFUNCTION("PROPER(REGEXREPLACE(TRIM(C82),""\s+"","" ""))"),"Hanna Johnson") -> Hanna Johnson | E82: =IFERROR(__xludf.DUMMYFUNCTION("IF(LEN(D82:D701), COUNTA(SPLIT(D82:D701,"" "")), """")"),2.0) -> 2 | F82: =IF(D82=G82,"✅","❌") -> ✅ | G82: =IFERROR(__xludf.DUMMYFUNCTION("REGEXEXTRACT(PROPER(SUBSTITUTE(TRIM(I82),""."","" "")),""^[^@]+"")"),"Hanna Johnson") -> Hanna Johnson | H82: =LOWER(TRIM(I82)) -> hanna.johnson@shop.io | I82: hanna.johnson@shop.io | J82: =IFERROR(__xludf.DUMMYFUNCTION("IF(REGEXMATCH(TRIM(I82),""^[A-Za-z0-9._%+-]+@[A-Za-z0-9.-]+\.[A-Za-z]{2,}$""),""✅ Valid"",""❌ Invalid"")"),"✅ Valid") -> ✅ Valid | K82: +4859490742 | L82: =IFERROR(__xludf.DUMMYFUNCTION("IF(K82=""N/A"", """", REGEXREPLACE( SUBSTITUTE(SUBSTITUTE(SUBSTITUTE(TO_TEXT(K82), CHAR(160),""""), UNICHAR(8239),""""), UNICHAR(8201),""""),""[+\-/(): )]"", """"))"),"4859490742") -> 4859490742 | M82: =IFERROR(__xludf.DUMMYFUNCTION("IF(L82="""","""", REGEXEXTRACT(REGEXREPLACE(L82,""x"", """"), ""[0-9]+""))"),"4859490742") -> 4859490742 | N82: =IF(LEFT(M82,2)="48", RIGHT(M82,LEN(M82)-2),M82) -> 59490742 | O82: =IFERROR(__xludf.DUMMYFUNCTION("REGEXMATCH(TO_TEXT(N82), ""^(5[013679]|6[069]|7[2-9]|88)"")"),TRUE) -> TRUE | P82: =LEN(N82) -> 8 | Q82: =IF(AND(O82=TRUE, P82=9), "✅ VALID", "❌ INVALID") -> ❌ INVALID | R82: Poland | S82: 45208 | T82: =IFERROR(__xludf.DUMMYFUNCTION("IF(ISNUMBER(S82),TEXT(S82,""yyyy-MM-dd""),REGEXREPLACE(REGEXREPLACE(TO_TEXT(S82),""[^0-9a-zA-Z]+"",""-""),""[^0-9]*$"",""""))"),"2023-10-09") -> 2023-10-09 | U82: 2023-10-09 | Y82: 2023-10-09
A83: CUST-5081 | B83: ✅ Unique | C83: Carlos Garcia | D83: =IFERROR(__xludf.DUMMYFUNCTION("PROPER(REGEXREPLACE(TRIM(C83),""\s+"","" ""))"),"Carlos Garcia") -> Carlos Garcia | E83: =IFERROR(__xludf.DUMMYFUNCTION("IF(LEN(D83:D701), COUNTA(SPLIT(D83:D701,"" "")), """")"),2.0) -> 2 | F83: =IF(D83=G83,"✅","❌") -> ✅ | G83: =IFERROR(__xludf.DUMMYFUNCTION("REGEXEXTRACT(PROPER(SUBSTITUTE(TRIM(I83),""."","" "")),""^[^@]+"")"),"Carlos Garcia") -> Carlos Garcia | H83: =LOWER(TRIM(I83)) -> carlos.garcia@shop.io | I83: Carlos.Garcia@Shop.Io | J83: =IFERROR(__xludf.DUMMYFUNCTION("IF(REGEXMATCH(TRIM(I83),""^[A-Za-z0-9._%+-]+@[A-Za-z0-9.-]+\.[A-Za-z]{2,}$""),""✅ Valid"",""❌ Invalid"")"),"✅ Valid") -> ✅ Valid | K83: +1-985-55230927 | L83: =IFERROR(__xludf.DUMMYFUNCTION("IF(OR(K83=""N/A"", K83=""missing"", K83=""none""), """", REGEXREPLACE( SUBSTITUTE(SUBSTITUTE(SUBSTITUTE(TO_TEXT(K83), CHAR(160),""""), UNICHAR(8239),""""), UNICHAR(8201),""""),""[+\-/(): )]"", """"))"),"198555230927") -> 198555230927 | M83: =IFERROR(__xludf.DUMMYFUNCTION("IF(L83="""","""", REGEXEXTRACT(REGEXREPLACE(L83,""x"", """"), ""[0-9]+""))"),"198555230927") -> 198555230927 | N83: =IF(LEFT(M83,1)="1", RIGHT(M83,LEN(M83)-1),M83) -> 98555230927 | O83: =IFERROR(__xludf.DUMMYFUNCTION("REGEXMATCH(TO_TEXT(N83), ""^[2-9][0-9]{9}$"")"),FALSE) -> FALSE | P83: =LEN(N83) -> 11 | Q83: =IF(AND(O83=TRUE, P83=10), "✅ VALID", "❌ INVALID") -> ❌ INVALID | R83: USA | S83: 45915 11:21 | T83: =IFERROR(__xludf.DUMMYFUNCTION("IF(ISNUMBER(S83),TEXT(S83,""yyyy-MM-dd""),REGEXREPLACE(REGEXREPLACE(TO_TEXT(S83),""[^0-9a-zA-Z]+"",""-""),""[^0-9]*$"",""""))"),"45915-11-21") -> 45915-11-21 | U83: =TEXT(T83,"yyyy-MM-dd") -> 45915-11-21 | V83: =CONCATENATE(LEFT(U83,5)) -> 45915 | W83: =DATE(1900,1,1) + V83 - 1 -> 45916 | X83: 2025-09-16 | Y83: 2025-09-16
A84: CUST-5082 | B84: ✅ Unique | C84: Adam Lee | D84: =IFERROR(__xludf.DUMMYFUNCTION("PROPER(REGEXREPLACE(TRIM(C84),""\s+"","" ""))"),"Adam Lee") -> Adam Lee | E84: =IFERROR(__xludf.DUMMYFUNCTION("IF(LEN(D84:D701), COUNTA(SPLIT(D84:D701,"" "")), """")"),2.0) -> 2 | F84: =IF(D84=G84,"✅","❌") -> ✅ | G84: =IFERROR(__xludf.DUMMYFUNCTION("REGEXEXTRACT(PROPER(SUBSTITUTE(TRIM(I84),""."","" "")),""^[^@]+"")"),"Adam Lee") -> Adam Lee | H84: =LOWER(TRIM(I84)) -> adam.lee@shop.io | I84: Adam.Lee@Shop.Io | J84: =IFERROR(__xludf.DUMMYFUNCTION("IF(REGEXMATCH(TRIM(I84),""^[A-Za-z0-9._%+-]+@[A-Za-z0-9.-]+\.[A-Za-z]{2,}$""),""✅ Valid"",""❌ Invalid"")"),"✅ Valid") -> ✅ Valid | K84: tel:+3301936724 | L84: =IFERROR(__xludf.DUMMYFUNCTION("IF(OR(K84=""N/A"", K84=""missing"", K84=""none""), """", REGEXREPLACE( SUBSTITUTE(SUBSTITUTE(SUBSTITUTE(TO_TEXT(K84), CHAR(160),""""), UNICHAR(8239),""""), UNICHAR(8201),""""),""[+\-/(): )]"", """"))"),"tel3301936724") -> tel3301936724 | M84: =IFERROR(__xludf.DUMMYFUNCTION("IF(L84="""","""", REGEXEXTRACT(REGEXREPLACE(L84,""x"", """"), ""[0-9]+""))"),"3301936724") -> 3301936724 | N84: =IF(LEFT(M84,2)="33", RIGHT(M84,LEN(M84)-2),M84) -> 01936724 | O84: =IFERROR(__xludf.DUMMYFUNCTION("REGEXMATCH(TO_TEXT(N84), ""^0[67]"")"),FALSE) -> FALSE | P84: =LEN(N84) -> 8 | Q84: =IF(AND(O84=TRUE, P84=9), "✅ VALID", "❌ INVALID") -> ❌ INVALID | R84: France | S84: 14.09.2022 23:38 | T84: =IFERROR(__xludf.DUMMYFUNCTION("IF(ISNUMBER(S84),TEXT(S84,""yyyy-MM-dd""),REGEXREPLACE(REGEXREPLACE(TO_TEXT(S84),""[^0-9a-zA-Z]+"",""-""),""[^0-9]*$"",""""))"),"14-09-2022-23-38") -> 14-09-2022-23-38 | U84: =TEXT(T84,"yyyy-MM-dd") -> 14-09-2022-23-38 | V84: =IFERROR(__xludf.DUMMYFUNCTION("REGEXEXTRACT(U84,""^\d{2}-\d{2}-\d{4}"")"),"14-09-2022") -> 14-09-2022 | W84: 2022-09-14 | Y84: 2022-09-14
A85: CUST-5083 | B85: ✅ Unique | C85: Qi Smith | D85: =IFERROR(__xludf.DUMMYFUNCTION("PROPER(REGEXREPLACE(TRIM(C85),""\s+"","" ""))"),"Qi Smith") -> Qi Smith | E85: =IFERROR(__xludf.DUMMYFUNCTION("IF(LEN(D85:D701), COUNTA(SPLIT(D85:D701,"" "")), """")"),2.0) -> 2 | F85: =IF(D85=G85,"✅","❌") -> ✅ | G85: =IFERROR(__xludf.DUMMYFUNCTION("REGEXEXTRACT(PROPER(SUBSTITUTE(TRIM(I85),""."","" "")),""^[^@]+"")"),"Qi Smith") -> Qi Smith | H85: =LOWER(TRIM(I85)) -> qi.smith@gmail.com | I85: qi.smith@gmail.com | J85: =IFERROR(__xludf.DUMMYFUNCTION("IF(REGEXMATCH(TRIM(I85),""^[A-Za-z0-9._%+-]+@[A-Za-z0-9.-]+\.[A-Za-z]{2,}$""),""✅ Valid"",""❌ Invalid"")"),"✅ Valid") -> ✅ Valid | K85: (160) 970247 | L85: =IFERROR(__xludf.DUMMYFUNCTION("IF(OR(K85=""N/A"", K85=""missing"", K85=""none""), """", REGEXREPLACE( SUBSTITUTE(SUBSTITUTE(SUBSTITUTE(TO_TEXT(K85), CHAR(160),""""), UNICHAR(8239),""""), UNICHAR(8201),""""),""[+\-/(): )]"", """"))"),"160970247") -> 160970247 | M85: =IFERROR(__xludf.DUMMYFUNCTION("IF(L85="""","""", REGEXEXTRACT(REGEXREPLACE(L85,""x"", """"), ""[0-9]+""))"),"160970247") -> 160970247 | N85: =IF(LEFT(M85,3)="353", RIGHT(M85,LEN(M85)-3),M85) -> 160970247 | O85: =IFERROR(__xludf.DUMMYFUNCTION("REGEXMATCH(TO_TEXT(N85), ""^0(83|85|86|87|89)"")"),FALSE) -> FALSE | P85: =LEN(N85) -> 9 | Q85: =IF(AND(O85=TRUE, P82=10), "✅ VALID", "❌ INVALID") -> ❌ INVALID | R85: Ireland | S85: 45548 | T85: =IFERROR(__xludf.DUMMYFUNCTION("IF(ISNUMBER(S85),TEXT(S85,""yyyy-MM-dd""),REGEXREPLACE(REGEXREPLACE(TO_TEXT(S85),""[^0-9a-zA-Z]+"",""-""),""[^0-9]*$"",""""))"),"2024-09-13") -> 2024-09-13 | U85: 2024-09-13 | Y85: 2024-09-13
A86: CUST-5084 | B86: ✅ Unique | C86: Ethan Lee | D86: =IFERROR(__xludf.DUMMYFUNCTION("PROPER(REGEXREPLACE(TRIM(C86),""\s+"","" ""))"),"Ethan Lee") -> Ethan Lee | E86: =IFERROR(__xludf.DUMMYFUNCTION("IF(LEN(D86:D701), COUNTA(SPLIT(D86:D701,"" "")), """")"),2.0) -> 2 | F86: =IF(D86=G86,"✅","❌") -> ✅ | G86: =IFERROR(__xludf.DUMMYFUNCTION("REGEXEXTRACT(PROPER(SUBSTITUTE(TRIM(I86),""."","" "")),""^[^@]+"")"),"Ethan Lee") -> Ethan Lee | H86: =LOWER(TRIM(I86)) -> ethan.lee@outlook.com | I86: ethan.lee@outlook.com | J86: =IFERROR(__xludf.DUMMYFUNCTION("IF(REGEXMATCH(TRIM(I86),""^[A-Za-z0-9._%+-]+@[A-Za-z0-9.-]+\.[A-Za-z]{2,}$""),""✅ Valid"",""❌ Invalid"")"),"✅ Valid") -> ✅ Valid | K86: +491630739937 ext 55 | L86: =IFERROR(__xludf.DUMMYFUNCTION("IF(OR(K86=""N/A"", K86=""missing"", K86=""none""), """", REGEXREPLACE( SUBSTITUTE(SUBSTITUTE(SUBSTITUTE(TO_TEXT(K86), CHAR(160),""""), UNICHAR(8239),""""), UNICHAR(8201),""""),""[+\-/(): )]"", """"))"),"491630739937ext55") -> 491630739937ext55 | M86: =IFERROR(__xludf.DUMMYFUNCTION("IF(L86="""","""", REGEXEXTRACT(REGEXREPLACE(L86,""x"", """"), ""[0-9]+""))"),"491630739937") -> 491630739937 | N86: =IF(LEFT(M86,2)="49", RIGHT(M86,LEN(M86)-2),M86) -> 1630739937 | O86: =IFERROR(__xludf.DUMMYFUNCTION("REGEXMATCH(TO_TEXT(N86), ""^0(15|16|17)"")"),FALSE) -> FALSE | P86: =LEN(N86) -> 10 | Q86: =IF(AND(O86=TRUE,OR(P86=10, P86=11)), "✅ VALID", "❌ INVALID") -> ❌ INVALID | R86: Germany | S86: 08/20/2024 18:04 | T86: =IFERROR(__xludf.DUMMYFUNCTION("IF(ISNUMBER(S86),TEXT(S86,""yyyy-MM-dd""),REGEXREPLACE(REGEXREPLACE(TO_TEXT(S86),""[^0-9a-zA-Z]+"",""-""),""[^0-9]*$"",""""))"),"08-20-2024-18-04") -> 08-20-2024-18-04 | U86: =TEXT(T86,"yyyy-MM-dd") -> 08-20-2024-18-04 | V86: =IFERROR(__xludf.DUMMYFUNCTION("REGEXEXTRACT(U86,""^\d{2}-\d{2}-\d{4}"")"),"08-20-2024") -> 08-20-2024 | W86: =TEXT(V86,"yyyy-MM-dd") -> 08-20-2024 | X86: 2024-08-20 | Y86: 2024-08-20
A87: CUST-5085 | B87: ✅ Unique | C87: Marek Rossi | D87: =IFERROR(__xludf.DUMMYFUNCTION("PROPER(REGEXREPLACE(TRIM(C87),""\s+"","" ""))"),"Marek Rossi") -> Marek Rossi | E87: =IFERROR(__xludf.DUMMYFUNCTION("IF(LEN(D87:D701), COUNTA(SPLIT(D87:D701,"" "")), """")"),2.0) -> 2 | F87: =IF(D87=G87,"✅","❌") -> ✅ | G87: =IFERROR(__xludf.DUMMYFUNCTION("REGEXEXTRACT(PROPER(SUBSTITUTE(TRIM(I87),""."","" "")),""^[^@]+"")"),"Marek Rossi") -> Marek Rossi | H87: =LOWER(TRIM(I87)) -> marek.rossi@yahoo.com | I87: marek.rossi@yahoo.com | J87: =IFERROR(__xludf.DUMMYFUNCTION("IF(REGEXMATCH(TRIM(I87),""^[A-Za-z0-9._%+-]+@[A-Za-z0-9.-]+\.[A-Za-z]{2,}$""),""✅ Valid"",""❌ Invalid"")"),"✅ Valid") -> ✅ Valid | K87: +492549422094 | L87: =IFERROR(__xludf.DUMMYFUNCTION("IF(OR(K87=""N/A"", K87=""missing"", K87=""none""), """", REGEXREPLACE( SUBSTITUTE(SUBSTITUTE(SUBSTITUTE(TO_TEXT(K87), CHAR(160),""""), UNICHAR(8239),""""), UNICHAR(8201),""""),""[+\-/(): )]"", """"))"),"492549422094") -> 492549422094 | M87: =IFERROR(__xludf.DUMMYFUNCTION("IF(L87="""","""", REGEXEXTRACT(REGEXREPLACE(L87,""x"", """"), ""[0-9]+""))"),"492549422094") -> 492549422094 | N87: =IF(LEFT(M87,2)="49", RIGHT(M87,LEN(M87)-2),M87) -> 2549422094 | O87: =IFERROR(__xludf.DUMMYFUNCTION("REGEXMATCH(TO_TEXT(N87), ""^0(15|16|17)"")"),FALSE) -> FALSE | P87: =LEN(N87) -> 10 | Q87: =IF(AND(O87=TRUE,OR(P87=10, P87=11)), "✅ VALID", "❌ INVALID") -> ❌ INVALID | R87: Germany | S87: 45137 12:40 | T87: =IFERROR(__xludf.DUMMYFUNCTION("IF(ISNUMBER(S87),TEXT(S87,""yyyy-MM-dd""),REGEXREPLACE(REGEXREPLACE(TO_TEXT(S87),""[^0-9a-zA-Z]+"",""-""),""[^0-9]*$"",""""))"),"45137-12-40") -> 45137-12-40 | U87: =TEXT(T87,"yyyy-MM-dd") -> 45137-12-40 | V87: =CONCATENATE(LEFT(U87,5)) -> 45137 | W87: =DATE(1900,1,1) + V87 - 1 -> 45138 | X87: 2023-07-31 | Y87: 2023-07-31
A88: CUST-5086 | B88: ✅ Unique | C88: Xenia Lopze | D88: Xenia Lopez | E88: =IFERROR(__xludf.DUMMYFUNCTION("IF(LEN(D88:D701), COUNTA(SPLIT(D88:D701,"" "")), """")"),2.0) -> 2 | F88: =IF(D88=G88,"✅","❌") -> ✅ | G88: Xenia Lopez | H88: =LOWER(TRIM(I88)) -> xenia.lopez@yahoo.com | I88: xenia.lopez@yahoo.com | J88: =IFERROR(__xludf.DUMMYFUNCTION("IF(REGEXMATCH(TRIM(I88),""^[A-Za-z0-9._%+-]+@[A-Za-z0-9.-]+\.[A-Za-z]{2,}$""),""✅ Valid"",""❌ Invalid"")"),"✅ Valid") -> ✅ Valid | K88: +492195087085 | L88: =IFERROR(__xludf.DUMMYFUNCTION("IF(OR(K88=""N/A"", K88=""missing"", K88=""none""), """", REGEXREPLACE( SUBSTITUTE(SUBSTITUTE(SUBSTITUTE(TO_TEXT(K88), CHAR(160),""""), UNICHAR(8239),""""), UNICHAR(8201),""""),""[+\-/(): )]"", """"))"),"492195087085") -> 492195087085 | M88: =IFERROR(__xludf.DUMMYFUNCTION("IF(L88="""","""", REGEXEXTRACT(REGEXREPLACE(L88,""x"", """"), ""[0-9]+""))"),"492195087085") -> 492195087085 | N88: =IF(LEFT(M88,2)="49", RIGHT(M88,LEN(M88)-2),M88) -> 2195087085 | O88: =IFERROR(__xludf.DUMMYFUNCTION("REGEXMATCH(TO_TEXT(N88), ""^0(15|16|17)"")"),FALSE) -> FALSE | P88: =LEN(N88) -> 10 | Q88: =IF(AND(O88=TRUE,OR(P88=10, P88=11)), "✅ VALID", "❌ INVALID") -> ❌ INVALID | R88: Germany | S88: 44692 | T88: =IFERROR(__xludf.DUMMYFUNCTION("IF(ISNUMBER(S88),TEXT(S88,""yyyy-MM-dd""),REGEXREPLACE(REGEXREPLACE(TO_TEXT(S88),""[^0-9a-zA-Z]+"",""-""),""[^0-9]*$"",""""))"),"2022-05-11") -> 2022-05-11 | U88: 2022-05-11 | Y88: 2022-05-11
A89: CUST-5087 | B89: ✅ Unique | C89: Omar Dubois | D89: =IFERROR(__xludf.DUMMYFUNCTION("PROPER(REGEXREPLACE(TRIM(C89),""\s+"","" ""))"),"Omar Dubois") -> Omar Dubois | E89: =IFERROR(__xludf.DUMMYFUNCTION("IF(LEN(D89:D701), COUNTA(SPLIT(D89:D701,"" "")), """")"),2.0) -> 2 | F89: =IF(D89=G89,"✅","❌") -> ✅ | G89: =IFERROR(__xludf.DUMMYFUNCTION("REGEXEXTRACT(PROPER(SUBSTITUTE(TRIM(I89),""."","" "")),""^[^@]+"")"),"Omar Dubois") -> Omar Dubois | H89: =LOWER(TRIM(I89)) -> omar.dubois@gmai.lcom | I89: OMAR.DUBOIS@GMAI.LCOM | J89: =IFERROR(__xludf.DUMMYFUNCTION("IF(REGEXMATCH(TRIM(I89),""^[A-Za-z0-9._%+-]+@[A-Za-z0-9.-]+\.[A-Za-z]{2,}$""),""✅ Valid"",""❌ Invalid"")"),"✅ Valid") -> ✅ Valid | K89: 69991x79 | L89: =IFERROR(__xludf.DUMMYFUNCTION("IF(OR(K89=""N/A"", K89=""missing"", K89=""none""), """", REGEXREPLACE( SUBSTITUTE(SUBSTITUTE(SUBSTITUTE(TO_TEXT(K89), CHAR(160),""""), UNICHAR(8239),""""), UNICHAR(8201),""""),""[+\-/(): )]"", """"))"),"69991x79") -> 69991x79 | M89: =IFERROR(__xludf.DUMMYFUNCTION("IF(L89="""","""", REGEXEXTRACT(REGEXREPLACE(L89,""x"", """"), ""[0-9]+""))"),"6999179") -> 6999179 | N89: =IF(LEFT(M89,3)="353", RIGHT(M89,LEN(M89)-3),M89) -> 6999179 | O89: =IFERROR(__xludf.DUMMYFUNCTION("REGEXMATCH(TO_TEXT(N89), ""^0(83|85|86|87|89)"")"),FALSE) -> FALSE | P89: =LEN(N89) -> 7 | Q89: =IF(AND(O89=TRUE, P86=10), "✅ VALID", "❌ INVALID") -> ❌ INVALID | R89: Ireland | S89: 13.03.2024 | T89: =IFERROR(__xludf.DUMMYFUNCTION("IF(ISNUMBER(S89),TEXT(S89,""yyyy-MM-dd""),REGEXREPLACE(REGEXREPLACE(TO_TEXT(S89),""[^0-9a-zA-Z]+"",""-""),""[^0-9]*$"",""""))"),"13-03-2024") -> 13-03-2024 | U89: 2024-03-13 | Y89: 2024-03-13
A90: CUST-5088 | B90: ✅ Unique | C90: KEN WILLIMAS | D90: Ken Williams | E90: =IFERROR(__xludf.DUMMYFUNCTION("IF(LEN(D90:D701), COUNTA(SPLIT(D90:D701,"" "")), """")"),2.0) -> 2 | F90: =IF(D90=G90,"✅","❌") -> ✅ | G90: Ken Williams | H90: =LOWER(TRIM(I90)) -> ken.williams@yahoo.com | I90: ken.williams@yahoo.com | J90: =IFERROR(__xludf.DUMMYFUNCTION("IF(REGEXMATCH(TRIM(I90),""^[A-Za-z0-9._%+-]+@[A-Za-z0-9.-]+\.[A-Za-z]{2,}$""),""✅ Valid"",""❌ Invalid"")"),"✅ Valid") -> ✅ Valid | K90: 3363212435 | L90: =IFERROR(__xludf.DUMMYFUNCTION("IF(OR(K90=""N/A"", K90=""missing"", K90=""none""), """", REGEXREPLACE( SUBSTITUTE(SUBSTITUTE(SUBSTITUTE(TO_TEXT(K90), CHAR(160),""""), UNICHAR(8239),""""), UNICHAR(8201),""""),""[+\-/(): )]"", """"))"),"3363212435") -> 3363212435 | M90: =IFERROR(__xludf.DUMMYFUNCTION("IF(L90="""","""", REGEXEXTRACT(REGEXREPLACE(L90,""x"", """"), ""[0-9]+""))"),"3363212435") -> 3363212435 | N90: =IF(LEFT(M90,2)="33", RIGHT(M90,LEN(M90)-2),M90) -> 63212435 | O90: =IFERROR(__xludf.DUMMYFUNCTION("REGEXMATCH(TO_TEXT(N90), ""^0[67]"")"),FALSE) -> FALSE | P90: =LEN(N90) -> 8 | Q90: =IF(AND(O90=TRUE, P90=9), "✅ VALID", "❌ INVALID") -> ❌ INVALID | R90: France | S90: 30.06.2024 | T90: =IFERROR(__xludf.DUMMYFUNCTION("IF(ISNUMBER(S90),TEXT(S90,""yyyy-MM-dd""),REGEXREPLACE(REGEXREPLACE(TO_TEXT(S90),""[^0-9a-zA-Z]+"",""-""),""[^0-9]*$"",""""))"),"30-06-2024") -> 30-06-2024 | U90: 2024-06-30 | Y90: 2024-06-30
A91: CUST-5089 | B91: ✅ Unique | C91: Paula Khan | D91: =IFERROR(__xludf.DUMMYFUNCTION("PROPER(REGEXREPLACE(TRIM(C91),""\s+"","" ""))"),"Paula Khan") -> Paula Khan | E91: =IFERROR(__xludf.DUMMYFUNCTION("IF(LEN(D91:D701), COUNTA(SPLIT(D91:D701,"" "")), """")"),2.0) -> 2 | F91: =IF(D91=G91,"✅","❌") -> ✅ | G91: =IFERROR(__xludf.DUMMYFUNCTION("REGEXEXTRACT(PROPER(SUBSTITUTE(TRIM(I91),""."","" "")),""^[^@]+"")"),"Paula Khan") -> Paula Khan | H91: =LOWER(TRIM(I91)) -> paula.khan@gmail.com | I91: paula.khan@gmail.com | J91: =IFERROR(__xludf.DUMMYFUNCTION("IF(REGEXMATCH(TRIM(I91),""^[A-Za-z0-9._%+-]+@[A-Za-z0-9.-]+\.[A-Za-z]{2,}$""),""✅ Valid"",""❌ Invalid"")"),"✅ Valid") -> ✅ Valid | K91: tel:+33031729349 | L91: =IFERROR(__xludf.DUMMYFUNCTION("IF(OR(K91=""N/A"", K91=""missing"", K91=""none""), """", REGEXREPLACE( SUBSTITUTE(SUBSTITUTE(SUBSTITUTE(TO_TEXT(K91), CHAR(160),""""), UNICHAR(8239),""""), UNICHAR(8201),""""),""[+\-/(): )]"", """"))"),"tel33031729349") -> tel33031729349 | M91: =IFERROR(__xludf.DUMMYFUNCTION("IF(L91="""","""", REGEXEXTRACT(REGEXREPLACE(L91,""x"", """"), ""[0-9]+""))"),"33031729349") -> 33031729349 | N91: =IF(LEFT(M91,2)="33", RIGHT(M91,LEN(M91)-2),M91) -> 031729349 | O91: =IFERROR(__xludf.DUMMYFUNCTION("REGEXMATCH(TO_TEXT(N91), ""^0[67]"")"),FALSE) -> FALSE | P91: =LEN(N91) -> 9 | Q91: =IF(AND(O91=TRUE, P91=9), "✅ VALID", "❌ INVALID") -> ❌ INVALID | R91: France | S91: 45551 | T91: =IFERROR(__xludf.DUMMYFUNCTION("IF(ISNUMBER(S91),TEXT(S91,""yyyy-MM-dd""),REGEXREPLACE(REGEXREPLACE(TO_TEXT(S91),""[^0-9a-zA-Z]+"",""-""),""[^0-9]*$"",""""))"),"2024-09-16") -> 2024-09-16 | U91: 2024-09-16 | Y91: 2024-09-16
A92: CUST-5090 | B92: ✅ Unique | C92: Ken King | D92: =IFERROR(__xludf.DUMMYFUNCTION("PROPER(REGEXREPLACE(TRIM(C92),""\s+"","" ""))"),"Ken King") -> Ken King | E92: =IFERROR(__xludf.DUMMYFUNCTION("IF(LEN(D92:D701), COUNTA(SPLIT(D92:D701,"" "")), """")"),2.0) -> 2 | F92: =IF(D92=G92,"✅","❌") -> ✅ | G92: =IFERROR(__xludf.DUMMYFUNCTION("REGEXEXTRACT(PROPER(SUBSTITUTE(TRIM(I92),""."","" "")),""^[^@]+"")"),"Ken King") -> Ken King | H92: =LOWER(TRIM(I92)) -> ken.king@outlook.com | I92: ken.king@outlook.com | J92: =IFERROR(__xludf.DUMMYFUNCTION("IF(REGEXMATCH(TRIM(I92),""^[A-Za-z0-9._%+-]+@[A-Za-z0-9.-]+\.[A-Za-z]{2,}$""),""✅ Valid"",""❌ Invalid"")"),"✅ Valid") -> ✅ Valid | K92: 70137x7540 | L92: =IFERROR(__xludf.DUMMYFUNCTION("IF(OR(K92=""N/A"", K92=""missing"", K92=""none""), """", REGEXREPLACE( SUBSTITUTE(SUBSTITUTE(SUBSTITUTE(TO_TEXT(K92), CHAR(160),""""), UNICHAR(8239),""""), UNICHAR(8201),""""),""[+\-/(): )]"", """"))"),"70137x7540") -> 70137x7540 | M92: =IFERROR(__xludf.DUMMYFUNCTION("IF(L92="""","""", REGEXEXTRACT(REGEXREPLACE(L92,""x"", """"), ""[0-9]+""))"),"701377540") -> 701377540 | N92: =IF(LEFT(M92,2)="49", RIGHT(M92,LEN(M92)-2),M92) -> 701377540 | O92: =IFERROR(__xludf.DUMMYFUNCTION("REGEXMATCH(TO_TEXT(N92), ""^0(15|16|17)"")"),FALSE) -> FALSE | P92: =LEN(N92) -> 9 | Q92: =IF(AND(O92=TRUE,OR(P92=10, P92=11)), "✅ VALID", "❌ INVALID") -> ❌ INVALID | R92: Germany | S92: 45208.74 | T92: =IFERROR(__xludf.DUMMYFUNCTION("IF(ISNUMBER(S92),TEXT(S92,""yyyy-MM-dd""),REGEXREPLACE(REGEXREPLACE(TO_TEXT(S92),""[^0-9a-zA-Z]+"",""-""),""[^0-9]*$"",""""))"),"2023-10-09") -> 2023-10-09 | U92: 2023-10-09 | Y92: 2023-10-09
A93: CUST-5091 | B93: ✅ Unique | C93: Marek Garcia | D93: =IFERROR(__xludf.DUMMYFUNCTION("PROPER(REGEXREPLACE(TRIM(C93),""\s+"","" ""))"),"Marek Garcia") -> Marek Garcia | E93: =IFERROR(__xludf.DUMMYFUNCTION("IF(LEN(D93:D701), COUNTA(SPLIT(D93:D701,"" "")), """")"),2.0) -> 2 | F93: =IF(D93=G93,"✅","❌") -> ✅ | G93: =IFERROR(__xludf.DUMMYFUNCTION("REGEXEXTRACT(PROPER(SUBSTITUTE(TRIM(I93),""."","" "")),""^[^@]+"")"),"Marek Garcia") -> Marek Garcia | H93: =LOWER(TRIM(I93)) -> marek.garcia@company.co.uk | I93: marek.garcia@company.co.uk | J93: =IFERROR(__xludf.DUMMYFUNCTION("IF(REGEXMATCH(TRIM(I93),""^[A-Za-z0-9._%+-]+@[A-Za-z0-9.-]+\.[A-Za-z]{2,}$""),""✅ Valid"",""❌ Invalid"")"),"✅ Valid") -> ✅ Valid | K93: +49 375 9898347 | L93: =IFERROR(__xludf.DUMMYFUNCTION("IF(OR(K93=""N/A"", K93=""missing"", K93=""none""), """", REGEXREPLACE( SUBSTITUTE(SUBSTITUTE(SUBSTITUTE(TO_TEXT(K93), CHAR(160),""""), UNICHAR(8239),""""), UNICHAR(8201),""""),""[+\-/(): )]"", """"))"),"493759898347") -> 493759898347 | M93: =IFERROR(__xludf.DUMMYFUNCTION("IF(L93="""","""", REGEXEXTRACT(REGEXREPLACE(L93,""x"", """"), ""[0-9]+""))"),"493759898347") -> 493759898347 | N93: =IF(LEFT(M93,2)="49", RIGHT(M93,LEN(M93)-2),M93) -> 3759898347 | O93: =IFERROR(__xludf.DUMMYFUNCTION("REGEXMATCH(TO_TEXT(N93), ""^0(15|16|17)"")"),FALSE) -> FALSE | P93: =LEN(N93) -> 10 | Q93: =IF(AND(O93=TRUE,OR(P93=10, P93=11)), "✅ VALID", "❌ INVALID") -> ❌ INVALID | R93: Germany | S93: 45049 | T93: =IFERROR(__xludf.DUMMYFUNCTION("IF(ISNUMBER(S93),TEXT(S93,""yyyy-MM-dd""),REGEXREPLACE(REGEXREPLACE(TO_TEXT(S93),""[^0-9a-zA-Z]+"",""-""),""[^0-9]*$"",""""))"),"2023-05-03") -> 2023-05-03 | U93: 2023-05-03 | Y93: 2023-05-03
